Workbook

Sheet Dashboard
B2: TRUMP TRACKER DASHBOARD
C3: unbiased, raw housing data. Updated every morning at 9:15 EST
B5: Supply | D5: Affordability Score (1-100) | F5: Crash Likelihood (1-100)
B6: ='TRUMP TRACKER'!Q21 -> 46.898679 | D6: ='TRUMP TRACKER'!Q22 -> 45.568 | F6: ='TRUMP TRACKER'!Q23 -> 45.75
B7: ='TRUMP TRACKER'!R21 -> 🟠 Tight Market | D7: ='TRUMP TRACKER'!R22 -> 🟠 Very Strained | F7: ='TRUMP TRACKER'!R23 -> 🟢 Nowhere Close
B8: higher = better | D8: higher = better | F8: higher = closer
D11: Housing Health Score
D12: ='TRUMP TRACKER'!Q28 -> 50.14236
D13: ='TRUMP TRACKER'!R28 -> 🔴 Affordability Crisis
B16: Supply Score Breakdown | C16: We take the current supply of homes and compare it to a | E16: 🟢 Balanced (90–100)
C17: national target. The result is scaled from 0 to 100 | E17: 🟡 Slight Undersupply (70–89.9)
C18: based on how close we are to needed home inventory. | E18: 🟠 Tight Market (45–69.9)
C19: (note: formula favors AFFORDABLE housing in scoring) | E19: 🔴 Critical Shortage (<45)
B23: Affordability Score Breakdown | C23: First-Time Buyer Affordability (max 40 pts) | E23: 🟢 Affordable (80–100)
C24: National Affordability Index (20 pts) | E24: 🟡 Pressured (60–79.9)
C25: Mortgage Rate (15 pts) | E25: 🟠 Strained (40–59.9)
C26: 10-Year Treasury (7.5 pts) | E26: 🔴 Meltdown (<40)
C27: Median Household Income (17.5 pts)
B31: Crash Score Breakdown | C31: We total all macroeconomic pressure points using a fluid | E31: 🔴 MELTDOWN (100–135)
C32: scoring formulas from 15 leading indicators | E32: 🟠 Crash in Sight (80–99.9)
C33: (e.g., delinquencies, vacancies, job market, yield curve). | E33: 🟡 Correction in Sight (70–79.9)
C34: all variables can be seen at A30 on TrumpTracker tab. | E34: 🟢 Buyer’s Market (45–69.9)
E35: 🟢 Strong Seller’s Market (<45)
B39: Housing Health Score Breakdown | E39: 🟢 Affordable Housing (85–100)
C40: 45% if the Affordability score | E40: 🟡 Buyer’s Market (72.5–84.9)
C41: 35% of the Supply score | E41: 🟠 Neutral Market (60–72.4)
C42: 20% of the Inverted Crash score | E42: 🔴 Affordability Crisis (50–59.9)
E43: 🔴 Nowhere Close to Affordable (40–49.9)
E44: 🔥 Crisis Mode (<40)

Sheet TRUMP TRACKER
A1: T.R.U.M.P. Tracker | G1: 21 | I1: HOUSING METRICS | P1: COST TRACKERS | T1: LAST UPDATED: 12/8/2025 01:03 PM EST | U1: LAST UPDATED: 1/7/2026 09:26 AM EST | AC1: =( (K23/J23)*0.5 + (K22/J22)*0.25 + (K24/J24)*0.15 + (K21/J21)*0.1 ) -> 0.51898679
A2: unbiased, raw housing data. Updated DAILY at 9:15 AM Est | I2: KPI | J2: Target | K2: Current | L2: Start | M2: % | N2: Total Change | P2: Builder Expenses | Q2: Current | R2: Start | S2: % | T2: Total Change | W2: Household Expenses pt 2 | X2: Current | Y2: Start | Z2: % | AA2: Total Change
A3: Housing Health Index | I3: Resale Home (Median $) | J3: 385000 | K3: 409200 | L3: 393400 | M3: =(K3 - L3) / L3 -> 0.040162684 | N3: =(K3-L3) -> 15800 | P3: Softwood Lumber | Q3: 252.735 | R3: 267.54 | S3: =(Q3 - R3) / R3 -> -0.05533752 | T3: =IF(OR(Q3="", R3=""), "", Q3 - R3) -> -14.805 | U3: =IF(OR(Q3="", R3="", R3=0), "", IF((Q3 - R3)/R3 >= 0.1, "⬆️⬆️ MAJOR Rise", IF((Q3 - R3)/R3 >= 0.01, "⬆️ Rise", IF((Q3 - R3)/R3 <= -0.1, "⬇️⬇️ MAJOR Drop", IF((Q3 - R3)/R3 <= -0.01, "⬇️ Drop", "Stable"))))) -> ⬇️ Drop | W3: Food Overall | X3: 342.262 | Y3: 335.67 | Z3: =(X3 - Y3) / Y3 -> 0.019638335 | AA3: =IF(OR(X3="", Y3=""), "", X3 - Y3) -> 6.592 | AB3: =IF(OR(X3="", Y3="", Y3=0), "", IF((X3 - Y3)/Y3 >= 0.1, "⬆️⬆️ MAJOR Rise", IF((X3 - Y3)/Y3 >= 0.01, "⬆️ Rise", IF((X3 - Y3)/Y3 <= -0.1, "⬇️⬇️ MAJOR Drop", IF((X3 - Y3)/Y3 <= -0.01, "⬇️ Drop", "Stable"))))) -> ⬆️ Rise
A4: Today | B4: =(Q22 * 0.45) + (Q21 * 0.35) + ((135 - Q23) / 135 * 100) * 0.2 -> 50.14236 | C4: 🔴 Nowhere close to affordable | I4: New Construction (Median $) | J4: 401800 | K4: 413500 | L4: 427900 | M4: =(K4 - L4) / L4 -> -0.033652723 | N4: =(K4-L4) -> -14400 | P4: Steel | Q4: 143.246 | R4: 131.69 | S4: =(Q4 - R4) / R4 -> 0.087751538 | T4: =IF(OR(Q4="", R4=""), "", Q4 - R4) -> 11.556 | U4: =IF(OR(Q4="", R4="", R4=0), "", IF((Q4 - R4)/R4 >= 0.1, "⬆️⬆️ MAJOR Rise", IF((Q4 - R4)/R4 >= 0.01, "⬆️ Rise", IF((Q4 - R4)/R4 <= -0.1, "⬇️⬇️ MAJOR Drop", IF((Q4 - R4)/R4 <= -0.01, "⬇️ Drop", "Stable"))))) -> ⬆️ Rise | W4: Doors/Windows | X4: 473.057 | Y4: 429.67 | Z4: =(X4 - Y4) / Y4 -> 0.10097749 | AA4: =IF(OR(X4="", Y4=""), "", X4 - Y4) -> 43.387 | AB4: =IF(OR(X4="", Y4="", Y4=0), "", IF((X4 - Y4)/Y4 >= 0.1, "⬆️⬆️ MAJOR Rise", IF((X4 - Y4)/Y4 >= 0.01, "⬆️ Rise", IF((X4 - Y4)/Y4 <= -0.1, "⬇️⬇️ MAJOR Drop", IF((X4 - Y4)/Y4 <= -0.01, "⬇️ Drop", "Stable"))))) -> ⬆️⬆️ MAJOR Rise
A5: 90 Day | B5: code in repair | C5: code in repair | I5: Affordable Home (Median $) | J5: 310000 | K5: 362800 | L5: 348600 | M5: =(K5 - L5) / L5 -> 0.040734366 | N5: =(K5-L5) -> 14200 | P5: Shingles | Q5: 369.258 | R5: 359.22 | S5: =(Q5 - R5) / R5 -> 0.027943878 | T5: =IF(OR(Q5="", R5=""), "", Q5 - R5) -> 10.038 | U5: =IF(OR(Q5="", R5="", R5=0), "", IF((Q5 - R5)/R5 >= 0.1, "⬆️⬆️ MAJOR Rise", IF((Q5 - R5)/R5 >= 0.01, "⬆️ Rise", IF((Q5 - R5)/R5 <= -0.1, "⬇️⬇️ MAJOR Drop", IF((Q5 - R5)/R5 <= -0.01, "⬇️ Drop", "Stable"))))) -> ⬆️ Rise | W5: HVAC System | X5: 233.063 | Y5: 222.5 | Z5: =(X5 - Y5) / Y5 -> 0.047474157 | AA5: =IF(OR(X5="", Y5=""), "", X5 - Y5) -> 10.563 | AB5: =IF(OR(X5="", Y5="", Y5=0), "", IF((X5 - Y5)/Y5 >= 0.1, "⬆️⬆️ MAJOR Rise", IF((X5 - Y5)/Y5 >= 0.01, "⬆️ Rise", IF((X5 - Y5)/Y5 <= -0.1, "⬇️⬇️ MAJOR Drop", IF((X5 - Y5)/Y5 <= -0.01, "⬇️ Drop", "Stable"))))) -> ⬆️ Rise
A6: 1 Year | B6: code in repair | C6: code in repair | P6: Plumbing | Q6: 463.869 | R6: 421.34 | S6: =(Q6 - R6) / R6 -> 0.10093749 | T6: =IF(OR(Q6="", R6=""), "", Q6 - R6) -> 42.529 | U6: =IF(OR(Q6="", R6="", R6=0), "", IF((Q6 - R6)/R6 >= 0.1, "⬆️⬆️ MAJOR Rise", IF((Q6 - R6)/R6 >= 0.01, "⬆️ Rise", IF((Q6 - R6)/R6 <= -0.1, "⬇️⬇️ MAJOR Drop", IF((Q6 - R6)/R6 <= -0.01, "⬇️ Drop", "Stable"))))) -> ⬆️⬆️ MAJOR Rise | W6: Fridge | X6: 134.751 | Y6: 132.62 | Z6: =(X6 - Y6) / Y6 -> 0.016068466 | AA6: =IF(OR(X6="", Y6=""), "", X6 - Y6) -> 2.131 | AB6: =IF(OR(X6="", Y6="", Y6=0), "", IF((X6 - Y6)/Y6 >= 0.1, "⬆️⬆️ MAJOR Rise", IF((X6 - Y6)/Y6 >= 0.01, "⬆️ Rise", IF((X6 - Y6)/Y6 <= -0.1, "⬇️⬇️ MAJOR Drop", IF((X6 - Y6)/Y6 <= -0.01, "⬇️ Drop", "Stable"))))) -> ⬆️ Rise
A7: 5 Year | B7: code in repair | C7: code in repair | P7: Concrete | Q7: 252.99 | R7: 251.22 | S7: =(Q7 - R7) / R7 -> 0.0070456174 | T7: =IF(OR(Q7="", R7=""), "", Q7 - R7) -> 1.77 | U7: =IF(OR(Q7="", R7="", R7=0), "", IF((Q7 - R7)/R7 >= 0.1, "⬆️⬆️ MAJOR Rise", IF((Q7 - R7)/R7 >= 0.01, "⬆️ Rise", IF((Q7 - R7)/R7 <= -0.1, "⬇️⬇️ MAJOR Drop", IF((Q7 - R7)/R7 <= -0.01, "⬇️ Drop", "Stable"))))) -> Stable | W7: Water Heater | X7: 641.381 | Y7: 591.49 | Z7: =(X7 - Y7) / Y7 -> 0.084348003 | AA7: =IF(OR(X7="", Y7=""), "", X7 - Y7) -> 49.891 | AB7: =IF(OR(X7="", Y7="", Y7=0), "", IF((X7 - Y7)/Y7 >= 0.1, "⬆️⬆️ MAJOR Rise", IF((X7 - Y7)/Y7 >= 0.01, "⬆️ Rise", IF((X7 - Y7)/Y7 <= -0.1, "⬇️⬇️ MAJOR Drop", IF((X7 - Y7)/Y7 <= -0.01, "⬇️ Drop", "Stable"))))) -> ⬆️ Rise
I8: MORTGAGE | P8: Household Expenses pt 1 | W8: Household Expenses pt 3
A9: Bill Tracker | I9: Mortgage Rate | J9: 0.0672 | K9: 0.0615 | L9: 0.0707 | M9: =(K9 - L9) / L9 -> -0.1301273 | N9: =(K9-L9)*100 -> -0.92 | P9: Power (per KWH) | Q9: 0.189 | R9: 0.179 | S9: =(Q9 - R9) / R9 -> 0.055865922 | T9: =IF(OR(Q9="", R9=""), "", Q9 - R9) -> 0.01 | U9: =IF(OR(Q9="", R9="", R9=0), "", IF((Q9 - R9)/R9 >= 0.1, "⬆️⬆️ MAJOR Rise", IF((Q9 - R9)/R9 >= 0.01, "⬆️ Rise", IF((Q9 - R9)/R9 <= -0.1, "⬇️⬇️ MAJOR Drop", IF((Q9 - R9)/R9 <= -0.01, "⬇️ Drop", "Stable"))))) -> ⬆️ Rise | W9: Beef | X9: 6.54 | Y9: 5.54 | Z9: =(X9 - Y9) / Y9 -> 0.18050542 | AA9: =IF(OR(X9="", Y9=""), "", X9 - Y9) -> 1 | AB9: =IF(OR(X9="", Y9="", Y9=0), "", IF((X9 - Y9)/Y9 >= 0.1, "⬆️⬆️ MAJOR Rise", IF((X9 - Y9)/Y9 >= 0.01, "⬆️ Rise", IF((X9 - Y9)/Y9 <= -0.1, "⬇️⬇️ MAJOR Drop", IF((X9 - Y9)/Y9 <= -0.01, "⬇️ Drop", "Stable"))))) -> ⬆️⬆️ MAJOR Rise
A10: Bill # | B10: Name | C10: Status | I10: Fed Rate | J10: 0.0433 | K10: 0.0372 | L10: 0.0433 | M10: =(K10 - L10) / L10 -> -0.1408776 | N10: =(K10-L10)*100 -> -0.61 | P10: Milk | Q10: 3.997 | R10: 4.03 | S10: =(Q10 - R10) / R10 -> -0.0081885856 | T10: =IF(OR(Q10="", R10=""), "", Q10 - R10) -> -0.033 | U10: =IF(OR(Q10="", R10="", R10=0), "", IF((Q10 - R10)/R10 >= 0.1, "⬆️⬆️ MAJOR Rise", IF((Q10 - R10)/R10 >= 0.01, "⬆️ Rise", IF((Q10 - R10)/R10 <= -0.1, "⬇️⬇️ MAJOR Drop", IF((Q10 - R10)/R10 <= -0.01, "⬇️ Drop", "Stable"))))) -> Stable | W10: Coffee | X10: 9.258 | Y10: 7.01 | Z10: =(X10 - Y10) / Y10 -> 0.32068474 | AA10: =IF(OR(X10="", Y10=""), "", X10 - Y10) -> 2.248 | AB10: =IF(OR(X10="", Y10="", Y10=0), "", IF((X10 - Y10)/Y10 >= 0.1, "⬆️⬆️ MAJOR Rise", IF((X10 - Y10)/Y10 >= 0.01, "⬆️ Rise", IF((X10 - Y10)/Y10 <= -0.1, "⬇️⬇️ MAJOR Drop", IF((X10 - Y10)/Y10 <= -0.01, "⬇️ Drop", "Stable"))))) -> ⬆️⬆️ MAJOR Rise
A11: HR 2945 (US) | B11: Housing for All Act | C11: Currently at committee lvl | I11: 10 Year Treasury Yield | J11: 0.0439 | K11: 0.0417 | L11: 0.04623 | M11: =(K11 - L11) / L11 -> -0.097988319 | N11: =(K11-L11)*100 -> -0.453 | P11: Eggs | Q11: 2.86 | R11: 4.95 | S11: =(Q11 - R11) / R11 -> -0.42222222 | T11: =IF(OR(Q11="", R11=""), "", Q11 - R11) -> -2.09 | U11: =IF(OR(Q11="", R11="", R11=0), "", IF((Q11 - R11)/R11 >= 0.1, "⬆️⬆️ MAJOR Rise", IF((Q11 - R11)/R11 >= 0.01, "⬆️ Rise", IF((Q11 - R11)/R11 <= -0.1, "⬇️⬇️ MAJOR Drop", IF((Q11 - R11)/R11 <= -0.01, "⬇️ Drop", "Stable"))))) -> ⬇️⬇️ MAJOR Drop | W11: Car Parts | X11: 186.065 | Y11: 182.98 | Z11: =(X11 - Y11) / Y11 -> 0.016859766 | AA11: =IF(OR(X11="", Y11=""), "", X11 - Y11) -> 3.085 | AB11: =IF(OR(X11="", Y11="", Y11=0), "", IF((X11 - Y11)/Y11 >= 0.1, "⬆️⬆️ MAJOR Rise", IF((X11 - Y11)/Y11 >= 0.01, "⬆️ Rise", IF((X11 - Y11)/Y11 <= -0.1, "⬇️⬇️ MAJOR Drop", IF((X11 - Y11)/Y11 <= -0.01, "⬇️ Drop", "Stable"))))) -> ⬆️ Rise
A12: HR 2725 (US) | B12: Affordable Housing Credit Improvement | C12: "ways & means" committee | I12: Core Inflation Y.O.Y. | J12: 0.03288774 | K12: 0.02951403 | L12: 0.0363 | M12: =(K12 - L12) / L12 -> -0.18694133 | N12: =(K12-L12)*100 -> -0.67859705 | P12: Bread | Q12: 1.79 | R12: 1.93 | S12: =(Q12 - R12) / R12 -> -0.07253886 | T12: =IF(OR(Q12="", R12=""), "", Q12 - R12) -> -0.14 | U12: =IF(OR(Q12="", R12="", R12=0), "", IF((Q12 - R12)/R12 >= 0.1, "⬆️⬆️ MAJOR Rise", IF((Q12 - R12)/R12 >= 0.01, "⬆️ Rise", IF((Q12 - R12)/R12 <= -0.1, "⬇️⬇️ MAJOR Drop", IF((Q12 - R12)/R12 <= -0.01, "⬇️ Drop", "Stable"))))) -> ⬇️ Drop | W12: Childcare/education | X12: 902.001 | Y12: 879.54 | Z12: =(X12 - Y12) / Y12 -> 0.025537213 | AA12: =IF(OR(X12="", Y12=""), "", X12 - Y12) -> 22.461 | AB12: =IF(OR(X12="", Y12="", Y12=0), "", IF((X12 - Y12)/Y12 >= 0.1, "⬆️⬆️ MAJOR Rise", IF((X12 - Y12)/Y12 >= 0.01, "⬆️ Rise", IF((X12 - Y12)/Y12 <= -0.1, "⬇️⬇️ MAJOR Drop", IF((X12 - Y12)/Y12 <= -0.01, "⬇️ Drop", "Stable"))))) -> ⬆️ Rise
A13: SB 79 (california) | B13: Transit - Orented Housing | C13: Senate Finance Committee | I13: Median Mortgage p/month* | J13: 2250 | K13: 2648.75 | L13: 2705 | M13: =(K13 - L13) / L13 -> -0.020794824 | N13: =(K13-L13) -> -56.25 | P13: Boneless Chicken | Q13: 4.15 | R13: 3.97 | S13: =(Q13 - R13) / R13 -> 0.04534005 | T13: =IF(OR(Q13="", R13=""), "", Q13 - R13) -> 0.18 | U13: =IF(OR(Q13="", R13="", R13=0), "", IF((Q13 - R13)/R13 >= 0.1, "⬆️⬆️ MAJOR Rise", IF((Q13 - R13)/R13 >= 0.01, "⬆️ Rise", IF((Q13 - R13)/R13 <= -0.1, "⬇️⬇️ MAJOR Drop", IF((Q13 - R13)/R13 <= -0.01, "⬇️ Drop", "Stable"))))) -> ⬆️ Rise | W13: Clothing | X13: 132.588 | Y13: 128.175 | Z13: =(X13 - Y13) / Y13 -> 0.034429491 | AA13: =IF(OR(X13="", Y13=""), "", X13 - Y13) -> 4.413 | AB13: =IF(OR(X13="", Y13="", Y13=0), "", IF((X13 - Y13)/Y13 >= 0.1, "⬆️⬆️ MAJOR Rise", IF((X13 - Y13)/Y13 >= 0.01, "⬆️ Rise", IF((X13 - Y13)/Y13 <= -0.1, "⬇️⬇️ MAJOR Drop", IF((X13 - Y13)/Y13 <= -0.01, "⬇️ Drop", "Stable"))))) -> ⬆️ Rise
A14: S 934 (US) | B14: Senate Finance Committee | C14: Senate Finance Committee | I14: AFFORDABILITY | P14: Gallon of Gas | Q14: 3.39 | R14: 3.21 | S14: =(Q14 - R14) / R14 -> 0.056074766 | T14: =IF(OR(Q14="", R14=""), "", Q14 - R14) -> 0.18 | U14: =IF(OR(Q14="", R14="", R14=0), "", IF((Q14 - R14)/R14 >= 0.1, "⬆️⬆️ MAJOR Rise", IF((Q14 - R14)/R14 >= 0.01, "⬆️ Rise", IF((Q14 - R14)/R14 <= -0.1, "⬇️⬇️ MAJOR Drop", IF((Q14 - R14)/R14 <= -0.01, "⬇️ Drop", "Stable"))))) -> ⬆️ Rise | W14: Used Car | X14: 186.488 | Y14: 185.43 | Z14: =(X14 - Y14) / Y14 -> 0.0057056571 | AA14: =IF(OR(X14="", Y14=""), "", X14 - Y14) -> 1.058 | AB14: =IF(OR(X14="", Y14="", Y14=0), "", IF((X14 - Y14)/Y14 >= 0.1, "⬆️⬆️ MAJOR Rise", IF((X14 - Y14)/Y14 >= 0.01, "⬆️ Rise", IF((X14 - Y14)/Y14 <= -0.1, "⬇️⬇️ MAJOR Drop", IF((X14 - Y14)/Y14 <= -0.01, "⬇️ Drop", "Stable"))))) -> Stable
A15: HR {tbd} (US) | B15: No tax on home sales act | C15: recently introduced | I15: FTHB Affordability Index | J15: 95 | K15: 64.6 | L15: 66.8 | M15: =(K15 - L15) / L15 -> -0.032934132 | N15: =(K15-L15)/L15 -> -0.032934132 | P15: Home Insurance | Q15: 266.307 | R15: 260.75 | S15: =(Q15 - R15) / R15 -> 0.021311601 | T15: =IF(OR(Q15="", R15=""), "", Q15 - R15) -> 5.557 | U15: =IF(OR(Q15="", R15="", R15=0), "", IF((Q15 - R15)/R15 >= 0.1, "⬆️⬆️ MAJOR Rise", IF((Q15 - R15)/R15 >= 0.01, "⬆️ Rise", IF((Q15 - R15)/R15 <= -0.1, "⬇️⬇️ MAJOR Drop", IF((Q15 - R15)/R15 <= -0.01, "⬇️ Drop", "Stable"))))) -> ⬆️ Rise | W15: Health Insurance | X15: 163.883 | Y15: 160.488 | Z15: =(X15 - Y15) / Y15 -> 0.02115423 | AA15: =IF(OR(X15="", Y15=""), "", X15 - Y15) -> 3.395 | AB15: =IF(OR(X15="", Y15="", Y15=0), "", IF((X15 - Y15)/Y15 >= 0.1, "⬆️⬆️ MAJOR Rise", IF((X15 - Y15)/Y15 >= 0.01, "⬆️ Rise", IF((X15 - Y15)/Y15 <= -0.1, "⬇️⬇️ MAJOR Drop", IF((X15 - Y15)/Y15 <= -0.01, "⬇️ Drop", "Stable"))))) -> ⬆️ Rise
A16: HR 2710 (US) | B16: People over parking act | C16: recently introduced | I16: Housing Affordability Index | J16: 125 | K16: 106.2 | L16: 100.7 | M16: =(K16 - L16) / L16 -> 0.054617676 | N16: =(K16-L16)/L16 -> 0.054617676 | P16: Car Insurance | Q16: 222.465 | R16: 218.25 | S16: =(Q16 - R16) / R16 -> 0.019312715 | T16: =IF(OR(Q16="", R16=""), "", Q16 - R16) -> 4.215 | U16: =IF(OR(Q16="", R16="", R16=0), "", IF((Q16 - R16)/R16 >= 0.1, "⬆️⬆️ MAJOR Rise", IF((Q16 - R16)/R16 >= 0.01, "⬆️ Rise", IF((Q16 - R16)/R16 <= -0.1, "⬇️⬇️ MAJOR Drop", IF((Q16 - R16)/R16 <= -0.01, "⬇️ Drop", "Stable"))))) -> ⬆️ Rise | W16: Rent | X16: 438.875 | Y16: 429.017 | Z16: =(X16 - Y16) / Y16 -> 0.02297811 | AA16: =IF(OR(X16="", Y16=""), "", X16 - Y16) -> 9.858 | AB16: =IF(OR(X16="", Y16="", Y16=0), "", IF((X16 - Y16)/Y16 >= 0.1, "⬆️⬆️ MAJOR Rise", IF((X16 - Y16)/Y16 >= 0.01, "⬆️ Rise", IF((X16 - Y16)/Y16 <= -0.1, "⬇️⬇️ MAJOR Drop", IF((X16 - Y16)/Y16 <= -0.01, "⬇️ Drop", "Stable"))))) -> ⬆️ Rise
I17: Median Household Income | J17: 80610 | K17: 83730 | L17: 80610 | M17: =(K17 - L17) / L17 -> 0.038704875 | N17: =(K17-L17) -> 3120 | P17: Medical Care | Q17: 585.611 | R17: 571.234 | S17: =(Q17 - R17) / R17 -> 0.02516832 | T17: =IF(OR(Q17="", R17=""), "", Q17 - R17) -> 14.377 | U17: =IF(OR(Q17="", R17="", R17=0), "", IF((Q17 - R17)/R17 >= 0.1, "⬆️⬆️ MAJOR Rise", IF((Q17 - R17)/R17 >= 0.01, "⬆️ Rise", IF((Q17 - R17)/R17 <= -0.1, "⬇️⬇️ MAJOR Drop", IF((Q17 - R17)/R17 <= -0.01, "⬇️ Drop", "Stable"))))) -> ⬆️ Rise | W17: Natural Gas Heat | X17: 1.639 | Y17: 1.552 | Z17: =(X17 - Y17) / Y17 -> 0.056056701 | AA17: =IF(OR(X17="", Y17=""), "", X17 - Y17) -> 0.087 | AB17: =IF(OR(X17="", Y17="", Y17=0), "", IF((X17 - Y17)/Y17 >= 0.1, "⬆️⬆️ MAJOR Rise", IF((X17 - Y17)/Y17 >= 0.01, "⬆️ Rise", IF((X17 - Y17)/Y17 <= -0.1, "⬇️⬇️ MAJOR Drop", IF((X17 - Y17)/Y17 <= -0.01, "⬇️ Drop", "Stable"))))) -> ⬆️ Rise | AC17: =( (K23/J23)*0.5 + (K22/J22)*0.25 + (K24/J24)*0.15 + (K21/J21)*0.1 ) -> 0.51898679
I18: LEGISLATION | W18: Sewer | X18: 321.363 | Y18: 310.23 | Z18: =(X18 - Y18) / Y18 -> 0.035886278 | AA18: =IF(OR(X18="", Y18=""), "", X18 - Y18) -> 11.133 | AB18: =IF(OR(X18="", Y18="", Y18=0), "", IF((X18 - Y18)/Y18 >= 0.1, "⬆️⬆️ MAJOR Rise", IF((X18 - Y18)/Y18 >= 0.01, "⬆️ Rise", IF((X18 - Y18)/Y18 <= -0.1, "⬇️⬇️ MAJOR Drop", IF((X18 - Y18)/Y18 <= -0.01, "⬇️ Drop", "Stable"))))) -> ⬆️ Rise
A19: Affordability by Region | I19: Bills in Congress** | J19: literally anything | K19: 0 | L19: 3 | N19: =2 -> 2 | P19: THE KEY 3 | R19: the 3 scores below, are weighted and used as an index for the Housing Health Score (P27) | W19: Public Transit Fees | X19: 257.461 | Y19: 264.66 | Z19: =(X19 - Y19) / Y19 -> -0.027200937 | AA19: =IF(OR(X19="", Y19=""), "", X19 - Y19) -> -7.199 | AB19: =IF(OR(X19="", Y19="", Y19=0), "", IF((X19 - Y19)/Y19 >= 0.1, "⬆️⬆️ MAJOR Rise", IF((X19 - Y19)/Y19 >= 0.01, "⬆️ Rise", IF((X19 - Y19)/Y19 <= -0.1, "⬇️⬇️ MAJOR Drop", IF((X19 - Y19)/Y19 <= -0.01, "⬇️ Drop", "Stable"))))) -> ⬇️ Drop
A20: metric | B20: North East | C20: Midwest | D20: South | E20: West | I20: SUPPLY | P20: Variable | Q20: Score | R20: Tier | U20: Monthly Change | W20: Furniture | X20: 154.477 | Y20: 148.3 | Z20: =(X20 - Y20) / Y20 -> 0.041652057 | AA20: =IF(OR(X20="", Y20=""), "", X20 - Y20) -> 6.177 | AB20: =IF(OR(X20="", Y20="", Y20=0), "", IF((X20 - Y20)/Y20 >= 0.1, "⬆️⬆️ MAJOR Rise", IF((X20 - Y20)/Y20 >= 0.01, "⬆️ Rise", IF((X20 - Y20)/Y20 <= -0.1, "⬇️⬇️ MAJOR Drop", IF((X20 - Y20)/Y20 <= -0.01, "⬇️ Drop", "Stable"))))) -> ⬆️ Rise
A21: Resale Home (Median $) | B21: 552100 | C21: 333900 | D21: 371300 | E21: 636600 | I21: Total Homes for Sale | J21: 2502500 | K21: 1072417 | L21: 829376 | M21: =(K21 - L21) / L21 -> 0.29304079 | N21: =(K21-L21) -> 243041 | P21: Supply | Q21: =IFS( AC17>=0.9, 100, AC17>=0.8, (AC17 - 0.8)*190 + 80, AC17>=0.65, (AC17 - 0.65)*126.67 + 60, AC17>=0.45, (AC17 - 0.45)*100 + 40, AC17>=0.3, (AC17 - 0.3)*126.67 + 20, TRUE, AC17*30 + 10 ) -> 46.898679 | R21: =IFS( Q21>=90, "🟢 Balanced", Q21>=70, "🟡 Slight Undersupply", Q21>=45, "🟠 Tight Market", TRUE, "🔴 Critical Shortage" ) -> 🟠 Tight Market | U21: TBD | W21: Cleaning supplies | X21: 236.131 | Y21: 223.265 | Z21: =(X21 - Y21) / Y21 -> 0.057626587 | AA21: =IF(OR(X21="", Y21=""), "", X21 - Y21) -> 12.866 | AB21: =IF(OR(X21="", Y21="", Y21=0), "", IF((X21 - Y21)/Y21 >= 0.1, "⬆️⬆️ MAJOR Rise", IF((X21 - Y21)/Y21 >= 0.01, "⬆️ Rise", IF((X21 - Y21)/Y21 <= -0.1, "⬇️⬇️ MAJOR Drop", IF((X21 - Y21)/Y21 <= -0.01, "⬇️ Drop", "Stable"))))) -> ⬆️ Rise
A22: Median Qualifying Income | B22: 136368 | C22: 82464 | D22: 91728 | E22: 157248 | I22: New Construction for Sale | J22: 550000 | K22: 490000 | L22: 496000 | M22: =(K22 - L22) / L22 -> -0.012096774 | N22: =(K22-L22) -> -6000 | P22: Affordability | Q22: =( IFS( K15>=95, 40, K15>=90, 35 + (K15 - 90) * 1, K15>=85, 30 + (K15 - 85) * 1, K15>=80, 25 + (K15 - 80) * 1, K15>=70, 18 + (K15 - 70) * 0.7, K15>=60, 12 + (K15 - 60) * 0.6, TRUE, 6 ) + IFS( K16>=125, 20, K16>=115, 17 + (K16 - 115) * 0.3, K16>=105, 13 + (K16 - 105) * 0.4, K16>=95, 9 + (K16 - 95) * 0.4, K16>=85, 6 + (K16 - 85) * 0.3, TRUE, 3 ) + IFS( K9<=0.045, 15, K9<=0.05, 12 + (0.05 - K9) * 600, K9<=0.055, 9 + (0.055 - K9) * 600, K9<=0.06, 6 + (0.06 - K9) * 600, K9<=0.065, 3 + (0.065 - K9) * 600, K9<=0.07, 1.5 + (0.07 - K9) * 300, TRUE, 0 ) + IFS( K11<=0.023, 7.5, K11<=0.03, 6 + (0.03 - K11) / 0.007 * 1.5, K11<=0.04, 4.5 + (0.04 - K11) / 0.01 * 1.5, K11<=0.045, 3 + (0.045 - K11) / 0.005 * 1.5, K11<=0.05, 1.5 + (0.05 - K11) / 0.005 * 1.5, TRUE, 0 ) + IFS( K17>=100000, 17.5, K17>=97000, 15 + (K17 - 97000) / 3000 * 2.5, K17>=90000, 12 + (K17 - 90000) / 7000 * 3, K17>=85000, 9 + (K17 - 85000) / 5000 * 3, K17>=80000, 6 + (K17 - 80000) / 5000 * 3, TRUE, 3 ) ) -> 45.568 | R22: =IFS( Q22>=80, "🟢 Affordable", Q22>=60, "🟡 Pressured", Q22>=40, "🟠 Very Strained", TRUE, "🔴 Meltdown" ) -> 🟠 Very Strained | U22: TBD | W22: Streaming / Cable TV | X22: 599.226 | Y22: 595.023 | Z22: =(X22 - Y22) / Y22 -> 0.0070635925 | AA22: =IF(OR(X22="", Y22=""), "", X22 - Y22) -> 4.203 | AB22: =IF(OR(X22="", Y22="", Y22=0), "", IF((X22 - Y22)/Y22 >= 0.1, "⬆️⬆️ MAJOR Rise", IF((X22 - Y22)/Y22 >= 0.01, "⬆️ Rise", IF((X22 - Y22)/Y22 <= -0.1, "⬇️⬇️ MAJOR Drop", IF((X22 - Y22)/Y22 <= -0.01, "⬇️ Drop", "Stable"))))) -> Stable
A23: Median Family Income | B23: 115443 | C23: 103209 | D23: 98566 | E23: 114661 | I23: Resale Homes for Sale | J23: 2000500 | K23: =K21-K22 -> 582417 | L23: =L21-L22 -> 333376 | M23: =(K23 - L23) / L23 -> 0.74702738 | N23: =(K23-L23) -> 249041 | P23: Crash Likelihood | Q23: =MIN(100, SUM(E32:E51)) -> 45.75 | R23: =IFS( Q23>=100, "🔴 MELTDOWN", Q23>=80, "🟠 Crash in Sight", Q23>=70, "🟡 Correction in Sight", Q23>=50, "🟡 Starting to Stall", TRUE, "🟢 Nowhere Close" ) -> 🟢 Nowhere Close | U23: TBD | W23: Internet | X23: 67.99 | Y23: 67.76 | Z23: =(X23 - Y23) / Y23 -> 0.0033943329 | AA23: =IF(OR(X23="", Y23=""), "", X23 - Y23) -> 0.23 | AB23: =IF(OR(X23="", Y23="", Y23=0), "", IF((X23 - Y23)/Y23 >= 0.1, "⬆️⬆️ MAJOR Rise", IF((X23 - Y23)/Y23 >= 0.01, "⬆️ Rise", IF((X23 - Y23)/Y23 <= -0.1, "⬇️⬇️ MAJOR Drop", IF((X23 - Y23)/Y23 <= -0.01, "⬇️ Drop", "Stable"))))) -> Stable
A24: Median Mortgage (P&I) | B24: 2841 | C24: 1718 | D24: 1911 | E24: 3276 | I24: Building Permits | J24: 1850000 | K24: 1330000 | L24: 1456000 | M24: =(K24 - L24) / L24 -> -0.086538462 | N24: =(K24-L24) -> -126000 | W24: Food away from home | X24: 387.202 | Y24: 375.53 | Z24: =(X24 - Y24) / Y24 -> 0.031081405 | AA24: =IF(OR(X24="", Y24=""), "", X24 - Y24) -> 11.672 | AB24: =IF(OR(X24="", Y24="", Y24=0), "", IF((X24 - Y24)/Y24 >= 0.1, "⬆️⬆️ MAJOR Rise", IF((X24 - Y24)/Y24 >= 0.01, "⬆️ Rise", IF((X24 - Y24)/Y24 <= -0.1, "⬇️⬇️ MAJOR Drop", IF((X24 - Y24)/Y24 <= -0.01, "⬇️ Drop", "Stable"))))) -> ⬆️ Rise
A25: Affordability today | B25: 92.7 | C25: 131.9 | D25: 109.9 | E25: 75 | I25: *$2,000 in HI & $2,000 in property taxes are escrowed into this payment. 30 year term w/ 10% down. No HOA or PMI. Based off "Resale Home (Median $) | W25: Personal Care | X25: 364.342 | Y25: 351.736 | Z25: =(X25 - Y25) / Y25 -> 0.03583938 | AA25: =IF(OR(X25="", Y25=""), "", X25 - Y25) -> 12.606 | AB25: =IF(OR(X25="", Y25="", Y25=0), "", IF((X25 - Y25)/Y25 >= 0.1, "⬆️⬆️ MAJOR Rise", IF((X25 - Y25)/Y25 >= 0.01, "⬆️ Rise", IF((X25 - Y25)/Y25 <= -0.1, "⬇️⬇️ MAJOR Drop", IF((X25 - Y25)/Y25 <= -0.01, "⬇️ Drop", "Stable"))))) -> ⬆️ Rise
A26: month prior | B26: 84.7 | C26: 125.2 | D26: 107.5 | E26: 72.9 | I26: **tracking for "Regulatory Costs", "Zoning Laws", "Impact Fee Structure", and "First time home buyer" related legislation | W26: Rice per lb | X26: 1.065 | Y26: 1.008 | Z26: =(X26 - Y26) / Y26 -> 0.056547619 | AA26: =IF(OR(X26="", Y26=""), "", X26 - Y26) -> 0.057 | AB26: =IF(OR(X26="", Y26="", Y26=0), "", IF((X26 - Y26)/Y26 >= 0.1, "⬆️⬆️ MAJOR Rise", IF((X26 - Y26)/Y26 >= 0.01, "⬆️ Rise", IF((X26 - Y26)/Y26 <= -0.1, "⬇️⬇️ MAJOR Drop", IF((X26 - Y26)/Y26 <= -0.01, "⬇️ Drop", "Stable"))))) -> ⬆️ Rise
A27: last year | B27: 95.4 | C27: 135.7 | D27: 109.2 | E27: 71 | P27: Housing Health Index | W27: Flour per lb | X27: 0.552 | Y27: 0.56 | Z27: =(X27 - Y27) / Y27 -> -0.014285714 | AA27: =IF(OR(X27="", Y27=""), "", X27 - Y27) -> -0.008 | AB27: =IF(OR(X27="", Y27="", Y27=0), "", IF((X27 - Y27)/Y27 >= 0.1, "⬆️⬆️ MAJOR Rise", IF((X27 - Y27)/Y27 >= 0.01, "⬆️ Rise", IF((X27 - Y27)/Y27 <= -0.1, "⬇️⬇️ MAJOR Drop", IF((X27 - Y27)/Y27 <= -0.01, "⬇️ Drop", "Stable"))))) -> ⬇️ Drop
A28: Yearly Change | B28: =(B25 - B27) / B27 -> -0.028301887 | C28: =(C25 - C27) / C27 -> -0.028002948 | D28: =(D25 - D27) / D27 -> 0.0064102564 | E28: =(E25 - E27) / E27 -> 0.056338028 | I28: Monthly Email Updates | P28: Today | Q28: =(Q22 * 0.45) + (Q21 * 0.35) + ((135 - Q23) / 135 * 100) * 0.2 -> 50.14236 | R28: =IFS( Q28 >= 85, "🟢 Affordable Housing", Q28 >= 72.5, "🟡 Buyer's Market", Q28 >= 60, "🟠 Neutral Market", Q28 >= 50, "🔴 Affordability Crisis", Q28 >= 40, "🔴 Nowhere close to affordable", TRUE, "🔥 Crisis Mode ") -> 🔴 Affordability Crisis | W28: Sugar per lb | X28: 0.991 | Y28: 1.011 | Z28: =(X28 - Y28) / Y28 -> -0.019782394 | AA28: =IF(OR(X28="", Y28=""), "", X28 - Y28) -> -0.02 | AB28: =IF(OR(X28="", Y28="", Y28=0), "", IF((X28 - Y28)/Y28 >= 0.1, "⬆️⬆️ MAJOR Rise", IF((X28 - Y28)/Y28 >= 0.01, "⬆️ Rise", IF((X28 - Y28)/Y28 <= -0.1, "⬇️⬇️ MAJOR Drop", IF((X28 - Y28)/Y28 <= -0.01, "⬇️ Drop", "Stable"))))) -> ⬇️ Drop
I29: links with promises + updates | W29: Tomatoes per lb | X29: 1.828 | Y29: 2.05 | Z29: =(X29 - Y29) / Y29 -> -0.10829268 | AA29: =IF(OR(X29="", Y29=""), "", X29 - Y29) -> -0.222 | AB29: =IF(OR(X29="", Y29="", Y29=0), "", IF((X29 - Y29)/Y29 >= 0.1, "⬆️⬆️ MAJOR Rise", IF((X29 - Y29)/Y29 >= 0.01, "⬆️ Rise", IF((X29 - Y29)/Y29 <= -0.1, "⬇️⬇️ MAJOR Drop", IF((X29 - Y29)/Y29 <= -0.01, "⬇️ Drop", "Stable"))))) -> ⬇️⬇️ MAJOR Drop
A30: HOUSING CRASH TRACKER (P23) | I30: Agenda 47 | P30: Economic Index (under construction) | W30: Bananas per lb | X30: 0.664 | Y30: 0.62 | Z30: =(X30 - Y30) / Y30 -> 0.070967742 | AA30: =IF(OR(X30="", Y30=""), "", X30 - Y30) -> 0.044 | AB30: =IF(OR(X30="", Y30="", Y30=0), "", IF((X30 - Y30)/Y30 >= 0.1, "⬆️⬆️ MAJOR Rise", IF((X30 - Y30)/Y30 >= 0.01, "⬆️ Rise", IF((X30 - Y30)/Y30 <= -0.1, "⬇️⬇️ MAJOR Drop", IF((X30 - Y30)/Y30 <= -0.01, "⬇️ Drop", "Stable"))))) -> ⬆️ Rise
A31: Variable | C31: Category | D31: Current | E31: Points | F31: Tier | I31: Everything Trump has done so far to effect Housing (click) | P31: **We compare each item’s current cost to its 2019 Q1 cost, weight essentials (food, utilities, rent, insurance, medical, etc.) more heavily than discretionary bills, average those ratios, and scale the result so 2019 Q1 equals 100. | W31: Potatoes per lb | X31: 1.014 | Y31: 0.973 | Z31: =(X31 - Y31) / Y31 -> 0.042137718 | AA31: =IF(OR(X31="", Y31=""), "", X31 - Y31) -> 0.041 | AB31: =IF(OR(X31="", Y31="", Y31=0), "", IF((X31 - Y31)/Y31 >= 0.1, "⬆️⬆️ MAJOR Rise", IF((X31 - Y31)/Y31 >= 0.01, "⬆️ Rise", IF((X31 - Y31)/Y31 <= -0.1, "⬇️⬇️ MAJOR Drop", IF((X31 - Y31)/Y31 <= -0.01, "⬇️ Drop", "Stable"))))) -> ⬆️ Rise
A32: Unemployment Rate | C32: Critical | D32: 0.046 | E32: =IFS(D32 < 0.04, 0, D32 < 0.06, 3, D32 < 0.08, 6, D32 < 0.1, 9, TRUE, 12) -> 3 | F32: =IFS( E32>=10, "🔴 High Risk", E32>=6, "🟠 Elevated Risk", E32>=3, "🟡 Moderate Risk", TRUE, "🟢 Low Risk" ) -> 🟡 Moderate Risk | I32: Latest on Housing & Urban Development | P32: Date | Q32: Index** | R32: MoM Change | S32: % | T32: YoY | U32: % | W32: Lettuce per lb | X32: 3.399 | Y32: 2.83 | Z32: =(X32 - Y32) / Y32 -> 0.20106007 | AA32: =IF(OR(X32="", Y32=""), "", X32 - Y32) -> 0.569 | AB32: =IF(OR(X32="", Y32="", Y32=0), "", IF((X32 - Y32)/Y32 >= 0.1, "⬆️⬆️ MAJOR Rise", IF((X32 - Y32)/Y32 >= 0.01, "⬆️ Rise", IF((X32 - Y32)/Y32 <= -0.1, "⬇️⬇️ MAJOR Drop", IF((X32 - Y32)/Y32 <= -0.01, "⬇️ Drop", "Stable"))))) -> ⬆️⬆️ MAJOR Rise
A33: FHA Mortgage Delinquency Rate | C33: Critical | D33: 0.041 | E33: =IFS(D33 < 0.05, 0, D33 < 0.1, 3, D33 < 0.13, 6, D33 < 0.15, 9, TRUE, 12) -> 0 | F33: =IFS( E33>=10, "🔴 High Risk", E33>=6, "🟠 Elevated Risk", E33>=3, "🟡 Moderate Risk", TRUE, "🟢 Low Risk" ) -> 🟢 Low Risk | I33: Project 2025 Tracker (projected housing related changes) | P33: 46021 | Q33: N/a | R33: {=IF(P33:P69="","", IF(Q32:Q68="","", Q33:Q69 - Q32:Q68 ) )} -> #REF! | S33: N/a | W33: Cheddar Cheese per lb | X33: 5.636 | Y33: 5.698 | Z33: =(X33 - Y33) / Y33 -> -0.010881011 | AA33: =IF(OR(X33="", Y33=""), "", X33 - Y33) -> -0.062 | AB33: =IF(OR(X33="", Y33="", Y33=0), "", IF((X33 - Y33)/Y33 >= 0.1, "⬆️⬆️ MAJOR Rise", IF((X33 - Y33)/Y33 >= 0.01, "⬆️ Rise", IF((X33 - Y33)/Y33 <= -0.1, "⬇️⬇️ MAJOR Drop", IF((X33 - Y33)/Y33 <= -0.01, "⬇️ Drop", "Stable"))))) -> ⬇️ Drop
A34: Total Mortgage Delinquency Rate | C34: Critical | D34: 0.0178 | E34: =IFS(D34<2%, 0, D34<5%, 5, D34<10%, 10, TRUE, 15) -> 0 | F34: =IFS( E34>=10, "🔴 High Risk", E34>=6, "🟠 Elevated Risk", E34>=3, "🟡 Moderate Risk", TRUE, "🟢 Low Risk" ) -> 🟢 Low Risk | P34: 45991 | Q34: "insufficient Data due to shutdown" | W34: Bacon per lb | X34: 6.928 | Y34: 7.044 | Z34: =(X34 - Y34) / Y34 -> -0.016467916 | AA34: =IF(OR(X34="", Y34=""), "", X34 - Y34) -> -0.116 | AB34: =IF(OR(X34="", Y34="", Y34=0), "", IF((X34 - Y34)/Y34 >= 0.1, "⬆️⬆️ MAJOR Rise", IF((X34 - Y34)/Y34 >= 0.01, "⬆️ Rise", IF((X34 - Y34)/Y34 <= -0.1, "⬇️⬇️ MAJOR Drop", IF((X34 - Y34)/Y34 <= -0.01, "⬇️ Drop", "Stable"))))) -> ⬇️ Drop
A35: Total Housing Supply | C35: Critical | D35: 1072417 | E35: =IFS(D35 > 0.6, 0, D35 > 0.45, 3, D35 > 0.3, 6, D35 > 0.15, 9, TRUE, 12) -> 0 | F35: =IFS( E35>=10, "🔴 High Risk", E35>=6, "🟠 Elevated Risk", E35>=3, "🟡 Moderate Risk", TRUE, "🟢 Low Risk" ) -> 🟢 Low Risk | I35: INVESTMENT TRACKER | P35: =IFERROR(__xludf.DUMMYFUNCTION("IFERROR( SORT( FILTER( COST_INDEX!$A$7:$A50501, COST_INDEX!$C$7:$C50501<>"""" ), 1, FALSE ), """") "),45961.0) -> 45961 | Q35: {=IF( P35:P44="", "", VLOOKUP(P35:P44, COST_INDEX!$A$7:$C50501, 3, FALSE) )} -> 0 | R35: {=IF(P35:P69="","", IF(Q36:Q70="","", Q35:Q69 - Q36:Q70 ) )} -> -138.19723 | S35: {=IF(P35:P69="","", IF(Q36:Q70="","", Q35:Q69 / Q36:Q70 - 1 ) )} -> -1 | T35: {=IF(P35:P69="","", IFERROR( Q35:Q69 - VLOOKUP( EDATE(P35:P69,-12), {P35:P69, Q35:Q69}, 2, FALSE ), "" ) )} | U35: {=IF(P35:P69="","", IFERROR( Q35:Q69 / VLOOKUP( EDATE(P35:P69,-12), {P35:P69, Q35:Q69}, 2, FALSE ) - 1, "" ) )} | W35: Potato Chips | X35: 6.821 | Y35: 6.474 | Z35: =(X35 - Y35) / Y35 -> 0.053599011 | AA35: =IF(OR(X35="", Y35=""), "", X35 - Y35) -> 0.347 | AB35: =IF(OR(X35="", Y35="", Y35=0), "", IF((X35 - Y35)/Y35 >= 0.1, "⬆️⬆️ MAJOR Rise", IF((X35 - Y35)/Y35 >= 0.01, "⬆️ Rise", IF((X35 - Y35)/Y35 <= -0.1, "⬇️⬇️ MAJOR Drop", IF((X35 - Y35)/Y35 <= -0.01, "⬇️ Drop", "Stable"))))) -> ⬆️ Rise
A36: Disposable Income of Homeowners | C36: Major | D36: 0.11249194 | E36: =IFS(D36 > 0.13, 0, D36 > 0.11, 2, D36 > 0.09, 4, D36 > 0.07, 6, TRUE, 8) -> 2 | F36: =IFS( E36>=10, "🔴 High Risk", E36>=6, "🟠 Elevated Risk", E36>=3, "🟡 Moderate Risk", TRUE, "🟢 Low Risk" ) -> 🟢 Low Risk | P36: =IFERROR(__xludf.DUMMYFUNCTION("""COMPUTED_VALUE"""),45930.0) -> 45930 | Q36: 138.19723 | R36: 0.22109244 | S36: 0.0016023962 | T36: 6.1685316 | U36: 0.046721142 | W36: Disposable Diapers | X36: 106.133 | Y36: 104.949 | Z36: =(X36 - Y36) / Y36 -> 0.01128167 | AA36: =IF(OR(X36="", Y36=""), "", X36 - Y36) -> 1.184 | AB36: =IF(OR(X36="", Y36="", Y36=0), "", IF((X36 - Y36)/Y36 >= 0.1, "⬆️⬆️ MAJOR Rise", IF((X36 - Y36)/Y36 >= 0.01, "⬆️ Rise", IF((X36 - Y36)/Y36 <= -0.1, "⬇️⬇️ MAJOR Drop", IF((X36 - Y36)/Y36 <= -0.01, "⬇️ Drop", "Stable"))))) -> ⬆️ Rise
A37: Foreclosure Rate | C37: Major | D37: 0.006 | E37: =IFS(D37 < 0.005, 0, D37 < 0.01, 2, D37 < 0.02, 4, D37 < 0.03, 6, TRUE, 8) -> 2 | F37: =IFS( E37>=10, "🔴 High Risk", E37>=6, "🟠 Elevated Risk", E37>=3, "🟡 Moderate Risk", TRUE, "🟢 Low Risk" ) -> 🟢 Low Risk | I37: Asset | J37: Value | K37: MoM % | L37: Yoy % | P37: =IFERROR(__xludf.DUMMYFUNCTION("""COMPUTED_VALUE"""),45900.0) -> 45900 | Q37: 137.97614 | R37: 1.0316368 | S37: 0.0075332471 | W37: Oranges per lb | X37: 1.803 | Y37: 1.53 | Z37: =(X37 - Y37) / Y37 -> 0.17843137 | AA37: =IF(OR(X37="", Y37=""), "", X37 - Y37) -> 0.273 | AB37: =IF(OR(X37="", Y37="", Y37=0), "", IF((X37 - Y37)/Y37 >= 0.1, "⬆️⬆️ MAJOR Rise", IF((X37 - Y37)/Y37 >= 0.01, "⬆️ Rise", IF((X37 - Y37)/Y37 <= -0.1, "⬇️⬇️ MAJOR Drop", IF((X37 - Y37)/Y37 <= -0.01, "⬇️ Drop", "Stable"))))) -> ⬆️⬆️ MAJOR Rise
A38: Business Loan Delinquencies | C38: Major | D38: 0.0133 | E38: =IFS(D38 < 0.01, 0, D38 < 0.015, 2, D38 < 0.02, 4, D38 < 0.03, 6, TRUE, 8) -> 2 | F38: =IFS( E38>=10, "🔴 High Risk", E38>=6, "🟠 Elevated Risk", E38>=3, "🟡 Moderate Risk", TRUE, "🟢 Low Risk" ) -> 🟢 Low Risk | I38: Gold | J38: 413.18 | K38: =IFERROR(__xludf.DUMMYFUNCTION("IFERROR( INDEX( INVEST_HISTORY!$A:$O, MAX(FILTER(ROW(INVEST_HISTORY!$A:$A), INVEST_HISTORY!$A:$A<>"""")), MATCH($I38, INVEST_HISTORY!$1:$1, 0) ) / INDEX( INVEST_HISTORY!$A:$O, MAX(FILTER(ROW(INVEST_HISTORY!$A:$A), INVEST_HISTOR"&"Y!$A:$A<>""""))-1, MATCH($I38, INVEST_HISTORY!$1:$1, 0) ) - 1, """") "),0.02592193336508819) -> 0.025921933 | L38: {=IF( J38="", "", IFERROR( J38 / INDEX( INVEST_HISTORY!$B$2:$O$2, 1, MATCH($I38, INVEST_HISTORY!$B$1:$O$1, 0) ) - 1, "" ) )} -> 0.60116257 | P38: =IFERROR(__xludf.DUMMYFUNCTION("""COMPUTED_VALUE"""),45869.0) -> 45869 | Q38: 136.9445 | R38: 0.4612551 | S38: 0.003379573 | W38: Toilet Paper | X38: 150.867 | Y38: 144.932 | Z38: =(X38 - Y38) / Y38 -> 0.040950239 | AA38: =IF(OR(X38="", Y38=""), "", X38 - Y38) -> 5.935 | AB38: =IF(OR(X38="", Y38="", Y38=0), "", IF((X38 - Y38)/Y38 >= 0.1, "⬆️⬆️ MAJOR Rise", IF((X38 - Y38)/Y38 >= 0.01, "⬆️ Rise", IF((X38 - Y38)/Y38 <= -0.1, "⬇️⬇️ MAJOR Drop", IF((X38 - Y38)/Y38 <= -0.01, "⬇️ Drop", "Stable"))))) -> ⬆️ Rise
A39: Delinquency Rate on All Loans | C39: Major | D39: 0.0147 | E39: =IFS(D39 < 0.015, 0, D39 < 0.025, 2, D39 < 0.04, 4, D39 < 0.06, 6, TRUE, 8) -> 0 | F39: =IFS( E39>=10, "🔴 High Risk", E39>=6, "🟠 Elevated Risk", E39>=3, "🟡 Moderate Risk", TRUE, "🟢 Low Risk" ) -> 🟢 Low Risk | I39: Silver | J39: 73.71 | K39: =IFERROR(__xludf.DUMMYFUNCTION("IFERROR( INDEX( INVEST_HISTORY!$A:$O, MAX(FILTER(ROW(INVEST_HISTORY!$A:$A), INVEST_HISTORY!$A:$A<>"""")), MATCH($I39, INVEST_HISTORY!$1:$1, 0) ) / INDEX( INVEST_HISTORY!$A:$O, MAX(FILTER(ROW(INVEST_HISTORY!$A:$A), INVEST_HISTOR"&"Y!$A:$A<>""""))-1, MATCH($I39, INVEST_HISTORY!$1:$1, 0) ) - 1, """") "),0.028703972165845082) -> 0.028703972 | L39: {=IF( J39="", "", IFERROR( J39 / INDEX( INVEST_HISTORY!$B$2:$O$2, 1, MATCH($I39, INVEST_HISTORY!$B$1:$O$1, 0) ) - 1, "" ) )} -> 1.5665042 | P39: =IFERROR(__xludf.DUMMYFUNCTION("""COMPUTED_VALUE"""),45838.0) -> 45838 | Q39: 136.48325 | R39: -0.26013217 | S39: -0.0019023383 | T39: 7.9400959 | U39: 0.061769887 | W39: Trash collection | X39: 204.967 | Y39: 194.665 | Z39: =(X39 - Y39) / Y39 -> 0.052921686 | AA39: =IF(OR(X39="", Y39=""), "", X39 - Y39) -> 10.302 | AB39: =IF(OR(X39="", Y39="", Y39=0), "", IF((X39 - Y39)/Y39 >= 0.1, "⬆️⬆️ MAJOR Rise", IF((X39 - Y39)/Y39 >= 0.01, "⬆️ Rise", IF((X39 - Y39)/Y39 <= -0.1, "⬇️⬇️ MAJOR Drop", IF((X39 - Y39)/Y39 <= -0.01, "⬇️ Drop", "Stable"))))) -> ⬆️ Rise
A40: Credit Card Delinquencies | C40: Minor | D40: 0.0298 | E40: =IFS(D40 < 0.02, 0, D40 < 0.03, 1.5, D40 < 0.04, 3.25, D40 < 0.05, 5, TRUE, 6.25) -> 1.5 | F40: =IFS( E40>=10, "🔴 High Risk", E40>=6, "🟠 Elevated Risk", E40>=3, "🟡 Moderate Risk", TRUE, "🟢 Low Risk" ) -> 🟢 Low Risk | I40: Platinum | J40: 220.45 | K40: =IFERROR(__xludf.DUMMYFUNCTION("IFERROR( INDEX( INVEST_HISTORY!$A:$O, MAX(FILTER(ROW(INVEST_HISTORY!$A:$A), INVEST_HISTORY!$A:$A<>"""")), MATCH($I40, INVEST_HISTORY!$1:$1, 0) ) / INDEX( INVEST_HISTORY!$A:$O, MAX(FILTER(ROW(INVEST_HISTORY!$A:$A), INVEST_HISTOR"&"Y!$A:$A<>""""))-1, MATCH($I40, INVEST_HISTORY!$1:$1, 0) ) - 1, """") "),0.054579326317909294) -> 0.054579326 | L40: {=IF( J40="", "", IFERROR( J40 / INDEX( INVEST_HISTORY!$B$2:$O$2, 1, MATCH($I40, INVEST_HISTORY!$B$1:$O$1, 0) ) - 1, "" ) )} -> 1.4836638 | P40: =IFERROR(__xludf.DUMMYFUNCTION("""COMPUTED_VALUE"""),45808.0) -> 45808 | Q40: 136.74338 | R40: 0.242093 | S40: 0.0017735584 | W40: Cereal | X40: 361.536 | Y40: 356.88 | Z40: =(X40 - Y40) / Y40 -> 0.013046402 | AA40: =IF(OR(X40="", Y40=""), "", X40 - Y40) -> 4.656 | AB40: =IF(OR(X40="", Y40="", Y40=0), "", IF((X40 - Y40)/Y40 >= 0.1, "⬆️⬆️ MAJOR Rise", IF((X40 - Y40)/Y40 >= 0.01, "⬆️ Rise", IF((X40 - Y40)/Y40 <= -0.1, "⬇️⬇️ MAJOR Drop", IF((X40 - Y40)/Y40 <= -0.01, "⬇️ Drop", "Stable"))))) -> ⬆️ Rise
A41: Car Payment Defaults (subprime) | C41: Minor | D41: 0.063 | E41: =IFS(D41<3%, 0, D41<6%, 3, D41<10%, 6, TRUE, 9) -> 6 | F41: =IFS( E41>=10, "🔴 High Risk", E41>=6, "🟠 Elevated Risk", E41>=3, "🟡 Moderate Risk", TRUE, "🟢 Low Risk" ) -> 🟠 Elevated Risk | I41: S&P 500 | J41: 6944.82 | K41: =IFERROR(__xludf.DUMMYFUNCTION("IFERROR( INDEX( INVEST_HISTORY!$A:$O, MAX(FILTER(ROW(INVEST_HISTORY!$A:$A), INVEST_HISTORY!$A:$A<>"""")), MATCH($I41, INVEST_HISTORY!$1:$1, 0) ) / INDEX( INVEST_HISTORY!$A:$O, MAX(FILTER(ROW(INVEST_HISTORY!$A:$A), INVEST_HISTOR"&"Y!$A:$A<>""""))-1, MATCH($I41, INVEST_HISTORY!$1:$1, 0) ) - 1, """") "),0.007044418407712083) -> 0.0070444184 | L41: {=IF( J41="", "", IFERROR( J41 / INDEX( INVEST_HISTORY!$B$2:$O$2, 1, MATCH($I41, INVEST_HISTORY!$B$1:$O$1, 0) ) - 1, "" ) )} -> 0.14390142 | P41: =IFERROR(__xludf.DUMMYFUNCTION("""COMPUTED_VALUE"""),45777.0) -> 45777 | Q41: 136.50129 | R41: -1.4869099 | S41: -0.010775631 | W41: First Aid Supplies | X41: 208.525 | Y41: 207.237 | Z41: =(X41 - Y41) / Y41 -> 0.0062151064 | AA41: =IF(OR(X41="", Y41=""), "", X41 - Y41) -> 1.288 | AB41: =IF(OR(X41="", Y41="", Y41=0), "", IF((X41 - Y41)/Y41 >= 0.1, "⬆️⬆️ MAJOR Rise", IF((X41 - Y41)/Y41 >= 0.01, "⬆️ Rise", IF((X41 - Y41)/Y41 <= -0.1, "⬇️⬇️ MAJOR Drop", IF((X41 - Y41)/Y41 <= -0.01, "⬇️ Drop", "Stable"))))) -> Stable
A42: Rental Vacancy Rate | C42: Minor | D42: 0.071 | E42: =IFS(D42 < 0.06, 0, D42 < 0.07, 1.5, D42 < 0.08, 3.25, D42 < 0.09, 5, TRUE, 6.25) -> 3.25 | F42: =IFS( E42>=10, "🔴 High Risk", E42>=6, "🟠 Elevated Risk", E42>=3, "🟡 Moderate Risk", TRUE, "🟢 Low Risk" ) -> 🟡 Moderate Risk | I42: Dow J | J42: 494.61 | K42: =IFERROR(__xludf.DUMMYFUNCTION("IFERROR( INDEX( INVEST_HISTORY!$A:$O, MAX(FILTER(ROW(INVEST_HISTORY!$A:$A), INVEST_HISTORY!$A:$A<>"""")), MATCH($I42, INVEST_HISTORY!$1:$1, 0) ) / INDEX( INVEST_HISTORY!$A:$O, MAX(FILTER(ROW(INVEST_HISTORY!$A:$A), INVEST_HISTOR"&"Y!$A:$A<>""""))-1, MATCH($I42, INVEST_HISTORY!$1:$1, 0) ) - 1, """") "),0.013172315391137168) -> 0.013172315 | L42: {=IF( J42="", "", IFERROR( J42 / INDEX( INVEST_HISTORY!$B$2:$O$2, 1, MATCH($I42, INVEST_HISTORY!$B$1:$O$1, 0) ) - 1, "" ) )} -> 0.10202308 | P42: =IFERROR(__xludf.DUMMYFUNCTION("""COMPUTED_VALUE"""),45747.0) -> 45747 | Q42: 137.9882 | R42: 1.3643173 | S42: 0.0099859358 | T42: 10.073671 | U42: 0.07875314 | W42: Cooking Oil | X42: 118.519 | Y42: 117.382 | Z42: =(X42 - Y42) / Y42 -> 0.0096863233 | AA42: =IF(OR(X42="", Y42=""), "", X42 - Y42) -> 1.137 | AB42: =IF(OR(X42="", Y42="", Y42=0), "", IF((X42 - Y42)/Y42 >= 0.1, "⬆️⬆️ MAJOR Rise", IF((X42 - Y42)/Y42 >= 0.01, "⬆️ Rise", IF((X42 - Y42)/Y42 <= -0.1, "⬇️⬇️ MAJOR Drop", IF((X42 - Y42)/Y42 <= -0.01, "⬇️ Drop", "Stable"))))) -> Stable
A43: Backdated Yield Curve (12 month) | C43: Critical | D43: 0.0071 | E43: =IFS(D43 > 0.01, 0, D43 > 0, 3, D43 > -0.5, 6, D43 > -1, 9, TRUE, 12) -> 3 | F43: =IFS( E43>=10, "🔴 High Risk", E43>=6, "🟠 Elevated Risk", E43>=3, "🟡 Moderate Risk", TRUE, "🟢 Low Risk" ) -> 🟡 Moderate Risk | I43: BTC | J43: 93706.28 | K43: =IFERROR(__xludf.DUMMYFUNCTION("IFERROR( INDEX( INVEST_HISTORY!$A:$O, MAX(FILTER(ROW(INVEST_HISTORY!$A:$A), INVEST_HISTORY!$A:$A<>"""")), MATCH($I43, INVEST_HISTORY!$1:$1, 0) ) / INDEX( INVEST_HISTORY!$A:$O, MAX(FILTER(ROW(INVEST_HISTORY!$A:$A), INVEST_HISTOR"&"Y!$A:$A<>""""))-1, MATCH($I43, INVEST_HISTORY!$1:$1, 0) ) - 1, """") "),0.04712670838316302) -> 0.047126708 | L43: {=IF( J43="", "", IFERROR( J43 / INDEX( INVEST_HISTORY!$B$2:$O$2, 1, MATCH($I43, INVEST_HISTORY!$B$1:$O$1, 0) ) - 1, "" ) )} -> -0.11097226 | P43: =IFERROR(__xludf.DUMMYFUNCTION("""COMPUTED_VALUE"""),45716.0) -> 45716 | Q43: 136.62388 | R43: 1.8550695 | S43: 0.013764828 | W43: Salt & Pepper | X43: 308.476 | Y43: 303.164 | Z43: =(X43 - Y43) / Y43 -> 0.017521869 | AA43: =IF(OR(X43="", Y43=""), "", X43 - Y43) -> 5.312 | AB43: =IF(OR(X43="", Y43="", Y43=0), "", IF((X43 - Y43)/Y43 >= 0.1, "⬆️⬆️ MAJOR Rise", IF((X43 - Y43)/Y43 >= 0.01, "⬆️ Rise", IF((X43 - Y43)/Y43 <= -0.1, "⬇️⬇️ MAJOR Drop", IF((X43 - Y43)/Y43 <= -0.01, "⬇️ Drop", "Stable"))))) -> ⬆️ Rise
A44: Job Openings (JOLTS) | C44: Major | D44: 7670000 | E44: =IFS(D44 > 9000000, 0, D44 > 7500000, 2, D44 > 6000000, 4, D44 > 5000000, 6, TRUE, 8) -> 2 | F44: =IFS( E44>=10, "🔴 High Risk", E44>=6, "🟠 Elevated Risk", E44>=3, "🟡 Moderate Risk", TRUE, "🟢 Low Risk" ) -> 🟢 Low Risk | I44: ETH | J44: 3225.2348 | K44: =IFERROR(__xludf.DUMMYFUNCTION("IFERROR( INDEX( INVEST_HISTORY!$A:$O, MAX(FILTER(ROW(INVEST_HISTORY!$A:$A), INVEST_HISTORY!$A:$A<>"""")), MATCH($I44, INVEST_HISTORY!$1:$1, 0) ) / INDEX( INVEST_HISTORY!$A:$O, MAX(FILTER(ROW(INVEST_HISTORY!$A:$A), INVEST_HISTOR"&"Y!$A:$A<>""""))-1, MATCH($I44, INVEST_HISTORY!$1:$1, 0) ) - 1, """") "),0.07896734592474464) -> 0.078967346 | L44: {=IF( J44="", "", IFERROR( J44 / INDEX( INVEST_HISTORY!$B$2:$O$2, 1, MATCH($I44, INVEST_HISTORY!$B$1:$O$1, 0) ) - 1, "" ) )} -> 0.035620005 | P44: =IFERROR(__xludf.DUMMYFUNCTION("""COMPUTED_VALUE"""),45688.0) -> 45688 | Q44: 134.76881 | R44: 2.0223242 | S44: 0.015234484 | W44: Tea | X44: 174.141 | Y44: 184.359 | Z44: =(X44 - Y44) / Y44 -> -0.055424471 | AA44: =IF(OR(X44="", Y44=""), "", X44 - Y44) -> -10.218 | AB44: =IF(OR(X44="", Y44="", Y44=0), "", IF((X44 - Y44)/Y44 >= 0.1, "⬆️⬆️ MAJOR Rise", IF((X44 - Y44)/Y44 >= 0.01, "⬆️ Rise", IF((X44 - Y44)/Y44 <= -0.1, "⬇️⬇️ MAJOR Drop", IF((X44 - Y44)/Y44 <= -0.01, "⬇️ Drop", "Stable"))))) -> ⬇️ Drop
A45: Layoffs | C45: Major | D45: 1854000 | E45: =IFS( D45<1500000, 0, D45<2000000, 3, D45<2250000, 6, D45<2500000, 9, TRUE, 12 ) -> 3 | F45: =IFS( E45>=10, "🔴 High Risk", E45>=6, "🟠 Elevated Risk", E45>=3, "🟡 Moderate Risk", TRUE, "🟢 Low Risk" ) -> 🟡 Moderate Risk | I45: XRP | J45: 2.3484 | K45: =IFERROR(__xludf.DUMMYFUNCTION("IFERROR( INDEX( INVEST_HISTORY!$A:$O, MAX(FILTER(ROW(INVEST_HISTORY!$A:$A), INVEST_HISTORY!$A:$A<>"""")), MATCH($I45, INVEST_HISTORY!$1:$1, 0) ) / INDEX( INVEST_HISTORY!$A:$O, MAX(FILTER(ROW(INVEST_HISTORY!$A:$A), INVEST_HISTOR"&"Y!$A:$A<>""""))-1, MATCH($I45, INVEST_HISTORY!$1:$1, 0) ) - 1, """") "),0.17273661994696687) -> 0.17273662 | L45: {=IF( J45="", "", IFERROR( J45 / INDEX( INVEST_HISTORY!$B$2:$O$2, 1, MATCH($I45, INVEST_HISTORY!$B$1:$O$1, 0) ) - 1, "" ) )} -> -0.2347248 | P45: =IFERROR(__xludf.DUMMYFUNCTION("IFERROR( SORT( FILTER( COST_INDEX!$E$7:$E50501, COST_INDEX!$G$7:$G50501<>"""" ), 1, FALSE ), """") "),45657.0) -> 45657 | Q45: {=IF( P45:P50501="", "", VLOOKUP(P45:P50501, COST_INDEX!$E$7:$G50501, 3, FALSE) )} -> 132.74649 | R45: 0.71778524 | S45: 0.0054365849 | T45: 6.2888967 | U45: 0.049731272 | W45: Wine | X45: 13.91 | Y45: 14.035 | Z45: =(X45 - Y45) / Y45 -> -0.0089063057 | AA45: =IF(OR(X45="", Y45=""), "", X45 - Y45) -> -0.125 | AB45: =IF(OR(X45="", Y45="", Y45=0), "", IF((X45 - Y45)/Y45 >= 0.1, "⬆️⬆️ MAJOR Rise", IF((X45 - Y45)/Y45 >= 0.01, "⬆️ Rise", IF((X45 - Y45)/Y45 <= -0.1, "⬇️⬇️ MAJOR Drop", IF((X45 - Y45)/Y45 <= -0.01, "⬇️ Drop", "Stable"))))) -> Stable
A46: Bank Plumbing (SOFR - IORB) | C46: Critical | D46: 0.0001 | E46: =IFS( D46<=0, 0, D46<0.001, 3, D46<0.0025, 6, D46<0.005, 9, TRUE, 12 ) -> 3 | F46: =IFS( E46>=10, "🔴 High Risk", E46>=6, "🟠 Elevated Risk", E46>=3, "🟡 Moderate Risk", TRUE, "🟢 Low Risk" ) -> 🟡 Moderate Risk | I46: 1 yr | J46: code in repair | K46: =IFERROR(__xludf.DUMMYFUNCTION("IFERROR( INDEX( INVEST_HISTORY!$A:$O, MAX(FILTER(ROW(INVEST_HISTORY!$A:$A), INVEST_HISTORY!$A:$A<>"""")), MATCH($I46, INVEST_HISTORY!$1:$1, 0) ) / INDEX( INVEST_HISTORY!$A:$O, MAX(FILTER(ROW(INVEST_HISTORY!$A:$A), INVEST_HISTOR"&"Y!$A:$A<>""""))-1, MATCH($I46, INVEST_HISTORY!$1:$1, 0) ) - 1, """") "),-1.0) -> -1 | L46: {=IF( J46="", "", IFERROR( J46 / INDEX( INVEST_HISTORY!$B$2:$O$2, 1, MATCH($I46, INVEST_HISTORY!$B$1:$O$1, 0) ) - 1, "" ) )} | P46: =IFERROR(__xludf.DUMMYFUNCTION("""COMPUTED_VALUE"""),45565.0) -> 45565 | Q46: 132.0287 | R46: 3.4855487 | S46: 0.027115787 | T46: 5.9939582 | U46: 0.047557984 | W46: Dental Care | X46: 140.922 | Y46: 139.372 | Z46: =(X46 - Y46) / Y46 -> 0.011121316 | AA46: =IF(OR(X46="", Y46=""), "", X46 - Y46) -> 1.55 | AB46: =IF(OR(X46="", Y46="", Y46=0), "", IF((X46 - Y46)/Y46 >= 0.1, "⬆️⬆️ MAJOR Rise", IF((X46 - Y46)/Y46 >= 0.01, "⬆️ Rise", IF((X46 - Y46)/Y46 <= -0.1, "⬇️⬇️ MAJOR Drop", IF((X46 - Y46)/Y46 <= -0.01, "⬇️ Drop", "Stable"))))) -> ⬆️ Rise
A47: Cash Deposits | C47: Major | D47: 18619.313 | E47: =IFS( D47>=18500, 0, D47>=18000, 3, D47>=17500, 6, D47>=17000, 9, TRUE, 12 ) -> 0 | F47: =IFS( E47>=10, "🔴 High Risk", E47>=6, "🟠 Elevated Risk", E47>=3, "🟡 Moderate Risk", TRUE, "🟢 Low Risk" ) -> 🟢 Low Risk | I47: 2 yr | J47: code in repair | K47: =IFERROR(__xludf.DUMMYFUNCTION("IFERROR( INDEX( INVEST_HISTORY!$A:$O, MAX(FILTER(ROW(INVEST_HISTORY!$A:$A), INVEST_HISTORY!$A:$A<>"""")), MATCH($I47, INVEST_HISTORY!$1:$1, 0) ) / INDEX( INVEST_HISTORY!$A:$O, MAX(FILTER(ROW(INVEST_HISTORY!$A:$A), INVEST_HISTOR"&"Y!$A:$A<>""""))-1, MATCH($I47, INVEST_HISTORY!$1:$1, 0) ) - 1, """") "),-1.0) -> -1 | L47: {=IF( J47="", "", IFERROR( J47 / INDEX( INVEST_HISTORY!$B$2:$O$2, 1, MATCH($I47, INVEST_HISTORY!$B$1:$O$1, 0) ) - 1, "" ) )} | P47: =IFERROR(__xludf.DUMMYFUNCTION("""COMPUTED_VALUE"""),45473.0) -> 45473 | Q47: 128.54315 | R47: 0.62862555 | S47: 0.0049144188 | T47: 3.6063653 | U47: 0.02886552 | W47: Energy Drinks | X47: 104.093 | Y47: 102.745 | Z47: =(X47 - Y47) / Y47 -> 0.01311986 | AA47: =IF(OR(X47="", Y47=""), "", X47 - Y47) -> 1.348 | AB47: =IF(OR(X47="", Y47="", Y47=0), "", IF((X47 - Y47)/Y47 >= 0.1, "⬆️⬆️ MAJOR Rise", IF((X47 - Y47)/Y47 >= 0.01, "⬆️ Rise", IF((X47 - Y47)/Y47 <= -0.1, "⬇️⬇️ MAJOR Drop", IF((X47 - Y47)/Y47 <= -0.01, "⬇️ Drop", "Stable"))))) -> ⬆️ Rise
A48: U6 Unemployment Rate | C48: Critical | D48: 0.087 | E48: =IFS( D48<=0.07, 0, D48<=0.095, 3, D48<0.1, 6, D48<0.15, 9, TRUE, 12 ) -> 3 | F48: =IFS( E48>=10, "🔴 High Risk", E48>=6, "🟠 Elevated Risk", E48>=3, "🟡 Moderate Risk", TRUE, "🟢 Low Risk" ) -> 🟡 Moderate Risk | I48: 5 yr | J48: code in repair | K48: =IFERROR(__xludf.DUMMYFUNCTION("IFERROR( INDEX( INVEST_HISTORY!$A:$O, MAX(FILTER(ROW(INVEST_HISTORY!$A:$A), INVEST_HISTORY!$A:$A<>"""")), MATCH($I48, INVEST_HISTORY!$1:$1, 0) ) / INDEX( INVEST_HISTORY!$A:$O, MAX(FILTER(ROW(INVEST_HISTORY!$A:$A), INVEST_HISTOR"&"Y!$A:$A<>""""))-1, MATCH($I48, INVEST_HISTORY!$1:$1, 0) ) - 1, """") "),-1.0) -> -1 | L48: {=IF( J48="", "", IFERROR( J48 / INDEX( INVEST_HISTORY!$B$2:$O$2, 1, MATCH($I48, INVEST_HISTORY!$B$1:$O$1, 0) ) - 1, "" ) )} | P48: =IFERROR(__xludf.DUMMYFUNCTION("""COMPUTED_VALUE"""),45382.0) -> 45382 | Q48: 127.91453 | R48: 1.4569373 | S48: 0.011521153 | T48: 1.1191533 | U48: 0.0088264521 | W48: Insulin | X48: 269.2 | Y48: 269.245 | Z48: =(X48 - Y48) / Y48 -> -0.00016713402 | AA48: =IF(OR(X48="", Y48=""), "", X48 - Y48) -> -0.045 | AB48: =IF(OR(X48="", Y48="", Y48=0), "", IF((X48 - Y48)/Y48 >= 0.1, "⬆️⬆️ MAJOR Rise", IF((X48 - Y48)/Y48 >= 0.01, "⬆️ Rise", IF((X48 - Y48)/Y48 <= -0.1, "⬇️⬇️ MAJOR Drop", IF((X48 - Y48)/Y48 <= -0.01, "⬇️ Drop", "Stable"))))) -> Stable
A49: Temporary Workers | C49: Major | D49: 2469800 | E49: =IFS( D49>=2800000, 0, D49>=2500000, 3, D49>=2250000, 6, D49>=2000000, 9, TRUE, 12 ) -> 6 | F49: =IFS( E49>=10, "🔴 High Risk", E49>=6, "🟠 Elevated Risk", E49>=3, "🟡 Moderate Risk", TRUE, "🟢 Low Risk" ) -> 🟠 Elevated Risk | I49: 10 yr | J49: code in repair | K49: =IFERROR(__xludf.DUMMYFUNCTION("IFERROR( INDEX( INVEST_HISTORY!$A:$O, MAX(FILTER(ROW(INVEST_HISTORY!$A:$A), INVEST_HISTORY!$A:$A<>"""")), MATCH($I49, INVEST_HISTORY!$1:$1, 0) ) / INDEX( INVEST_HISTORY!$A:$O, MAX(FILTER(ROW(INVEST_HISTORY!$A:$A), INVEST_HISTOR"&"Y!$A:$A<>""""))-1, MATCH($I49, INVEST_HISTORY!$1:$1, 0) ) - 1, """") "),-1.0) -> -1 | L49: {=IF( J49="", "", IFERROR( J49 / INDEX( INVEST_HISTORY!$B$2:$O$2, 1, MATCH($I49, INVEST_HISTORY!$B$1:$O$1, 0) ) - 1, "" ) )} | P49: =IFERROR(__xludf.DUMMYFUNCTION("""COMPUTED_VALUE"""),45291.0) -> 45291 | Q49: 126.45759 | R49: 0.42284673 | S49: 0.0033550014 | T49: -2.5946102 | U49: -0.020105122 | W49: Diesel Gas | X49: 3.665 | Y49: 3.6659 | Z49: =(X49 - Y49) / Y49 -> -0.00024550588 | AA49: =IF(OR(X49="", Y49=""), "", X49 - Y49) -> -0.0009 | AB49: =IF(OR(X49="", Y49="", Y49=0), "", IF((X49 - Y49)/Y49 >= 0.1, "⬆️⬆️ MAJOR Rise", IF((X49 - Y49)/Y49 >= 0.01, "⬆️ Rise", IF((X49 - Y49)/Y49 <= -0.1, "⬇️⬇️ MAJOR Drop", IF((X49 - Y49)/Y49 <= -0.01, "⬇️ Drop", "Stable"))))) -> Stable
A50: Inital Job Loss Claims | C50: Minor | D50: 199000 | E50: =IFS( D50<=225000, 0, D50<=250000, 3, D50<=335000, 6, D50<=425000, 9, TRUE, 12 ) -> 0 | F50: =IFS( E50>=10, "🔴 High Risk", E50>=6, "🟠 Elevated Risk", E50>=3, "🟡 Moderate Risk", TRUE, "🟢 Low Risk" ) -> 🟢 Low Risk | I50: 20 yr | J50: code in repair | K50: =IFERROR(__xludf.DUMMYFUNCTION("IFERROR( INDEX( INVEST_HISTORY!$A:$O, MAX(FILTER(ROW(INVEST_HISTORY!$A:$A), INVEST_HISTORY!$A:$A<>"""")), MATCH($I50, INVEST_HISTORY!$1:$1, 0) ) / INDEX( INVEST_HISTORY!$A:$O, MAX(FILTER(ROW(INVEST_HISTORY!$A:$A), INVEST_HISTOR"&"Y!$A:$A<>""""))-1, MATCH($I50, INVEST_HISTORY!$1:$1, 0) ) - 1, """") "),-1.0) -> -1 | L50: {=IF( J50="", "", IFERROR( J50 / INDEX( INVEST_HISTORY!$B$2:$O$2, 1, MATCH($I50, INVEST_HISTORY!$B$1:$O$1, 0) ) - 1, "" ) )} | P50: =IFERROR(__xludf.DUMMYFUNCTION("""COMPUTED_VALUE"""),45199.0) -> 45199 | Q50: 126.03474 | R50: 1.0979557 | S50: 0.0087880901 | T50: -0.40688146 | U50: -0.0032179392 | W50: Kitchen Appliances | X50: 158.755 | Y50: 153.025 | Z50: =(X50 - Y50) / Y50 -> 0.037444862 | AA50: =IF(OR(X50="", Y50=""), "", X50 - Y50) -> 5.73 | AB50: =IF(OR(X50="", Y50="", Y50=0), "", IF((X50 - Y50)/Y50 >= 0.1, "⬆️⬆️ MAJOR Rise", IF((X50 - Y50)/Y50 >= 0.01, "⬆️ Rise", IF((X50 - Y50)/Y50 <= -0.1, "⬇️⬇️ MAJOR Drop", IF((X50 - Y50)/Y50 <= -0.01, "⬇️ Drop", "Stable"))))) -> ⬆️ Rise
A51: Standing Repo Usage (in $ billions) | C51: Minor | D51: 194.919 | E51: =IFS( D51=0, 0, D51<100, 3, D51<250, 6, D51<500, 9, TRUE, 12 ) -> 6 | F51: =IFS( E51>=10, "🔴 High Risk", E51>=6, "🟠 Elevated Risk", E51>=3, "🟡 Moderate Risk", TRUE, "🟢 Low Risk" ) -> 🟠 Elevated Risk | I51: 30 yr | J51: code in repair | K51: =IFERROR(__xludf.DUMMYFUNCTION("IFERROR( INDEX( INVEST_HISTORY!$A:$O, MAX(FILTER(ROW(INVEST_HISTORY!$A:$A), INVEST_HISTORY!$A:$A<>"""")), MATCH($I51, INVEST_HISTORY!$1:$1, 0) ) / INDEX( INVEST_HISTORY!$A:$O, MAX(FILTER(ROW(INVEST_HISTORY!$A:$A), INVEST_HISTOR"&"Y!$A:$A<>""""))-1, MATCH($I51, INVEST_HISTORY!$1:$1, 0) ) - 1, """") "),-1.0) -> -1 | L51: {=IF( J51="", "", IFERROR( J51 / INDEX( INVEST_HISTORY!$B$2:$O$2, 1, MATCH($I51, INVEST_HISTORY!$B$1:$O$1, 0) ) - 1, "" ) )} | P51: =IFERROR(__xludf.DUMMYFUNCTION("""COMPUTED_VALUE"""),45107.0) -> 45107 | Q51: 124.93679 | R51: -1.8585865 | S51: -0.014658157 | T51: 2.1304564 | U51: 0.0173481 | W51: Pet Food | X51: 191.49 | Y51: 189.824 | Z51: =(X51 - Y51) / Y51 -> 0.0087765509 | AA51: =IF(OR(X51="", Y51=""), "", X51 - Y51) -> 1.666 | AB51: =IF(OR(X51="", Y51="", Y51=0), "", IF((X51 - Y51)/Y51 >= 0.1, "⬆️⬆️ MAJOR Rise", IF((X51 - Y51)/Y51 >= 0.01, "⬆️ Rise", IF((X51 - Y51)/Y51 <= -0.1, "⬇️⬇️ MAJOR Drop", IF((X51 - Y51)/Y51 <= -0.01, "⬇️ Drop", "Stable"))))) -> Stable
I52: DXY | J52: code in repair | K52: =IFERROR(__xludf.DUMMYFUNCTION("IF($J52="""","""", IFERROR( $J52 / INDEX( FILTER(INVEST_HISTORY!$P$2:$P$100, INVEST_HISTORY!$P$2:$P$100<>""""), ROWS(FILTER(INVEST_HISTORY!$P$2:$P$100, INVEST_HISTORY!$P$2:$P$100<>""""))-1 ) - 1, """") )"),"") | L52: =IFERROR(__xludf.DUMMYFUNCTION("IF($J52="""","""", IFERROR( $J52 / INDEX( FILTER(INVEST_HISTORY!$P$2:$P$100, INVEST_HISTORY!$P$2:$P$100<>""""), 1 ) - 1, """") ) "),"") | P52: =IFERROR(__xludf.DUMMYFUNCTION("""COMPUTED_VALUE"""),45016.0) -> 45016 | Q52: 126.79537 | R52: -2.2568262 | S52: -0.017487701 | T52: 10.076788 | U52: 0.086334051 | W52: Computer | X52: 106.838 | Y52: 104.241 | Z52: =(X52 - Y52) / Y52 -> 0.024913422 | AA52: =IF(OR(X52="", Y52=""), "", X52 - Y52) -> 2.597 | AB52: =IF(OR(X52="", Y52="", Y52=0), "", IF((X52 - Y52)/Y52 >= 0.1, "⬆️⬆️ MAJOR Rise", IF((X52 - Y52)/Y52 >= 0.01, "⬆️ Rise", IF((X52 - Y52)/Y52 <= -0.1, "⬇️⬇️ MAJOR Drop", IF((X52 - Y52)/Y52 <= -0.01, "⬇️ Drop", "Stable"))))) -> ⬆️ Rise
P53: =IFERROR(__xludf.DUMMYFUNCTION("""COMPUTED_VALUE"""),44926.0) -> 44926 | Q53: 129.0522 | R53: 2.6105755 | S53: 0.020646488 | T53: 15.856636 | U53: 0.14008178 | W53: Lawn care | X53: 162.95 | Y53: 162.46 | Z53: =(X53 - Y53) / Y53 -> 0.003016127 | AA53: =IF(OR(X53="", Y53=""), "", X53 - Y53) -> 0.49 | AB53: =IF(OR(X53="", Y53="", Y53=0), "", IF((X53 - Y53)/Y53 >= 0.1, "⬆️⬆️ MAJOR Rise", IF((X53 - Y53)/Y53 >= 0.01, "⬆️ Rise", IF((X53 - Y53)/Y53 <= -0.1, "⬇️⬇️ MAJOR Drop", IF((X53 - Y53)/Y53 <= -0.01, "⬇️ Drop", "Stable"))))) -> Stable
P54: =IFERROR(__xludf.DUMMYFUNCTION("""COMPUTED_VALUE"""),44834.0) -> 44834 | Q54: 126.44162 | R54: 3.6352936 | S54: 0.029601842 | T54: 15.532713 | U54: 0.14004928
P55: =IFERROR(__xludf.DUMMYFUNCTION("""COMPUTED_VALUE"""),44742.0) -> 44742 | Q55: 122.80633 | R55: 6.0877454 | S55: 0.052157464 | T55: 14.840221 | U55: 0.13745259
P56: =IFERROR(__xludf.DUMMYFUNCTION("""COMPUTED_VALUE"""),44651.0) -> 44651 | Q56: 116.71858 | R56: 3.5230212 | S56: 0.031123315 | T56: 12.286536 | U56: 0.11765101
P57: =IFERROR(__xludf.DUMMYFUNCTION("""COMPUTED_VALUE"""),44561.0) -> 44561 | Q57: 113.19556 | R57: 2.2866533 | S57: 0.0206174 | T57: 9.4183799 | U57: 0.090755786
P58: =IFERROR(__xludf.DUMMYFUNCTION("""COMPUTED_VALUE"""),44469.0) -> 44469 | Q58: 110.90891 | R58: 2.9428015 | S58: 0.027256715 | T58: 7.9358858 | U58: 0.077067619
P59: =IFERROR(__xludf.DUMMYFUNCTION("""COMPUTED_VALUE"""),44377.0) -> 44377 | Q59: 107.96611 | R59: 3.5340601 | S59: 0.033840762 | T59: 4.5417076 | U59: 0.043913308
P60: =IFERROR(__xludf.DUMMYFUNCTION("""COMPUTED_VALUE"""),44286.0) -> 44286 | Q60: 104.43205 | R60: 0.65486504 | S60: 0.0063102988 | T60: 3.5438883 | U60: 0.0351269
P61: =IFERROR(__xludf.DUMMYFUNCTION("""COMPUTED_VALUE"""),44196.0) -> 44196 | Q61: 103.77718 | R61: 0.80415922 | S61: 0.0078094164 | T61: 3.2292121 | U61: 0.032116133
P62: =IFERROR(__xludf.DUMMYFUNCTION("""COMPUTED_VALUE"""),44104.0) -> 44104 | Q62: 102.97302 | R62: -0.45137676 | S62: -0.0043643159 | T62: 2.5888694 | U62: 0.025789622
P63: =IFERROR(__xludf.DUMMYFUNCTION("""COMPUTED_VALUE"""),44012.0) -> 44012 | Q63: 103.4244 | R63: 2.5362408 | S63: 0.025139132 | T63: 4.0993737 | U63: 0.041272314
P64: =IFERROR(__xludf.DUMMYFUNCTION("""COMPUTED_VALUE"""),43921.0) -> 43921 | Q64: 100.88816 | R64: 0.34018882 | S64: 0.0033833485 | T64: 0.88816018 | U64: 0.0088816018
P65: =IFERROR(__xludf.DUMMYFUNCTION("""COMPUTED_VALUE"""),43830.0) -> 43830 | Q65: 100.54797 | R65: 0.1638166 | S65: 0.001631897
P66: =IFERROR(__xludf.DUMMYFUNCTION("""COMPUTED_VALUE"""),43738.0) -> 43738 | Q66: 100.38415 | R66: 1.0591275 | S66: 0.010663249
P67: =IFERROR(__xludf.DUMMYFUNCTION("""COMPUTED_VALUE"""),43646.0) -> 43646 | Q67: 99.325027 | R67: -0.67497274 | S67: -0.0067497274
P68: =IFERROR(__xludf.DUMMYFUNCTION("""COMPUTED_VALUE"""),43555.0) -> 43555 | Q68: 100

Sheet FRED_HISTORY
A1: Date | B1: Median Home Value | C1: Median New Home Sale Price | D1: Mortgage Rate | E1: Fed Funds Rate | F1: 10-Year Treasury Yield | G1: Core Inflation (Sticky) | H1: Housing Affordability Index | I1: Median Household Income | J1: Total Inventory | K1: New Construction Inventory | L1: Building Permits | M1: Unemployment Rate | N1: Mortgage Delinquency | O1: Disposable Income Share | P1: Foreclosure Rate | Q1: Business Loan Delinquency | R1: All Loans Delinquency | S1: Credit Card Delinquency | T1: Rental Vacancy Rate | U1: Job Openings | V1: U6 Unemployment Rate | W1: Temp Help Employment | X1: Lumber | Y1: Steel | Z1: Shingles | AA1: Plumbing | AB1: Concrete | AC1: Power (per KWH) | AD1: Milk | AE1: Eggs | AF1: Bread | AG1: Chicken (boneless) | AH1: Home Insurance | AI1: Auto Insurance | AJ1: Medical Care | AK1: Food Overall | AL1: Doors & Windows | AM1: HVAC System | AN1: Fridge | AO1: Water Heater | AP1: Beef | AQ1: Coffee | AR1: Car Parts | AS1: Childcare / Education | AT1: Clothing | AU1: Used Car | AV1: Health Insurance (PPI) | AW1: Rent | AX1: Natural Gas | AY1: Water/Sewer/Trash (CPI) | AZ1: Public Transit Fares | BA1: Furniture | BB1: Cleaning Supplies | BC1: Cable / Streaming TV | BD1: Internet / IT | BE1: Food Away From Home | BF1: Personal Care | BG1: Rice per lb | BH1: White Flour per lb | BI1: White Sugar per lb | BJ1: Tomatoes per lb | BK1: Bananas per lb | BL1: Potatoes per lb | BM1: Lettuce per lb | BN1: Cheddar Cheese per lb | BO1: Bacon per lb | BP1: Potato Chips | BQ1: Disposable Diapers | BR1: Oranges per lb | BS1: Tissue Paper / Toilet Paper | BT1: Trash Collection (PPI)
A2: 45688 | B2: 393400 | C2: 429600 | D2: 0.0695 | E2: 0.0433 | F2: 0.0458 | G2: 0.036252763 | H2: 101.6 | I2: 80610 | J2: 829376 | K2: 496000 | L2: 1460000 | M2: 0.04 | N2: 0.0178 | O2: 0.11257759 | P2: 0.0047 | Q2: 0.0129 | R2: 0.0156 | S2: 0.0306 | T2: 0.071 | U2: 7762000 | V2: 0.075 | W2: 2543800 | X2: 267.542 | Y2: 131.669 | Z2: 359.216 | AA2: 421.341 | AB2: 251.215 | AC2: 0.179 | AD2: 4.025 | AE2: 4.953 | AF2: 1.925 | AG2: 3.969 | AH2: 261.261 | AI2: 217.268 | AJ2: 571.234 | AK2: 335.671 | AL2: 429.678 | AM2: 222.5 | AN2: 131.262 | AO2: 591.449 | AP2: 5.545 | AQ2: 7.019 | AR2: 182.985 | AS2: 879.514 | AT2: 128.175 | AU2: 185.424 | AV2: 160.448 | AW2: 429.017 | AX2: 1.552 | AY2: 310.239 | AZ2: 264.669 | BA2: 148.308 | BB2: 236.131 | BC2: 595.023 | BD2: 6.766 | BE2: 375.532 | BF2: 351.736 | BG2: 1.008 | BH2: 0.561 | BI2: 1.011 | BJ2: 2.05 | BK2: 0.621 | BL2: 0.973 | BM2: 2.831 | BN2: 5.698 | BO2: 7.044 | BP2: 6.474 | BQ2: 104.949 | BR2: 1.531 | BS2: 144.932 | BT2: 194.665
A3: 45716 | B3: 396800 | C3: 415100 | D3: 0.0676 | E3: 0.0433 | F3: 0.0424 | G3: 0.035165153 | H3: 102.5 | I3: 80610 | J3: 847825 | K3: 499000 | L3: 1454000 | M3: 0.041 | N3: 0.0178 | O3: 0.11257759 | P3: 0.0047 | Q3: 0.0129 | R3: 0.0156 | S3: 0.0306 | T3: 0.071 | U3: 7480000 | V3: 0.08 | W3: 2541600 | X3: 274.907 | Y3: 133.158 | Z3: 356.041 | AA3: 421.341 | AB3: 251.468 | AC3: 0.179 | AD3: 4.026 | AE3: 5.897 | AF3: 1.925 | AG3: 4.079 | AH3: 261.775 | AI3: 218.12 | AJ3: 572.797 | AK3: 336.223 | AL3: 430.286 | AM3: 223.835 | AN3: 130.747 | AO3: 591.449 | AP3: 5.625 | AQ3: 7.246 | AR3: 182.12 | AS3: 881.006 | AT3: 128.862 | AU3: 187.057 | AV3: 160.746 | AW3: 430.224 | AX3: 1.584 | AY3: 313.344 | AZ3: 261.231 | BA3: 149.408 | BB3: 236.131 | BC3: 599.392 | BD3: 6.805 | BE3: 376.991 | BF3: 353.165 | BG3: 1.03 | BH3: 0.561 | BI3: 1.012 | BJ3: 1.848 | BK3: 0.619 | BL3: 0.957 | BM3: 2.865 | BN3: 5.536 | BO3: 6.798 | BP3: 6.462 | BQ3: 104.949 | BR3: 1.536 | BS3: 145.166 | BT3: 196.708
A4: 45747 | B4: 403100 | C4: 412900 | D4: 0.0665 | E4: 0.0433 | F4: 0.0423 | G4: 0.032578151 | H4: 103.5 | I4: 80610 | J4: 892561 | K4: 504000 | L4: 1481000 | M4: 0.042 | N4: 0.0178 | O4: 0.11257759 | P4: 0.0047 | Q4: 0.0129 | R4: 0.0156 | S4: 0.0306 | T4: 0.071 | U4: 7200000 | V4: 0.079 | W4: 2527300 | X4: 287.961 | Y4: 132.455 | Z4: 355.373 | AA4: 421.341 | AB4: 251.42 | AC4: 0.181 | AD4: 4.05 | AE4: 6.227 | AF4: 1.88 | AG4: 4.16 | AH4: 263.589 | AI4: 222.027 | AJ4: 573.966 | AK4: 337.686 | AL4: 434.714 | AM4: 223.791 | AN4: 130.847 | AO4: 591.449 | AP4: 5.79 | AQ4: 7.385 | AR4: 181.89 | AS4: 884.67 | AT4: 126.726 | AU4: 185.772 | AV4: 160.964 | AW4: 431.655 | AX4: 1.596 | AY4: 313.925 | AZ4: 256.412 | BA4: 149.42 | BB4: 236.131 | BC4: 594.03 | BD4: 6.829 | BE4: 378.363 | BF4: 353.554 | BG4: 1.038 | BH4: 0.565 | BI4: 1.014 | BJ4: 1.819 | BK4: 0.625 | BL4: 0.95 | BM4: 2.923 | BN4: 5.737 | BO4: 6.978 | BP4: 6.536 | BQ4: 106.133 | BR4: 1.484 | BS4: 148.794 | BT4: 202.175
A5: 45777 | B5: 414000 | C5: 413600 | D5: 0.0681 | E5: 0.0433 | F5: 0.0417 | G5: 0.031766899 | H5: 100.9 | I5: 80610 | J5: 959251 | K5: 500000 | L5: 1422000 | M5: 0.042 | N5: 0.0178 | O5: 0.11249194 | P5: 0.006 | Q5: 0.0128 | R5: 0.0147 | S5: 0.0304 | T5: 0.07 | U5: 7395000 | V5: 0.078 | W5: 2544200 | X5: 280.407 | Y5: 135.495 | Z5: 352.468 | AA5: 428.847 | AB5: 250.895 | AC5: 0.181 | AD5: 4.074 | AE5: 5.122 | AF5: 1.913 | AG5: 4.18 | AH5: 263.858 | AI5: 221.749 | AJ5: 576.785 | AK5: 337.424 | AL5: 437.606 | AM5: 226.566 | AN5: 130.962 | AO5: 591.449 | AP5: 5.801 | AQ5: 7.536 | AR5: 181.709 | AS5: 885.988 | AT5: 128.994 | AU5: 184.783 | AV5: 161.532 | AW5: 433.13 | AX5: 1.626 | AY5: 314.82 | AZ5: 258.686 | BA5: 150.485 | BB5: 236.131 | BC5: 591.592 | BD5: 6.782 | BE5: 380.039 | BF5: 353.939 | BG5: 1.031 | BH5: 0.557 | BI5: 1.021 | BJ5: 1.793 | BK5: 0.635 | BL5: 0.967 | BM5: 2.915 | BN5: 5.743 | BO5: 7.009 | BP5: 6.611 | BQ5: 106.133 | BR5: 1.485 | BS5: 148.606 | BT5: 201.195
A6: 45808 | B6: 423700 | C6: 424800 | D6: 0.0689 | E6: 0.0433 | F6: 0.0441 | G6: 0.031591311 | H6: 97.1 | I6: 83730 | J6: 1036101 | K6: 504000 | L6: 1394000 | M6: 0.042 | N6: 0.0178 | O6: 0.11249194 | P6: 0.006 | Q6: 0.0128 | R6: 0.0147 | S6: 0.0304 | T6: 0.07 | U6: 7712000 | V6: 0.078 | W6: 2529000 | X6: 271.479 | Y6: 139.919 | Z6: 365.694 | AA6: 438.959 | AB6: 252.303 | AC6: 0.182 | AD6: 4.022 | AE6: 4.548 | AF6: 1.876 | AG6: 4.216 | AH6: 264.252 | AI6: 222.217 | AJ6: 578.236 | AK6: 338.386 | AL6: 437.456 | AM6: 229.204 | AN6: 132.461 | AO6: 641.379 | AP6: 5.981 | AQ6: 7.931 | AR6: 183.402 | AS6: 888.536 | AT6: 131.974 | AU6: 183.779 | AV6: 161.917 | AW6: 434.054 | AX6: 1.626 | AY6: 315.585 | AZ6: 261.734 | BA6: 150.69 | BB6: 236.131 | BC6: 595.208 | BD6: 6.778 | BE6: 381.228 | BF6: 355.642 | BG6: 1.067 | BH6: 0.562 | BI6: 1.054 | BJ6: 1.705 | BK6: 0.655 | BL6: 0.958 | BM6: 2.994 | BN6: 5.908 | BO6: 6.985 | BP6: 6.731 | BQ6: 106.133 | BR6: 1.564 | BS6: 148.885 | BT6: 200.623
A7: 45838 | B7: 432700 | C7: 403600 | D7: 0.0677 | E7: 0.0433 | F7: 0.0424 | G7: 0.03288774 | H7: 95.1 | I7: 83730 | J7: 1082520 | K7: 503000 | L7: 1393000 | M7: 0.041 | N7: 0.0178 | O7: 0.11249194 | P7: 0.006 | Q7: 0.0128 | R7: 0.0147 | S7: 0.0304 | T7: 0.07 | U7: 7357000 | V7: 0.077 | W7: 2519000 | X7: 266.343 | Y7: 144.144 | Z7: 367.402 | AA7: 438.959 | AB7: 252.308 | AC7: 0.19 | AD7: 4.029 | AE7: 3.775 | AF7: 1.864 | AG7: 4.239 | AH7: 264.439 | AI7: 222.183 | AJ7: 580.978 | AK7: 339.498 | AL7: 444.218 | AM7: 231.425 | AN7: 134.217 | AO7: 641.379 | AP7: 6.12 | AQ7: 8.132 | AR7: 184.509 | AS7: 890.277 | AT7: 136.564 | AU7: 182.543 | AV7: 162.375 | AW7: 435.038 | AX7: 1.653 | AY7: 316.851 | AZ7: 258.924 | BA7: 152.394 | BB7: 236.131 | BC7: 597.347 | BD7: 6.797 | BE7: 382.75 | BF7: 357.641 | BG7: 1.061 | BH7: 0.574 | BI7: 1.054 | BJ7: 1.737 | BK7: 0.654 | BL7: 0.981 | BM7: 2.951 | BN7: 5.999 | BO7: 7.098 | BP7: 6.815 | BQ7: 106.133 | BR7: 1.633 | BS7: 148.832 | BT7: 199.748
A8: 45869 | B8: 425700 | C8: 395100 | D8: 0.0672 | E8: 0.0433 | F8: 0.0437 | G8: 0.034198105 | H8: 97.9 | I8: 83730 | J8: 1102787 | K8: 497000 | L8: 1362000 | M8: 0.042 | N8: 0.0178 | O8: 0.11249194 | P8: 0.006 | Q8: 0.0133 | R8: 0.0147 | S8: 0.0298 | T8: 0.07 | U8: 7208000 | V8: 0.079 | W8: 2504000 | X8: 261.368 | Y8: 143.349 | Z8: 367.122 | AA8: 463.869 | AB8: 252.104 | AC8: 0.189 | AD8: 4.162 | AE8: 3.599 | AF8: 1.851 | AG8: 4.204 | AH8: 265.354 | AI8: 222.286 | AJ8: 584.77 | AK8: 339.652 | AL8: 444.383 | AM8: 232.833 | AN8: 135.085 | AO8: 641.381 | AP8: 6.254 | AQ8: 8.414 | AR8: 186.085 | AS8: 893.568 | AT8: 133.021 | AU8: 183.419 | AV8: 163.448 | AW8: 436.152 | AX8: 1.642 | AY8: 318.244 | AZ8: 254.018 | BA8: 152.865 | BB8: 236.131 | BC8: 594.484 | BD8: 6.758 | BE8: 383.808 | BF8: 357.824 | BG8: 1.068 | BH8: 0.557 | BI8: 1.046 | BJ8: 1.793 | BK8: 0.657 | BL8: 0.978 | BM8: 3.006 | BN8: 6.041 | BO8: 7.118 | BP8: 6.797 | BQ8: 106.133 | BR8: 1.77 | BS8: 150.033 | BT8: 202.015
A9: 45900 | B9: 422400 | C9: 413500 | D9: 0.0656 | E9: 0.0433 | F9: 0.0423 | G9: 0.034 | H9: 100.6 | I9: 83730 | J9: 1098681 | K9: 490000 | L9: 1330000 | M9: 0.043 | N9: 0.0178 | O9: 0.11249194 | P9: 0.006 | Q9: 0.0133 | R9: 0.0147 | S9: 0.0298 | T9: 0.07 | U9: 7227000 | V9: 0.081 | W9: 2493900 | X9: 263.714 | Y9: 144.126 | Z9: 369.985 | AA9: 463.869 | AB9: 252.682 | AC9: 0.19 | AD9: 4.171 | AE9: 3.587 | AF9: 1.841 | AG9: 4.212 | AH9: 265.897 | AI9: 222.351 | AJ9: 583.832 | AK9: 341.208 | AL9: 472.839 | AM9: 233.259 | AN9: 133.343 | AO9: 641.381 | AP9: 6.318 | AQ9: 8.872 | AR9: 187.124 | AS9: 895.305 | AT9: 135.835 | AU9: 185.322 | AV9: 163.484 | AW9: 437.462 | AX9: 1.634 | AY9: 319.403 | AZ9: 254.848 | BA9: 153.039 | BB9: 236.131 | BC9: 592.604 | BD9: 6.797 | BE9: 384.909 | BF9: 359.588 | BG9: 1.059 | BH9: 0.557 | BI9: 1.04 | BJ9: 1.925 | BK9: 0.666 | BL9: 1.001 | BM9: 3.006 | BN9: 6.123 | BO9: 7.208 | BP9: 6.751 | BQ9: 106.133 | BR9: 1.795 | BS9: 149.826 | BT9: 202.325
A10: 45930 | B10: 412300 | C10: 413500 | D10: 0.063 | E10: 0.0422 | F10: 0.0416 | G10: 0.033260801 | H10: 104.5 | I10: 83730 | J10: 1100407 | K10: 490000 | L10: 1330000 | M10: 0.044 | N10: 0.0178 | O10: 0.11249194 | P10: 0.006 | Q10: 0.0133 | R10: 0.0147 | S10: 0.0298 | T10: 0.07 | U10: 7227000 | V10: 0.08 | W10: 2478000 | X10: 252.735 | Y10: 143.246 | Z10: 369.258 | AA10: 463.869 | AB10: 252.99 | AC10: 0.188 | AD10: 4.129 | AE10: 3.488 | AF10: 1.867 | AG10: 4.172 | AH10: 266.307 | AI10: 222.465 | AJ10: 585.097 | AK10: 342.054 | AL10: 473.057 | AM10: 233.063 | AN10: 134.751 | AO10: 641.381 | AP10: 6.323 | AQ10: 9.139 | AR10: 188.028 | AS10: 897.302 | AT10: 132.588 | AU10: 184.568 | AV10: 163.883 | AW10: 438.322 | AX10: 1.613 | AY10: 319.867 | AZ10: 259.202 | BA10: 154.023 | BB10: 236.131 | BC10: 593.928 | BD10: 6.772 | BE10: 385.451 | BF10: 362.968 | BG10: 1.06 | BH10: 0.563 | BI10: 1.042 | BJ10: 1.91 | BK10: 0.67 | BL10: 1.014 | BM10: 3.006 | BN10: 6.049 | BO10: 7.29 | BP10: 6.971 | BQ10: 106.133 | BR10: 1.803 | BS10: 150.867 | BT10: 204.967
A11: 45961 | B11: 415200 | D11: 0.0617 | E11: 0.0409 | F11: 0.0411 | J11: 1100001

Sheet FRED_HISTORY_QUARTERLY
A1: Date | B1: Median Home Value | C1: Median New Home Sale Price | D1: Mortgage Rate | E1: Fed Funds Rate | F1: 10-Year Treasury Yield | G1: Core Inflation (Sticky) | H1: Housing Affordability Index | I1: Median Household Income | J1: Total Inventory | K1: New Construction Inventory | L1: Building Permits | M1: Unemployment Rate | N1: Mortgage Delinquency | O1: Disposable Income Share | P1: Foreclosure Rate | Q1: Business Loan Delinquency | R1: All Loans Delinquency | S1: Credit Card Delinquency | T1: Rental Vacancy Rate | U1: Job Openings | V1: U6 Unemployment Rate | W1: Temp Help Employment | X1: Lumber | Y1: Steel | Z1: Shingles | AA1: Plumbing | AB1: Concrete | AC1: Power (per KWH) | AD1: Milk | AE1: Eggs | AF1: Bread | AG1: Chicken (boneless) | AH1: Home Insurance | AI1: Auto Insurance | AJ1: Medical Care | AK1: Food Overall | AL1: Doors & Windows | AM1: HVAC System | AN1: Fridge | AO1: Water Heater | AP1: Beef | AQ1: Coffee | AR1: Car Parts | AS1: Childcare / Education | AT1: Clothing | AU1: Used Car | AV1: Health Insurance (PPI) | AW1: Rent | AX1: Natural Gas | AY1: Water/Sewer/Trash (CPI) | AZ1: Public Transit Fares | BA1: Furniture | BB1: Cleaning Supplies | BC1: Cable / Streaming TV | BD1: Internet / IT | BE1: Food Away From Home | BF1: Personal Care | BG1: Rice per lb | BH1: White Flour per lb | BI1: White Sugar per lb | BJ1: Tomatoes per lb | BK1: Bananas per lb | BL1: Potatoes per lb | BM1: Lettuce per lb | BN1: Cheddar Cheese per lb | BO1: Bacon per lb | BP1: Potato Chips | BQ1: Disposable Diapers | BR1: Oranges per lb | BS1: Tissue Paper / Toilet Paper | BT1: Trash Collection (PPI) | BU1: econ index
A2: 33328 | B2: 100600 | C2: 122500 | D2: 0.0952 | E2: 0.0612 | F2: 0.0805 | G2: 0.054742846 | I2: 63530 | K2: 308000 | L2: 911000 | M2: 0.068 | N2: 0.0309 | O2: 0.11565484 | Q2: 0.0629 | R2: 0.0638 | S2: 0.0526 | T2: 0.075 | W2: 1116100 | X2: 117.2 | Z2: 101.6 | AA2: 170.4 | AC2: 0.085 | AE2: 1.069 | AF2: 0.702 | AJ2: 173.2 | AK2: 135.3 | AL2: 133.6 | AO2: 124.5 | AP2: 1.61 | AQ2: 2.894 | AR2: 101.3 | AS2: 186.2 | AU2: 116.8 | AW2: 142.1 | AX2: 0.599 | AZ2: 153.3 | BA2: 115.7 | BB2: 128.5 | BE2: 136.5 | BF2: 135.8 | BG2: 0.498 | BH2: 0.235 | BI2: 0.434 | BJ2: 0.948 | BK2: 0.577 | BL2: 0.327 | BN2: 3.548 | BO2: 2.318 | BP2: 2.954 | BR2: 0.93
A3: 33419 | B3: 104400 | C3: 119000 | D3: 0.0967 | E3: 0.059 | F3: 0.0824 | G3: 0.049346539 | I3: 63530 | K3: 295000 | L3: 964000 | M3: 0.069 | N3: 0.0318 | O3: 0.11419594 | Q3: 0.0641 | R3: 0.0604 | S3: 0.0548 | T3: 0.073 | W3: 1113700 | X3: 138.2 | Z3: 100.2 | AA3: 170.6 | AC3: 0.09 | AE3: 0.884 | AF3: 0.705 | AJ3: 176.4 | AK3: 137.4 | AL3: 133.3 | AO3: 124.4 | AP3: 1.604 | AQ3: 2.866 | AR3: 101.7 | AS3: 190 | AU3: 118.4 | AW3: 143.2 | AX3: 0.586 | AZ3: 146.6 | BA3: 115.9 | BE3: 137.8 | BF3: 137.3 | BG3: 0.506 | BH3: 0.237 | BI3: 0.432 | BJ3: 1.672 | BK3: 0.532 | BL3: 0.386 | BN3: 3.528 | BO3: 2.305 | BP3: 3.062
A4: 33511 | B4: 102900 | C4: 120000 | D4: 0.0892 | E4: 0.0545 | F4: 0.0747 | G4: 0.044435948 | I4: 63530 | K4: 291000 | L4: 974000 | M4: 0.069 | N4: 0.0323 | O4: 0.11306831 | Q4: 0.0622 | R4: 0.0593 | S4: 0.0535 | T4: 0.076 | W4: 1130500 | X4: 126.1 | Z4: 98.9 | AA4: 171.3 | AC4: 0.091 | AE4: 0.987 | AF4: 0.717 | AJ4: 179.9 | AK4: 136.4 | AL4: 133.3 | AO4: 123.9 | AP4: 1.553 | AQ4: 2.692 | AR4: 102.5 | AS4: 196.5 | AU4: 118.4 | AW4: 144.4 | AX4: 0.589 | AZ4: 146.6 | BA4: 116.4 | BB4: 129.3 | BE4: 138.9 | BF4: 137.8 | BG4: 0.506 | BH4: 0.232 | BI4: 0.422 | BJ4: 0.759 | BK4: 0.432 | BL4: 0.314 | BN4: 3.597 | BO4: 2.16 | BP4: 2.901
A5: 33603 | B5: 103100 | C5: 122000 | D5: 0.0835 | E5: 0.0443 | F5: 0.0671 | G5: 0.043469677 | I5: 63530 | K5: 284000 | L5: 1061000 | M5: 0.073 | N5: 0.0328 | O5: 0.11110772 | Q5: 0.0603 | R5: 0.0582 | S5: 0.0532 | T5: 0.073 | W5: 1139000 | X5: 129.7 | Z5: 97.3 | AA5: 171.9 | AC5: 0.085 | AE5: 1.012 | AF5: 0.717 | AJ5: 183.1 | AK5: 137 | AL5: 133.3 | AO5: 123.9 | AP5: 1.577 | AQ5: 2.625 | AR5: 103.2 | AS5: 199.6 | AU5: 119.1 | AW5: 145.1 | AX5: 0.606 | AZ5: 149.8 | BA5: 116.3 | BE5: 139.6 | BF5: 138 | BG5: 0.51 | BH5: 0.223 | BI5: 0.418 | BJ5: 0.793 | BK5: 0.419 | BL5: 0.283 | BN5: 3.534 | BO5: 1.994 | BP5: 2.954 | BR5: 0.652
A6: 33694 | B6: 105100 | C6: 120000 | D6: 0.0898 | E6: 0.0398 | F6: 0.0754 | G6: 0.039758443 | I6: 63010 | K6: 279000 | L6: 1082000 | M6: 0.074 | N6: 0.0312 | O6: 0.10858007 | Q6: 0.0576 | R6: 0.0577 | S6: 0.0527 | T6: 0.074 | W6: 1170500 | X6: 152.9 | Z6: 96.5 | AA6: 175.4 | AC6: 0.086 | AE6: 0.85 | AF6: 0.747 | AJ6: 186.8 | AK6: 137.6 | AL6: 133.1 | AO6: 128.5 | AP6: 1.545 | AQ6: 2.631 | AR6: 103.4 | AS6: 203.5 | AU6: 118.6 | AW6: 146.5 | AX6: 0.567 | AZ6: 153.5 | BA6: 117.7 | BB6: 129.3 | BC6: 183.3 | BE6: 140.1 | BF6: 139.6 | BG6: 0.515 | BH6: 0.239 | BI6: 0.419 | BJ6: 1.729 | BK6: 0.517 | BL6: 0.28 | BN6: 3.612 | BO6: 1.922 | BP6: 2.943 | BR6: 0.563
A7: 33785 | B7: 107000 | C7: 124500 | D7: 0.0843 | E7: 0.0376 | F7: 0.0714 | G7: 0.038601886 | I7: 63010 | K7: 273000 | L7: 1057000 | M7: 0.078 | N7: 0.0306 | O7: 0.10688985 | Q7: 0.0549 | R7: 0.053 | S7: 0.051 | T7: 0.077 | W7: 1208400 | X7: 148.2 | Z7: 97.1 | AA7: 176.9 | AC7: 0.092 | AE7: 0.801 | AF7: 0.757 | AJ7: 189.6 | AK7: 137.6 | AL7: 133.6 | AO7: 127.9 | AP7: 1.535 | AQ7: 2.625 | AR7: 103.2 | AS7: 207.8 | AU7: 122.5 | AW7: 146.7 | AX7: 0.582 | AZ7: 145.3 | BA7: 118.2 | BC7: 185.9 | BE7: 140.6 | BF7: 139.9 | BG7: 0.52 | BH7: 0.244 | BI7: 0.415 | BJ7: 0.747 | BK7: 0.463 | BL7: 0.294 | BN7: 3.588 | BO7: 1.926 | BP7: 2.906 | BR7: 0.573
A8: 33877 | B8: 105600 | C8: 119500 | D8: 0.0802 | E8: 0.0322 | F8: 0.0637 | G8: 0.033492378 | I8: 63010 | K8: 265000 | L8: 1114000 | M8: 0.076 | N8: 0.0288 | O8: 0.10551259 | Q8: 0.0525 | R8: 0.0516 | S8: 0.0498 | T8: 0.073 | W8: 1231300 | X8: 147.3 | Z8: 97.3 | AA8: 176.1 | AC8: 0.092 | AE8: 0.873 | AF8: 0.756 | AJ8: 192.4 | AK8: 138.9 | AL8: 134.4 | AO8: 127.8 | AP8: 1.521 | AQ8: 2.537 | AR8: 103.2 | AS8: 212.1 | AU8: 126.2 | AW8: 147.1 | AX8: 0.604 | AZ8: 145.6 | BA8: 118.3 | BB8: 129.9 | BC8: 186.7 | BE8: 141.2 | BF8: 140.1 | BG8: 0.542 | BH8: 0.249 | BI8: 0.41 | BJ8: 0.765 | BK8: 0.459 | BL8: 0.33 | BN8: 3.565 | BO8: 1.925 | BP8: 2.856
A9: 33969 | B9: 105600 | C9: 126000 | D9: 0.0814 | E9: 0.0292 | F9: 0.067 | G9: 0.034782626 | I9: 63010 | K9: 265000 | L9: 1176000 | M9: 0.074 | N9: 0.0279 | O9: 0.10467593 | Q9: 0.0476 | R9: 0.0484 | S9: 0.0469 | T9: 0.071 | W9: 1282800 | X9: 159.6 | Z9: 99.4 | AA9: 176.1 | AC9: 0.088 | AE9: 0.928 | AF9: 0.738 | AJ9: 195.3 | AK9: 138.8 | AL9: 134.2 | AO9: 127.8 | AP9: 1.5 | AQ9: 2.364 | AR9: 102.6 | AS9: 216.7 | AU9: 128 | AW9: 148.5 | AX9: 0.623 | AZ9: 158.2 | BA9: 118.2 | BC9: 188.4 | BE9: 141.6 | BF9: 141.3 | BG9: 0.525 | BH9: 0.233 | BI9: 0.406 | BJ9: 1.227 | BK9: 0.404 | BL9: 0.308 | BN9: 3.395 | BO9: 1.863 | BP9: 2.84 | BR9: 0.516
A10: 34059 | B10: 105100 | C10: 125000 | D10: 0.075 | E10: 0.0307 | F10: 0.0603 | G10: 0.033344281 | I10: 62700 | K10: 270000 | L10: 1056000 | M10: 0.07 | N10: 0.0278 | O10: 0.10430733 | Q10: 0.0441 | R10: 0.0469 | S10: 0.046 | T10: 0.078 | W10: 1318800 | X10: 212 | Z10: 98.9 | AA10: 178.1 | AC10: 0.088 | AE10: 0.927 | AF10: 0.742 | AJ10: 198.1 | AK10: 139.6 | AL10: 134.9 | AO10: 130.2 | AP10: 1.562 | AQ10: 2.462 | AR10: 102.1 | AS10: 220.9 | AU10: 126.6 | AW10: 149.1 | AX10: 0.616 | AZ10: 163.5 | BA10: 118.7 | BB10: 130.6 | BC10: 199.4 | BE10: 142.4 | BF10: 142.9 | BG10: 0.525 | BH10: 0.238 | BI10: 0.406 | BJ10: 0.88 | BK10: 0.475 | BL10: 0.327 | BN10: 3.35 | BO10: 1.802 | BP10: 2.839 | BR10: 0.506
A11: 34150 | B11: 111900 | C11: 124500 | D11: 0.0734 | E11: 0.0304 | F11: 0.058 | G11: 0.035693269 | I11: 62700 | K11: 275000 | L11: 1130000 | M11: 0.07 | N11: 0.0267 | O11: 0.10365702 | Q11: 0.0401 | R11: 0.0411 | S11: 0.0446 | T11: 0.076 | W11: 1379500 | X11: 185.8 | Z11: 98.2 | AA11: 179 | AC11: 0.094 | AE11: 0.921 | AF11: 0.752 | AJ11: 201.3 | AK11: 140.6 | AL11: 135.7 | AO11: 135.2 | AP11: 1.562 | AQ11: 2.533 | AR11: 101.5 | AS11: 224.8 | AU11: 134.3 | AW11: 150.4 | AX11: 0.636 | AZ11: 164.5 | BA11: 119.1 | BC11: 198.4 | BE11: 143.2 | BF11: 143.3 | BG11: 0.518 | BH11: 0.238 | BI11: 0.403 | BJ11: 1.278 | BK11: 0.446 | BL11: 0.379 | BN11: 3.331 | BO11: 1.949 | BP11: 2.827 | BR11: 0.549
A12: 34242 | B12: 110500 | C12: 129400 | D12: 0.0695 | E12: 0.0309 | F12: 0.054 | G12: 0.036423837 | I12: 62700 | K12: 287000 | L12: 1251000 | M12: 0.067 | N12: 0.0259 | O12: 0.10417195 | Q12: 0.0361 | R12: 0.0383 | S12: 0.0408 | T12: 0.07 | W12: 1424200 | X12: 185.9 | Z12: 97.7 | AA12: 180.6 | AC12: 0.097 | AE12: 0.89 | AF12: 0.748 | AJ12: 203.6 | AK12: 141.4 | AL12: 136 | AO12: 133.8 | AP12: 1.551 | AQ12: 2.493 | AR12: 101.2 | AS12: 228.5 | AU12: 138.7 | AW12: 151 | AX12: 0.646 | AZ12: 168.4 | BA12: 119.6 | BB12: 130.9 | BC12: 201.8 | BE12: 143.8 | BF12: 145.3 | BG12: 0.494 | BH12: 0.232 | BI12: 0.404 | BJ12: 1.092 | BK12: 0.395 | BL12: 0.341 | BN12: 3.336 | BO12: 1.982 | BP12: 2.895
A13: 34334 | B13: 110800 | C13: 125000 | D13: 0.0713 | E13: 0.0296 | F13: 0.0583 | G13: 0.035484759 | I13: 62700 | K13: 293000 | L13: 1461000 | M13: 0.065 | N13: 0.0244 | O13: 0.10380138 | Q13: 0.0305 | R13: 0.0338 | S13: 0.0391 | T13: 0.069 | W13: 1485100 | X13: 208.8 | Z13: 96.8 | AA13: 180.4 | AC13: 0.09 | AE13: 0.871 | AF13: 0.76 | AJ13: 205.8 | AK13: 142.8 | AL13: 135.9 | AO13: 134.2 | AP13: 1.574 | AQ13: 2.48 | AR13: 101.1 | AS13: 232.2 | AU13: 139.3 | AW13: 151.9 | AX13: 0.662 | AZ13: 176.5 | BA13: 120.3 | BC13: 202.1 | BE13: 144.3 | BF13: 146.1 | BG13: 0.495 | BH13: 0.222 | BI13: 0.398 | BJ13: 1.313 | BK13: 0.414 | BL13: 0.364 | BN13: 3.361 | BO13: 2.018 | BP13: 2.918 | BR13: 0.556
A14: 34424 | B14: 109800 | C14: 132300 | D14: 0.078 | E14: 0.0334 | F14: 0.0677 | G14: 0.035701509 | I14: 63370 | K14: 298000 | L14: 1342000 | M14: 0.065 | N14: 0.0239 | O14: 0.10401077 | Q14: 0.0279 | R14: 0.0329 | S14: 0.036 | T14: 0.075 | V14: 0.115 | W14: 1567200 | X14: 210.2 | Z14: 95.3 | AA14: 181.7 | AC14: 0.089 | AE14: 0.926 | AF14: 0.755 | AJ14: 207.9 | AK14: 142.7 | AL14: 137.4 | AO14: 138.2 | AP14: 1.576 | AQ14: 2.515 | AR14: 101.4 | AS14: 235.8 | AU14: 133.6 | AW14: 153.2 | AX14: 0.666 | AZ14: 178.5 | BA14: 120.6 | BB14: 131.9 | BC14: 199.5 | BE14: 144.8 | BF14: 146.6 | BG14: 0.556 | BH14: 0.226 | BI14: 0.401 | BJ14: 0.914 | BK14: 0.5 | BL14: 0.395 | BN14: 3.409 | BO14: 2.017 | BP14: 2.97 | BR14: 0.52
A15: 34515 | B15: 116600 | C15: 133500 | D15: 0.0846 | E15: 0.0425 | F15: 0.0734 | G15: 0.031947385 | I15: 63370 | K15: 315000 | L15: 1357000 | M15: 0.061 | N15: 0.0226 | O15: 0.10466155 | Q15: 0.024 | R15: 0.028 | S15: 0.0329 | T15: 0.074 | V15: 0.11 | W15: 1627600 | X15: 199.8 | Z15: 96 | AA15: 182.5 | AC15: 0.095 | AE15: 0.841 | AF15: 0.761 | AJ15: 210.5 | AK15: 143.8 | AL15: 139.8 | AO15: 137.3 | AP15: 1.511 | AQ15: 2.598 | AR15: 101.8 | AS15: 239.5 | AU15: 140.9 | AW15: 153.5 | AX15: 0.642 | AZ15: 169.9 | BA15: 121.4 | BC15: 197.8 | BE15: 145.5 | BF15: 148.8 | BG15: 0.555 | BH15: 0.236 | BI15: 0.397 | BJ15: 1.047 | BK15: 0.447 | BL15: 0.39 | BN15: 3.28 | BO15: 1.985 | BP15: 2.968 | BR15: 0.618
A16: 34607 | B16: 113300 | C16: 129700 | D16: 0.0882 | E16: 0.0473 | F16: 0.0762 | G16: 0.032542816 | I16: 63370 | K16: 331000 | L16: 1412000 | M16: 0.059 | N16: 0.0216 | O16: 0.1060019 | Q16: 0.0222 | R16: 0.0263 | S16: 0.0325 | T16: 0.072 | V16: 0.104 | W16: 1681100 | X16: 192.9 | Z16: 96.3 | AA16: 183.6 | AC16: 0.096 | AE16: 0.855 | AF16: 0.776 | AJ16: 213.1 | AK16: 145.3 | AL16: 142.5 | AO16: 138.3 | AP16: 1.463 | AQ16: 4.458 | AR16: 101 | AS16: 242.6 | AU16: 145.4 | AW16: 155 | AX16: 0.639 | AZ16: 171.7 | BA16: 121.4 | BB16: 132.7 | BC16: 194.5 | BE16: 146.2 | BF16: 148.7 | BG16: 0.534 | BH16: 0.237 | BI16: 0.403 | BJ16: 0.958 | BK16: 0.453 | BL16: 0.355 | BN16: 3.39 | BO16: 1.973 | BP16: 2.965
A17: 34699 | B17: 113600 | C17: 135000 | D17: 0.0918 | E17: 0.0545 | F17: 0.0784 | G17: 0.029014466 | I17: 63370 | K17: 336000 | L17: 1396000 | M17: 0.055 | N17: 0.0206 | O17: 0.10713335 | Q17: 0.0218 | R17: 0.0251 | S17: 0.0329 | T17: 0.074 | V17: 0.101 | W17: 1722500 | X17: 188.8 | Z17: 96.5 | AA17: 185.2 | AC17: 0.091 | AE17: 0.873 | AF17: 0.748 | AJ17: 215.9 | AK17: 146.8 | AL17: 145.3 | AO17: 138.3 | AP17: 1.38 | AQ17: 4.382 | AR17: 101.7 | AS17: 246.1 | AU17: 151.5 | AW17: 155.7 | AX17: 0.647 | AZ17: 165.6 | BA17: 120.8 | BC17: 196.7 | BE17: 147.1 | BF17: 149.2 | BG17: 0.534 | BH17: 0.225 | BI17: 0.392 | BJ17: 1.428 | BK17: 0.458 | BL17: 0.335 | BN17: 3.322 | BO17: 1.892 | BP17: 3.012 | BR17: 0.552
A18: 34789 | B18: 110900 | C18: 130000 | D18: 0.0838 | E18: 0.0598 | F18: 0.072 | G18: 0.031674812 | I18: 65380 | K18: 346000 | L18: 1226000 | M18: 0.054 | N18: 0.0208 | O18: 0.10903623 | Q18: 0.0212 | R18: 0.0263 | S18: 0.0348 | T18: 0.074 | V18: 0.099 | W18: 1737100 | X18: 185.4 | Z18: 98.4 | AA18: 188 | AC18: 0.091 | AE18: 0.875 | AF18: 0.775 | AJ18: 218.1 | AK18: 147.1 | AL18: 152.4 | AO18: 146.3 | AP18: 1.392 | AQ18: 4.108 | AR18: 101.9 | AS18: 250.1 | AU18: 154.8 | AW18: 156.6 | AX18: 0.629 | AZ18: 174.5 | BA18: 122.6 | BB18: 135.5 | BC18: 198.3 | BE18: 148.1 | BF18: 150.2 | BG18: 0.511 | BH18: 0.242 | BI18: 0.398 | BJ18: 1.081 | BK18: 0.508 | BL18: 0.348 | BN18: 3.348 | BO18: 1.91 | BP18: 2.975 | BR18: 0.571
A19: 34880 | B19: 119600 | C19: 133700 | D19: 0.0753 | E19: 0.06 | F19: 0.0621 | G19: 0.033322835 | I19: 65380 | K19: 348000 | L19: 1305000 | M19: 0.056 | N19: 0.0211 | O19: 0.11096832 | Q19: 0.021 | R19: 0.0244 | S19: 0.037 | T19: 0.077 | V19: 0.101 | W19: 1716500 | X19: 173.7 | Z19: 102.7 | AA19: 188.3 | AC19: 0.098 | AE19: 0.825 | AF19: 0.781 | AJ19: 219.9 | AK19: 148.3 | AL19: 153.6 | AO19: 146.3 | AP19: 1.333 | AQ19: 4.059 | AR19: 102.3 | AS19: 253 | AU19: 158.3 | AW19: 157.6 | AX19: 0.608 | AZ19: 182.5 | BA19: 122.5 | BC19: 200.1 | BE19: 148.8 | BF19: 151 | BG19: 0.518 | BH19: 0.244 | BI19: 0.395 | BJ19: 1.102 | BK19: 0.49 | BL19: 0.396 | BN19: 3.343 | BO19: 1.896 | BP19: 2.987 | BR19: 0.65
A20: 34972 | B20: 119400 | C20: 130000 | D20: 0.0762 | E20: 0.058 | F20: 0.0617 | G20: 0.033516975 | I20: 65380 | K20: 353000 | L20: 1421000 | M20: 0.056 | N20: 0.0216 | O20: 0.11203198 | Q20: 0.0207 | R20: 0.0247 | S20: 0.0385 | T20: 0.077 | V20: 0.102 | W20: 1770800 | X20: 179.9 | Z20: 102.4 | AA20: 189.9 | AC20: 0.097 | AD20: 2.459 | AE20: 0.956 | AF20: 0.808 | AJ20: 222.4 | AK20: 149.1 | AL20: 153.5 | AO20: 146.4 | AP20: 1.376 | AQ20: 3.996 | AR20: 102.3 | AS20: 256.8 | AU20: 156.5 | AW20: 158.5 | AX20: 0.605 | AZ20: 176.1 | BA20: 123.8 | BB20: 138.8 | BC20: 202.3 | BE20: 149.6 | BF20: 152.4 | BG20: 0.523 | BH20: 0.256 | BI20: 0.398 | BJ20: 0.95 | BK20: 0.49 | BL20: 0.399 | BN20: 3.347 | BO20: 2.042 | BP20: 2.97
A21: 35064 | B21: 118400 | C21: 138600 | D21: 0.0711 | E21: 0.056 | F21: 0.0558 | G21: 0.033798295 | I21: 65380 | K21: 370000 | L21: 1442000 | M21: 0.056 | N21: 0.0217 | O21: 0.11242819 | Q21: 0.0207 | R21: 0.0248 | S21: 0.0395 | T21: 0.077 | V21: 0.1 | W21: 1776900 | X21: 169.3 | Z21: 102 | AA21: 191.3 | AC21: 0.091 | AD21: 2.518 | AE21: 1.16 | AF21: 0.837 | AJ21: 224.3 | AK21: 149.9 | AL21: 153.5 | AO21: 146.3 | AP21: 1.403 | AQ21: 3.752 | AR21: 102.2 | AS21: 260.1 | AU21: 158.2 | AW21: 159.6 | AX21: 0.625 | AZ21: 170.7 | BA21: 123.8 | BC21: 204.3 | BE21: 150.4 | BF21: 154.3 | BG21: 0.553 | BH21: 0.243 | BI21: 0.398 | BJ21: 1.507 | BK21: 0.454 | BL21: 0.38 | BN21: 3.39 | BO21: 2.166 | BP21: 3.026 | BR21: 0.643
A22: 35155 | B22: 119100 | C22: 137000 | D22: 0.0769 | E22: 0.0531 | F22: 0.0634 | G22: 0.03134501 | I22: 66340 | K22: 368000 | L22: 1437000 | M22: 0.055 | N22: 0.0218 | O22: 0.11263491 | Q22: 0.0206 | R22: 0.0252 | S22: 0.0404 | T22: 0.079 | V22: 0.099 | W22: 1795300 | X22: 174.6 | Z22: 101.4 | AA22: 194.5 | AC22: 0.092 | AD22: 2.539 | AE22: 1.138 | AF22: 0.852 | AJ22: 226.2 | AK22: 151.4 | AL22: 155.2 | AO22: 152.8 | AP22: 1.375 | AQ22: 3.55 | AR22: 102.3 | AS22: 263.4 | AU22: 159.1 | AW22: 160.6 | AX22: 0.616 | AZ22: 178.9 | BA22: 124.6 | BB22: 140.8 | BC22: 206.8 | BE22: 151.2 | BF22: 155.3 | BG22: 0.556 | BH22: 0.274 | BI22: 0.406 | BJ22: 1.467 | BK22: 0.539 | BL22: 0.392 | BN22: 3.332 | BO22: 2.202 | BP22: 3.035 | BR22: 0.565
A23: 35246 | B23: 126300 | C23: 140000 | D23: 0.0829 | E23: 0.0527 | F23: 0.0673 | G23: 0.030517846 | I23: 66340 | K23: 355000 | L23: 1429000 | M23: 0.053 | N23: 0.0226 | O23: 0.11292664 | Q23: 0.0206 | R23: 0.024 | S23: 0.0427 | T23: 0.078 | V23: 0.097 | W23: 1851800 | X23: 196.8 | Z23: 100 | AA23: 195.1 | AC23: 0.096 | AD23: 2.599 | AE23: 0.945 | AF23: 0.886 | AJ23: 228 | AK23: 152.9 | AL23: 155.6 | AO23: 153.3 | AP23: 1.324 | AQ23: 3.438 | AR23: 102.5 | AS23: 266.7 | AU23: 156.7 | AW23: 161.8 | AX23: 0.647 | AZ23: 182.2 | BA23: 124.5 | BC23: 210.7 | BE23: 152.3 | BF23: 155.9 | BG23: 0.537 | BH23: 0.297 | BI23: 0.418 | BJ23: 1.127 | BK23: 0.498 | BL23: 0.401 | BN23: 3.374 | BO23: 2.493 | BP23: 2.981 | BR23: 0.716
A24: 35338 | B24: 122900 | C24: 139000 | D24: 0.0816 | E24: 0.053 | F24: 0.0672 | G24: 0.030630902 | I24: 66340 | K24: 330000 | L24: 1392000 | M24: 0.052 | N24: 0.0224 | O24: 0.11341343 | Q24: 0.0201 | R24: 0.024 | S24: 0.0446 | T24: 0.08 | V24: 0.095 | W24: 1891100 | X24: 203.9 | Z24: 100.9 | AA24: 196.2 | AC24: 0.099 | AD24: 2.666 | AE24: 1.15 | AF24: 0.886 | AJ24: 229.7 | AK24: 154.6 | AL24: 156.1 | AO24: 152.9 | AP24: 1.36 | AQ24: 3.333 | AR24: 102.1 | AS24: 269.6 | AU24: 156.8 | AW24: 162.9 | AX24: 0.646 | AZ24: 184.6 | BA24: 125.1 | BB24: 141.4 | BC24: 217 | BE24: 153.5 | BF24: 157.2 | BG24: 0.54 | BH24: 0.308 | BI24: 0.426 | BJ24: 0.98 | BK24: 0.458 | BL24: 0.375 | BN24: 3.062 | BO24: 2.809 | BP24: 3.069
A25: 35430 | B25: 124000 | C25: 144900 | D25: 0.0764 | E25: 0.0529 | F25: 0.0643 | G25: 0.03056422 | I25: 66340 | K25: 322000 | L25: 1411000 | M25: 0.054 | N25: 0.0233 | O25: 0.11400413 | Q25: 0.0195 | R25: 0.0242 | S25: 0.046 | T25: 0.077 | V25: 0.096 | W25: 1926200 | X25: 202.4 | Z25: 100.2 | AA25: 195.9 | AC25: 0.092 | AD25: 2.727 | AE25: 1.308 | AF25: 0.875 | AJ25: 231.2 | AK25: 156.3 | AL25: 156.1 | AO25: 153.1 | AP25: 1.424 | AQ25: 3.307 | AR25: 102.1 | AS25: 272.9 | AU25: 154.9 | AW25: 163.9 | AX25: 0.69 | AZ25: 189.9 | BA25: 125 | BC25: 220.1 | BE25: 155 | BF25: 159.2 | BG25: 0.546 | BH25: 0.292 | BI25: 0.428 | BJ25: 1.21 | BK25: 0.481 | BL25: 0.335 | BN25: 3.085 | BO25: 2.642 | BP25: 3.118 | BR25: 0.593
A26: 35520 | B26: 123700 | C26: 148000 | D26: 0.0797 | E26: 0.0539 | F26: 0.0692 | G26: 0.028546081 | I26: 67720 | K26: 288000 | L26: 1436000 | M26: 0.052 | N26: 0.023 | O26: 0.1136194 | Q26: 0.019 | R26: 0.0245 | S26: 0.047 | T26: 0.075 | V26: 0.091 | W26: 2004600 | X26: 210.5 | Z26: 99.6 | AA26: 197.1 | AC26: 0.093 | AD26: 2.632 | AE26: 1.056 | AF26: 0.855 | AJ26: 233 | AK26: 156.6 | AL26: 157.1 | AO26: 154.1 | AP26: 1.356 | AQ26: 3.512 | AR26: 102.2 | AS26: 276.1 | AU26: 155 | AW26: 165.1 | AX26: 0.692 | AZ26: 188.1 | BA26: 125.4 | BB26: 142.8 | BC26: 223.5 | BE26: 156 | BF26: 161.2 | BG26: 0.564 | BH26: 0.305 | BI26: 0.431 | BJ26: 1.654 | BK26: 0.532 | BL26: 0.33 | BN26: 3.07 | BO26: 2.657 | BP26: 3.145 | BR26: 0.546
A27: 35611 | B27: 131400 | C27: 145000 | D27: 0.0758 | E27: 0.0556 | F27: 0.0651 | G27: 0.028284456 | I27: 67720 | K27: 288000 | L27: 1402000 | M27: 0.05 | N27: 0.0228 | O27: 0.11364968 | Q27: 0.0181 | R27: 0.0224 | S27: 0.0473 | T27: 0.079 | V27: 0.089 | W27: 2060000 | X27: 211.5 | Z27: 100.8 | AA27: 198.7 | AC27: 0.099 | AD27: 2.587 | AE27: 0.952 | AF27: 0.874 | AJ27: 234.4 | AK27: 156.9 | AL27: 158.2 | AO27: 154.3 | AP27: 1.408 | AQ27: 4.428 | AR27: 101.7 | AS27: 279.6 | AU27: 151.6 | AW27: 166.5 | AX27: 0.664 | AZ27: 186.6 | BA27: 125.7 | BC27: 228.1 | BE27: 156.6 | BF27: 162.6 | BG27: 0.558 | BH27: 0.31 | BI27: 0.436 | BJ27: 1.3 | BK27: 0.488 | BL27: 0.345 | BN27: 3.137 | BO27: 2.694 | BP27: 3.118 | BR27: 0.706
A28: 35703 | B28: 131300 | C28: 146300 | D28: 0.0728 | E28: 0.0554 | F28: 0.0612 | G28: 0.025448043 | I28: 67720 | K28: 284000 | L28: 1494000 | M28: 0.049 | N28: 0.0226 | O28: 0.11373444 | Q28: 0.0172 | R28: 0.0221 | S28: 0.047 | T28: 0.079 | V28: 0.087 | W28: 2082900 | X28: 201.9 | Z28: 100.3 | AA28: 199.2 | AC28: 0.099 | AD28: 2.533 | AE28: 1.009 | AF28: 0.885 | AJ28: 235.5 | AK28: 158 | AL28: 158.6 | AO28: 154.3 | AP28: 1.42 | AQ28: 4.617 | AR28: 101.7 | AS28: 283.5 | AU28: 148.2 | AW28: 167.8 | AX28: 0.677 | AZ28: 186 | BA28: 125.4 | BB28: 143.4 | BC28: 232.8 | BE28: 157.8 | BF28: 162.8 | BG28: 0.564 | BH28: 0.305 | BI28: 0.436 | BJ28: 1.091 | BK28: 0.458 | BL28: 0.388 | BN28: 3.126 | BO28: 2.75 | BP28: 3.176
A29: 35795 | B29: 131400 | C29: 145900 | D29: 0.0699 | E29: 0.055 | F29: 0.0575 | G29: 0.026215356 | I29: 67720 | K29: 281000 | L29: 1456000 | M29: 0.047 | N29: 0.022 | O29: 0.11323085 | Q29: 0.017 | R29: 0.0229 | S29: 0.0481 | T29: 0.077 | V29: 0.085 | W29: 2163500 | X29: 194.8 | Z29: 98.7 | AA29: 198.3 | AC29: 0.09 | AD29: 2.672 | AE29: 1.172 | AF29: 0.884 | AJ29: 237.8 | AK29: 158.7 | AL29: 157.8 | AO29: 154.3 | AP29: 1.392 | AQ29: 4.161 | AR29: 101.4 | AS29: 287.1 | AU29: 147.4 | AW29: 169 | AX29: 0.708 | AY29: 100.1 | AZ29: 184.3 | BA29: 125.1 | BC29: 235.4 | BE29: 159 | BF29: 163.9 | BG29: 0.575 | BH29: 0.279 | BI29: 0.428 | BJ29: 1.617 | BK29: 0.461 | BL29: 0.37 | BN29: 3.458 | BO29: 2.607 | BP29: 3.166 | BR29: 0.583
A30: 35885 | B30: 131100 | C30: 152700 | D30: 0.0708 | E30: 0.0549 | F30: 0.0567 | G30: 0.026723043 | I30: 70200 | K30: 284000 | L30: 1605000 | M30: 0.047 | N30: 0.022 | O30: 0.11176228 | Q30: 0.0181 | R30: 0.0231 | S30: 0.0476 | T30: 0.077 | V30: 0.084 | W30: 2193600 | X30: 193.7 | Z30: 98.3 | AA30: 199.6 | AC30: 0.085 | AD30: 2.658 | AE30: 1.043 | AF30: 0.853 | AJ30: 239.4 | AK30: 159.7 | AL30: 157.9 | AO30: 156.2 | AP30: 1.413 | AQ30: 4.033 | AR30: 101.2 | AS30: 290.4 | AU30: 148.4 | AW30: 170.3 | AX30: 0.686 | AY30: 100.9 | AZ30: 193.7 | BA30: 126.3 | BC30: 241.3 | BE30: 159.9 | BF30: 164.7 | BG30: 0.545 | BH30: 0.302 | BI30: 0.433 | BJ30: 1.515 | BK30: 0.475 | BL30: 0.368 | BN30: 3.477 | BO30: 2.539 | BP30: 3.107 | BR30: 0.505
A31: 35976 | B31: 138600 | C31: 148000 | D31: 0.0696 | E31: 0.0556 | F31: 0.0544 | G31: 0.026002045 | I31: 70200 | K31: 286000 | L31: 1551000 | M31: 0.045 | N31: 0.0212 | O31: 0.11195718 | Q31: 0.0173 | R31: 0.0213 | S31: 0.0476 | T31: 0.08 | V31: 0.081 | W31: 2251600 | X31: 177.1 | Z31: 99.3 | AA31: 198.2 | AC31: 0.091 | AD31: 2.622 | AE31: 0.932 | AF31: 0.859 | AH31: 100 | AI31: 100 | AJ31: 241.8 | AK31: 160.2 | AL31: 158.2 | AO31: 155.5 | AP31: 1.388 | AQ31: 3.786 | AR31: 101 | AS31: 293.9 | AU31: 150.8 | AW31: 171.8 | AX31: 0.673 | AY31: 101.5 | AZ31: 188.2 | BA31: 126.7 | BC31: 244.7 | BE31: 160.7 | BF31: 165.3 | BG31: 0.536 | BH31: 0.305 | BI31: 0.431 | BJ31: 1.393 | BK31: 0.507 | BL31: 0.39 | BN31: 3.432 | BO31: 2.457 | BP31: 3.153 | BR31: 0.672
A32: 36068 | B32: 137200 | C32: 155000 | D32: 0.0664 | E32: 0.0551 | F32: 0.0444 | G32: 0.02594218 | I32: 70200 | K32: 289000 | L32: 1577000 | M32: 0.046 | N32: 0.0209 | O32: 0.11183267 | Q32: 0.0177 | R32: 0.0216 | S32: 0.0472 | T32: 0.082 | V32: 0.08 | W32: 2242500 | X32: 175.2 | Z32: 100.3 | AA32: 194.4 | AC32: 0.089 | AD32: 2.757 | AE32: 1.022 | AF32: 0.86 | AH32: 100.6 | AI32: 99.7 | AJ32: 244.1 | AK32: 161.1 | AL32: 158.5 | AO32: 156 | AP32: 1.361 | AQ32: 3.62 | AR32: 101.2 | AS32: 296.8 | AU32: 151.6 | AW32: 173.4 | AX32: 0.668 | AY32: 102.3 | AZ32: 190.2 | BA32: 126.5 | BC32: 248.7 | BE32: 162.1 | BF32: 167.1 | BG32: 0.544 | BH32: 0.305 | BI32: 0.432 | BJ32: 1.241 | BK32: 0.476 | BL32: 0.376 | BN32: 3.587 | BO32: 2.576 | BP32: 3.121
A33: 36160 | B33: 136300 | C33: 152500 | D33: 0.0683 | E33: 0.0468 | F33: 0.0465 | G33: 0.02437823 | I33: 70200 | K33: 294000 | L33: 1742000 | M33: 0.044 | N33: 0.0203 | O33: 0.112519 | Q33: 0.0187 | R33: 0.0225 | S33: 0.0474 | T33: 0.078 | V33: 0.076 | W33: 2332800 | X33: 175.1 | Z33: 99.1 | AA33: 191.6 | AC33: 0.084 | AD33: 2.859 | AE33: 1.089 | AF33: 0.866 | AH33: 101.5 | AI33: 99.9 | AJ33: 245.9 | AK33: 162.4 | AL33: 158.6 | AO33: 155.4 | AP33: 1.388 | AQ33: 3.446 | AR33: 101.2 | AS33: 300.2 | AU33: 152.4 | AW33: 174.8 | AX33: 0.697 | AY33: 102.9 | AZ33: 188.4 | BA33: 126.6 | BC33: 252 | BE33: 163 | BF33: 168.3 | BG33: 0.543 | BH33: 0.279 | BI33: 0.427 | BJ33: 1.798 | BK33: 0.51 | BL33: 0.375 | BN33: 3.759 | BO33: 2.58 | BP33: 3.177 | BR33: 0.608
A34: 36250 | B34: 136300 | C34: 157300 | D34: 0.0698 | E34: 0.0481 | F34: 0.0525 | G34: 0.02237507 | I34: 71980 | K34: 289000 | L34: 1665000 | M34: 0.042 | N34: 0.0194 | O34: 0.11306154 | Q34: 0.0197 | R34: 0.0224 | S34: 0.0466 | T34: 0.082 | V34: 0.075 | W34: 2403700 | X34: 193.4 | Z34: 97.9 | AA34: 191.7 | AC34: 0.084 | AD34: 3.003 | AE34: 1.005 | AF34: 0.883 | AH34: 102.6 | AI34: 99.9 | AJ34: 247.9 | AK34: 163.3 | AL34: 159 | AO34: 154.5 | AP34: 1.404 | AQ34: 3.476 | AR34: 100.1 | AS34: 304.4 | AU34: 147.4 | AW34: 175.9 | AX34: 0.663 | AY34: 103.3 | AZ34: 198.8 | BA34: 126.7 | BC34: 252.2 | BE34: 164.2 | BF34: 169.9 | BG34: 0.544 | BH34: 0.289 | BI34: 0.437 | BJ34: 1.395 | BK34: 0.506 | BL34: 0.384 | BN34: 3.714 | BO34: 2.507 | BP34: 3.249 | BR34: 0.869
A35: 36341 | B35: 144600 | C35: 159300 | D35: 0.0763 | E35: 0.0476 | F35: 0.0581 | G35: 0.02070264 | I35: 71980 | K35: 295000 | L35: 1702000 | M35: 0.043 | N35: 0.0188 | O35: 0.11474377 | Q35: 0.02 | R35: 0.021 | S35: 0.0458 | T35: 0.081 | V35: 0.075 | W35: 2454200 | X35: 205.9 | Z35: 97.5 | AA35: 197.1 | AC35: 0.089 | AD35: 2.704 | AE35: 0.949 | AF35: 0.885 | AH35: 103.3 | AI35: 99.6 | AJ35: 250 | AK35: 163.7 | AL35: 159.1 | AO35: 154.8 | AP35: 1.448 | AQ35: 3.421 | AR35: 100.1 | AS35: 307.9 | AU35: 150.9 | AW35: 177.2 | AX35: 0.667 | AY35: 103.9 | AZ35: 192.6 | BA35: 126.8 | BC35: 253.9 | BE35: 164.6 | BF35: 170.9 | BG35: 0.553 | BH35: 0.303 | BI35: 0.431 | BJ35: 1.304 | BK35: 0.502 | BL35: 0.391 | BN35: 3.672 | BO35: 2.504 | BP35: 3.235 | BR35: 0.944
A36: 36433 | B36: 142600 | C36: 163200 | D36: 0.0776 | E36: 0.0522 | F36: 0.059 | G36: 0.02070746 | I36: 71980 | K36: 301000 | L36: 1551000 | M36: 0.042 | N36: 0.0215 | O36: 0.11593912 | Q36: 0.0206 | R36: 0.0219 | S36: 0.046 | T36: 0.082 | V36: 0.074 | W36: 2475500 | X36: 197.4 | Z36: 99.4 | AA36: 196.5 | AC36: 0.09 | AD36: 2.794 | AE36: 0.956 | AF36: 0.878 | AH36: 104.9 | AI36: 99.3 | AJ36: 252.5 | AK36: 164.6 | AL36: 158.8 | AO36: 154.7 | AP36: 1.484 | AQ36: 3.393 | AR36: 100.6 | AS36: 311.1 | AU36: 155.7 | AW36: 178.5 | AX36: 0.707 | AY36: 104.4 | AZ36: 194.7 | BA36: 127 | BC36: 255.6 | BE36: 165.8 | BF36: 172.1 | BG36: 0.547 | BH36: 0.31 | BI36: 0.437 | BJ36: 1.272 | BK36: 0.481 | BL36: 0.413 | BN36: 3.806 | BO36: 2.58 | BP36: 3.237
A37: 36525 | B37: 141800 | C37: 164800 | D37: 0.0806 | E37: 0.053 | F37: 0.0645 | G37: 0.02167848 | I37: 71980 | K37: 308000 | L37: 1683000 | M37: 0.04 | N37: 0.0199 | O37: 0.11602639 | Q37: 0.0199 | R37: 0.0211 | S37: 0.0455 | T37: 0.079 | V37: 0.071 | W37: 2603500 | X37: 192.8 | Z37: 100.7 | AA37: 198.9 | AC37: 0.085 | AD37: 2.875 | AE37: 0.92 | AF37: 0.899 | AH37: 105.6 | AI37: 99.5 | AJ37: 254.9 | AK37: 165.5 | AL37: 161 | AO37: 153.2 | AP37: 1.528 | AQ37: 3.347 | AR37: 100.8 | AS37: 314.8 | AU37: 155 | AW37: 180.1 | AX37: 0.71 | AY37: 104.9 | AZ37: 201.2 | BA37: 126.4 | BC37: 259.1 | BE37: 166.8 | BF37: 174.3 | BG37: 0.502 | BH37: 0.267 | BI37: 0.426 | BJ37: 1.405 | BK37: 0.494 | BL37: 0.395 | BN37: 3.845 | BO37: 2.752 | BP37: 3.33 | BR37: 0.641
A38: 36616 | B38: 141600 | C38: 165100 | D38: 0.0823 | E38: 0.0585 | F38: 0.0603 | G38: 0.02483286 | I38: 71790 | K38: 313000 | L38: 1651000 | M38: 0.04 | N38: 0.0195 | O38: 0.11581974 | Q38: 0.0211 | R38: 0.0211 | S38: 0.0443 | T38: 0.079 | V38: 0.071 | W38: 2645400 | X38: 193 | Z38: 100.5 | AA38: 201.2 | AC38: 0.085 | AD38: 2.748 | AE38: 0.931 | AF38: 0.924 | AH38: 106.3 | AI38: 99.8 | AJ38: 257.7 | AK38: 166.5 | AL38: 161.4 | AO38: 154.7 | AP38: 1.532 | AQ38: 3.633 | AR38: 101.4 | AS38: 319.3 | AU38: 153 | AW38: 181.9 | AX38: 0.712 | AY38: 105.7 | AZ38: 209.8 | BA38: 127.9 | BC38: 263.5 | BE38: 167.9 | BF38: 176.2 | BG38: 0.481 | BH38: 0.285 | BI38: 0.429 | BJ38: 1.364 | BK38: 0.517 | BL38: 0.393 | BN38: 3.81 | BO38: 2.928 | BP38: 3.354 | BR38: 0.572
A39: 36707 | B39: 148100 | C39: 160100 | D39: 0.0822 | E39: 0.0653 | F39: 0.0603 | G39: 0.02701492 | I39: 71790 | K39: 306000 | L39: 1572000 | M39: 0.04 | N39: 0.0198 | O39: 0.11727593 | Q39: 0.0224 | R39: 0.0208 | S39: 0.0451 | T39: 0.08 | V39: 0.07 | W39: 2649400 | X39: 179.5 | Z39: 105.6 | AA39: 202.9 | AC39: 0.09 | AD39: 2.763 | AE39: 0.838 | AF39: 0.915 | AH39: 107.9 | AI39: 100 | AJ39: 260.3 | AK39: 167.4 | AL39: 160.8 | AO39: 155.6 | AP39: 1.556 | AQ39: 3.431 | AR39: 101.2 | AS39: 324.6 | AU39: 155.7 | AW39: 183.4 | AX39: 0.781 | AY39: 106.4 | AZ39: 212.6 | BA39: 128.1 | BC39: 265.9 | BE39: 168.6 | BF39: 177.9 | BG39: 0.49 | BH39: 0.305 | BI39: 0.428 | BJ39: 1.318 | BK39: 0.506 | BL39: 0.376 | BN39: 3.758 | BO39: 3.132 | BP39: 3.302 | BR39: 0.699
A40: 36799 | B40: 150300 | C40: 171500 | D40: 0.0788 | E40: 0.0652 | F40: 0.058 | G40: 0.02897082 | I40: 71790 | K40: 300000 | L40: 1570000 | M40: 0.039 | N40: 0.0209 | O40: 0.11883636 | Q40: 0.0233 | R40: 0.0219 | S40: 0.0453 | T40: 0.082 | V40: 0.07 | W40: 2640000 | X40: 167.5 | Z40: 104.3 | AA40: 204.7 | AC40: 0.091 | AD40: 2.809 | AE40: 0.92 | AF40: 0.918 | AH40: 108.9 | AI40: 100.4 | AJ40: 263.3 | AK40: 168.9 | AL40: 161.2 | AO40: 155.7 | AP40: 1.579 | AQ40: 3.339 | AR40: 101.7 | AS40: 326.3 | AU40: 156.2 | AW40: 185.4 | AX40: 0.851 | AY40: 107.1 | AZ40: 213 | BA40: 129 | BC40: 270.2 | BE40: 170 | BF40: 179.9 | BH40: 0.303 | BI40: 0.424 | BJ40: 1.319 | BK40: 0.488 | BL40: 0.374 | BN40: 3.876 | BO40: 3.209 | BP40: 3.416
A41: 36891 | B41: 148200 | C41: 162000 | D41: 0.0713 | E41: 0.064 | F41: 0.0512 | G41: 0.02972089 | I41: 71790 | K41: 298000 | L41: 1543000 | M41: 0.039 | N41: 0.0223 | O41: 0.1207207 | Q41: 0.0252 | R41: 0.024 | S41: 0.0457 | T41: 0.078 | U41: 5088000 | V41: 0.069 | W41: 2587200 | X41: 164.9 | Z41: 105.1 | AA41: 200.6 | AC41: 0.086 | AD41: 2.785 | AE41: 0.959 | AF41: 0.987 | AH41: 109.4 | AI41: 101 | AJ41: 265.6 | AK41: 170 | AL41: 161.8 | AO41: 155.8 | AP41: 1.625 | AQ41: 3.212 | AR41: 103.1 | AS41: 331 | AU41: 160.2 | AW41: 187.4 | AX41: 0.977 | AY41: 108 | AZ41: 209.5 | BA41: 128.6 | BC41: 272.4 | BE41: 170.8 | BF41: 181.3 | BH41: 0.275 | BI41: 0.414 | BJ41: 1.567 | BK41: 0.487 | BL41: 0.347 | BN41: 3.763 | BO41: 3.028 | BP41: 3.437 | BR41: 0.624
A42: 36981 | B42: 150800 | C42: 166300 | D42: 0.0691 | E42: 0.0531 | F42: 0.0493 | G42: 0.02961886 | I42: 70610 | K42: 292000 | L42: 1659000 | M42: 0.043 | N42: 0.0234 | O42: 0.12175219 | Q42: 0.0265 | R42: 0.0244 | S42: 0.0481 | T42: 0.082 | U42: 4762000 | V42: 0.073 | W42: 2485300 | X42: 165.7 | Z42: 104.1 | AA42: 198.4 | AC42: 0.089 | AD42: 2.76 | AE42: 0.886 | AF42: 1.02 | AH42: 111.7 | AI42: 101.7 | AJ42: 269.4 | AK42: 171.7 | AL42: 162.1 | AO42: 151.9 | AP42: 1.74 | AQ42: 3.205 | AR42: 104.7 | AS42: 335.1 | AU42: 159.9 | AW42: 189.5 | AX42: 1.078 | AY42: 108.6 | AZ42: 210 | BA42: 129.1 | BC42: 275.5 | BE42: 172.3 | BF42: 182.2 | BH42: 0.312 | BI42: 0.437 | BJ42: 1.336 | BK42: 0.51 | BL42: 0.356 | BN42: 3.846 | BO42: 3.159 | BP42: 3.378 | BR42: 0.646
A43: 37072 | B43: 160800 | C43: 179400 | D43: 0.0711 | E43: 0.0397 | F43: 0.0542 | G43: 0.03200619 | I43: 70610 | K43: 301000 | L43: 1626000 | M43: 0.045 | N43: 0.0241 | O43: 0.12386421 | Q43: 0.0294 | R43: 0.0248 | S43: 0.0494 | T43: 0.083 | U43: 4361000 | V43: 0.079 | W43: 2342900 | X43: 187.3 | Z43: 106.7 | AA43: 199.5 | AC43: 0.097 | AD43: 2.911 | AE43: 0.92 | AF43: 0.989 | AH43: 112.5 | AI43: 102.6 | AJ43: 272.4 | AK43: 173.1 | AL43: 162.4 | AO43: 151.9 | AP43: 1.703 | AQ43: 3.156 | AR43: 104.4 | AS43: 340.1 | AU43: 158.9 | AW43: 191.8 | AX43: 0.937 | AY43: 109.2 | AZ43: 216.3 | BA43: 129.2 | BC43: 277.2 | BE43: 173.6 | BF43: 184.1 | BH43: 0.313 | BI43: 0.435 | BJ43: 1.356 | BK43: 0.506 | BL43: 0.388 | BN43: 3.968 | BO43: 3.253 | BP43: 3.564 | BR43: 0.793
A44: 37164 | B44: 156500 | C44: 166400 | D44: 0.0672 | E44: 0.0307 | F44: 0.046 | G44: 0.03388746 | I44: 70610 | K44: 310000 | L44: 1565000 | M44: 0.05 | N44: 0.0219 | O44: 0.12329806 | Q44: 0.0326 | R44: 0.0271 | S44: 0.05 | T44: 0.084 | U44: 4071000 | V44: 0.087 | W44: 2259000 | X44: 173.4 | Z44: 109.7 | AA44: 197.7 | AC44: 0.097 | AD44: 2.941 | AE44: 0.916 | AF44: 0.996 | AH44: 113.5 | AI44: 103.4 | AJ44: 275.2 | AK44: 174.2 | AL44: 162.1 | AO44: 151.9 | AP44: 1.717 | AQ44: 3.025 | AR44: 105.2 | AS44: 345 | AU44: 157.3 | AW44: 194 | AX44: 0.811 | AY44: 110.3 | AZ44: 212.7 | BA44: 129.4 | BC44: 280.5 | BE44: 175.1 | BF44: 185.5 | BH44: 0.296 | BI44: 0.442 | BJ44: 1.168 | BK44: 0.508 | BL44: 0.422 | BN44: 4.143 | BO44: 3.487 | BP44: 3.397
A45: 37256 | B45: 162400 | C45: 180200 | D45: 0.0716 | E45: 0.0182 | F45: 0.0507 | G45: 0.0356492 | I45: 70610 | K45: 308000 | L45: 1680000 | M45: 0.057 | N45: 0.0226 | O45: 0.12682582 | Q45: 0.0348 | R45: 0.0282 | S45: 0.0469 | T45: 0.088 | U45: 3677000 | V45: 0.096 | W45: 2138200 | X45: 161 | Z45: 110.2 | AA45: 198.2 | AC45: 0.09 | AD45: 2.895 | AE45: 0.925 | AF45: 1.005 | AH45: 114.8 | AI45: 105.3 | AJ45: 278.2 | AK45: 174.7 | AL45: 162.2 | AO45: 151.9 | AP45: 1.713 | AQ45: 2.913 | AR45: 105.8 | AS45: 350.4 | AU45: 157.2 | AW45: 196.2 | AX45: 0.787 | AY45: 111.1 | AZ45: 204.8 | BA45: 128.9 | BC45: 283.2 | BE45: 176 | BF45: 186.4 | BH45: 0.282 | BI45: 0.425 | BJ45: 1.404 | BK45: 0.505 | BL45: 0.41 | BN45: 4.165 | BO45: 3.3 | BP45: 3.477 | BR45: 0.713
A46: 37346 | B46: 160100 | C46: 183400 | D46: 0.0718 | E46: 0.0173 | F46: 0.0542 | G46: 0.0346848 | I46: 70040 | K46: 316000 | L46: 1691000 | M46: 0.057 | N46: 0.0224 | O46: 0.12456402 | Q46: 0.0369 | R46: 0.0276 | S46: 0.0494 | T46: 0.091 | U46: 3612000 | V46: 0.094 | W46: 2190500 | X46: 178.2 | Z46: 109.1 | AA46: 199.6 | AC46: 0.089 | AD46: 2.816 | AE46: 1.003 | AF46: 1.012 | AH46: 116.3 | AI46: 107.3 | AJ46: 281.4 | AK46: 176.1 | AL46: 161.5 | AO46: 155.1 | AP46: 1.74 | AQ46: 2.859 | AR46: 106.5 | AS46: 355.5 | AU46: 152.1 | AW46: 198.1 | AX46: 0.755 | AY46: 112.3 | AZ46: 207.9 | BA46: 128.7 | BC46: 289.8 | BE46: 177.1 | BF46: 187.3 | BH46: 0.31 | BI46: 0.426 | BJ46: 1.292 | BK46: 0.519 | BL46: 0.465 | BN46: 4.162 | BO46: 3.266 | BP46: 3.418 | BR46: 0.71
A47: 37437 | B47: 173200 | C47: 190600 | D47: 0.0655 | E47: 0.0175 | F47: 0.0486 | G47: 0.03241692 | I47: 70040 | K47: 328000 | L47: 1758000 | M47: 0.058 | N47: 0.0216 | O47: 0.12362782 | Q47: 0.0392 | R47: 0.0267 | S47: 0.0478 | T47: 0.084 | U47: 3412000 | V47: 0.095 | W47: 2230100 | X47: 170.2 | Z47: 112 | AA47: 200.2 | AC47: 0.095 | AD47: 2.768 | AE47: 0.975 | AF47: 1.011 | AH47: 118.2 | AI47: 109.1 | AJ47: 284.6 | AK47: 175.9 | AL47: 162.4 | AO47: 154 | AP47: 1.719 | AQ47: 2.938 | AR47: 106.7 | AS47: 361.2 | AU47: 152.2 | AW47: 199.5 | AX47: 0.771 | AY47: 112.6 | AZ47: 211.3 | BA47: 128.7 | BC47: 294.5 | BE47: 178.2 | BF47: 188.3 | BG47: 0.47 | BH47: 0.325 | BI47: 0.43 | BJ47: 1.299 | BK47: 0.512 | BL47: 0.517 | BN47: 4.311 | BO47: 3.193 | BP47: 3.43 | BR47: 0.849
A48: 37529 | B48: 167600 | C48: 177500 | D48: 0.0599 | E48: 0.0175 | F48: 0.0363 | G48: 0.03026606 | I48: 70040 | K48: 333000 | L48: 1803000 | M48: 0.057 | N48: 0.021 | O48: 0.12374393 | Q48: 0.0388 | R48: 0.0268 | S48: 0.0489 | T48: 0.09 | U48: 3301000 | V48: 0.096 | W48: 2207600 | X48: 169.5 | Z48: 111.3 | AA48: 201.8 | AC48: 0.095 | AD48: 2.728 | AE48: 1.055 | AF48: 1.016 | AH48: 121.2 | AI48: 110.7 | AJ48: 288.1 | AK48: 176.5 | AL48: 164 | AO48: 153.9 | AP48: 1.676 | AQ48: 2.921 | AR48: 107.4 | AS48: 367.1 | AU48: 152.2 | AW48: 200.8 | AX48: 0.776 | AY48: 113.6 | AZ48: 206.5 | BA48: 128.1 | BC48: 297.4 | BE48: 179.2 | BF48: 189.2 | BG48: 0.471 | BH48: 0.322 | BI48: 0.437 | BJ48: 1.158 | BK48: 0.498 | BL48: 0.511 | BN48: 4.381 | BO48: 3.155 | BP48: 3.498
A49: 37621 | B49: 172800 | C49: 197600 | D49: 0.0593 | E49: 0.0124 | F49: 0.0383 | G49: 0.02792164 | I49: 70040 | K49: 339000 | L49: 1896000 | M49: 0.06 | N49: 0.02 | O49: 0.12341276 | Q49: 0.0388 | R49: 0.0265 | S49: 0.0484 | T49: 0.093 | U49: 3169000 | V49: 0.098 | W49: 2159300 | X49: 164.8 | Z49: 108.4 | AA49: 201.4 | AC49: 0.089 | AD49: 2.682 | AE49: 1.176 | AF49: 1.026 | AH49: 125.6 | AI49: 113.6 | AJ49: 292.1 | AK49: 177.1 | AL49: 164.6 | AN49: 100 | AO49: 153.9 | AP49: 1.693 | AQ49: 2.838 | AR49: 107 | AS49: 372 | AU49: 148.5 | AW49: 202.4 | AX49: 0.847 | AY49: 114.6 | AZ49: 203 | BA49: 127 | BC49: 303.7 | BE49: 180.1 | BF49: 189.9 | BG49: 0.458 | BH49: 0.292 | BI49: 0.421 | BJ49: 1.655 | BK49: 0.504 | BL49: 0.479 | BN49: 4.107 | BO49: 3.242 | BP49: 3.472 | BR49: 0.742
A50: 37711 | B50: 170300 | C50: 185100 | D50: 0.0591 | E50: 0.0125 | F50: 0.0383 | G50: 0.02619135 | I50: 70080 | K50: 338000 | L50: 1757000 | M50: 0.059 | N50: 0.0197 | O50: 0.12358857 | Q50: 0.0365 | R50: 0.0254 | S50: 0.0468 | T50: 0.094 | U50: 3099000 | V50: 0.1 | W50: 2166600 | X50: 164.5 | Z50: 114.2 | AA50: 202.5 | AC50: 0.089 | AD50: 2.656 | AE50: 1.209 | AF50: 1.042 | AH50: 130.7 | AI50: 116.3 | AJ50: 293.4 | AK50: 178.4 | AL50: 166.2 | AN50: 98.2 | AO50: 170 | AP50: 1.858 | AQ50: 2.933 | AR50: 107.9 | AS50: 378.2 | AU50: 148.5 | AW50: 204 | AX50: 1.028 | AY50: 115.7 | AZ50: 206.1 | BA50: 127.1 | BC50: 305.3 | BE50: 181 | BF50: 191.7 | BG50: 0.44 | BH50: 0.319 | BI50: 0.427 | BJ50: 1.619 | BK50: 0.513 | BL50: 0.463 | BN50: 4.049 | BO50: 3.216 | BP50: 3.546 | BR50: 0.728
A51: 37802 | B51: 185000 | C51: 187900 | D51: 0.0524 | E51: 0.0122 | F51: 0.0354 | G51: 0.02261697 | I51: 70080 | K51: 343000 | L51: 1875000 | M51: 0.063 | N51: 0.0183 | O51: 0.1229993 | Q51: 0.0356 | R51: 0.0234 | S51: 0.0453 | T51: 0.096 | U51: 3390000 | V51: 0.103 | W51: 2221900 | X51: 164.9 | Z51: 117.6 | AA51: 202.7 | AC51: 0.097 | AD51: 2.676 | AE51: 1.199 | AF51: 0.961 | AH51: 133.8 | AI51: 118.2 | AJ51: 296.1 | AK51: 179.7 | AL51: 166.2 | AN51: 98 | AO51: 170 | AP51: 1.932 | AQ51: 2.931 | AR51: 107.7 | AS51: 384.3 | AU51: 147.4 | AW51: 205.3 | AX51: 0.992 | AY51: 116.6 | AZ51: 214.4 | BA51: 126.2 | BC51: 309.5 | BE51: 181.9 | BF51: 192.8 | BG51: 0.428 | BH51: 0.327 | BI51: 0.429 | BJ51: 1.398 | BK51: 0.521 | BL51: 0.462 | BN51: 3.796 | BO51: 3.136 | BP51: 3.581 | BR51: 0.875
A52: 37894 | B52: 182400 | C52: 192000 | D52: 0.0598 | E52: 0.0101 | F52: 0.0396 | G52: 0.02174311 | I52: 70080 | K52: 350000 | L52: 1961000 | M52: 0.061 | N52: 0.0173 | O52: 0.12144751 | Q52: 0.0327 | R52: 0.0222 | S52: 0.0424 | T52: 0.099 | U52: 3091000 | V52: 0.104 | W52: 2260900 | X52: 183.8 | Z52: 114.9 | AA52: 202.9 | AC52: 0.098 | AD52: 2.904 | AE52: 1.257 | AF52: 0.994 | AH52: 135.6 | AI52: 119 | AJ52: 299.8 | AK52: 180.9 | AL52: 166.3 | AN52: 96.6 | AO52: 169.9 | AP52: 2.022 | AQ52: 2.919 | AR52: 107.7 | AS52: 393.7 | AU52: 139 | AW52: 206.7 | AX52: 0.974 | AY52: 118.3 | AZ52: 211.2 | BA52: 125.2 | BC52: 311.6 | BE52: 182.8 | BF52: 195.4 | BG52: 0.461 | BH52: 0.317 | BI52: 0.426 | BJ52: 1.438 | BK52: 0.494 | BL52: 0.444 | BN52: 3.9 | BO52: 3.219 | BP52: 3.508
A53: 37986 | B53: 185400 | C53: 196000 | D53: 0.0585 | E53: 0.0098 | F53: 0.0427 | G53: 0.01967767 | I53: 70080 | K53: 370000 | L53: 1987000 | M53: 0.057 | N53: 0.0176 | O53: 0.12215914 | Q53: 0.0285 | R53: 0.0221 | S53: 0.0443 | T53: 0.102 | U53: 3414000 | V53: 0.098 | W53: 2294700 | X53: 178.4 | Z53: 114.1 | AA53: 204.7 | AB53: 100 | AC53: 0.09 | AD53: 2.947 | AE53: 1.559 | AF53: 0.954 | AH53: 138.7 | AI53: 119.6 | AJ53: 303 | AK53: 183.5 | AL53: 166.5 | AM53: 100 | AN53: 97.1 | AO53: 169.9 | AP53: 2.232 | AQ53: 2.875 | AR53: 107.7 | AS53: 399.5 | AU53: 131 | AW53: 207.7 | AX53: 0.991 | AY53: 120 | AZ53: 205.6 | BA53: 124.7 | BC53: 314.9 | BE53: 184.3 | BF53: 194.3 | BG53: 0.482 | BH53: 0.287 | BI53: 0.422 | BJ53: 1.533 | BK53: 0.504 | BL53: 0.439 | BN53: 4.067 | BO53: 3.182 | BP53: 3.583 | BQ53: 100 | BR53: 0.862 | BT53: 100
A54: 38077 | B54: 182700 | C54: 209600 | D54: 0.054 | E54: 0.01 | F54: 0.0386 | G54: 0.02126567 | I54: 69970 | K54: 381000 | L54: 2066000 | M54: 0.058 | N54: 0.0165 | O54: 0.12219274 | Q54: 0.0257 | R54: 0.0196 | S54: 0.0421 | T54: 0.104 | U54: 3525000 | V54: 0.1 | W54: 2313700 | X54: 204.7 | Z54: 111.4 | AA54: 208.6 | AB54: 101.7 | AC54: 0.091 | AD54: 2.786 | AE54: 1.625 | AF54: 0.947 | AH54: 141.5 | AI54: 120.9 | AJ54: 306.5 | AK54: 184.2 | AL54: 168.1 | AM54: 100.6 | AN54: 96.8 | AO54: 180 | AP54: 2.196 | AQ54: 2.932 | AR54: 107.8 | AS54: 406.6 | AU54: 131.8 | AW54: 209.1 | AX54: 0.992 | AY54: 121.9 | AZ54: 209.9 | BA54: 125.7 | BC54: 318.1 | BE54: 185.8 | BF54: 195.8 | BG54: 0.504 | BH54: 0.3 | BI54: 0.426 | BJ54: 1.529 | BK54: 0.5 | BL54: 0.459 | BN54: 4.079 | BO54: 3.129 | BP54: 3.435 | BR54: 0.73 | BT54: 100.8
A55: 38168 | B55: 201800 | C55: 215700 | D55: 0.0625 | E55: 0.0103 | F55: 0.0462 | G55: 0.02370793 | I55: 69970 | K55: 383000 | L55: 2020000 | M55: 0.056 | N55: 0.016 | O55: 0.12157168 | Q55: 0.023 | R55: 0.0179 | S55: 0.0415 | T55: 0.102 | U55: 3337000 | V55: 0.096 | W55: 2383600 | X55: 218.6 | Z55: 113.9 | AA55: 210.8 | AB55: 103.6 | AC55: 0.099 | AD55: 3.574 | AE55: 1.311 | AF55: 0.979 | AH55: 144.7 | AI55: 121.4 | AJ55: 309.8 | AK55: 186.4 | AL55: 173.1 | AM55: 101.6 | AN55: 96.7 | AO55: 189.1 | AP55: 2.078 | AQ55: 2.75 | AR55: 108.2 | AS55: 413.2 | AU55: 129.9 | AW55: 210.9 | AX55: 1.047 | AY55: 123.8 | AZ55: 212.3 | BA55: 125.6 | BC55: 322.6 | BE55: 187 | BF55: 196.9 | BG55: 0.538 | BH55: 0.312 | BI55: 0.425 | BJ55: 1.331 | BK55: 0.498 | BL55: 0.462 | BN55: 4.55 | BO55: 3.42 | BP55: 3.446 | BR55: 0.878 | BT55: 101.5
A56: 38260 | B56: 197200 | C56: 211600 | D56: 0.0572 | E56: 0.0161 | F56: 0.0414 | G56: 0.0223192 | I56: 69970 | K56: 410000 | L56: 2041000 | M56: 0.054 | N56: 0.0156 | O56: 0.12272636 | Q56: 0.0203 | R56: 0.0174 | S56: 0.0407 | T56: 0.101 | U56: 3821000 | V56: 0.094 | W56: 2419300 | X56: 231.1 | Z56: 117.5 | AA56: 213.7 | AB56: 106.4 | AC56: 0.099 | AD56: 3.149 | AE56: 1.145 | AF56: 0.985 | AH56: 146 | AI56: 122.2 | AJ56: 312.9 | AK56: 186.9 | AL56: 175.6 | AM56: 102.5 | AN56: 98 | AO56: 193.6 | AP56: 2.121 | AQ56: 2.874 | AR56: 109.3 | AS56: 420.3 | AU56: 135.5 | AW56: 212.5 | AX56: 1.034 | AY56: 125.7 | AZ56: 205.3 | BA56: 125 | BC56: 325.1 | BE56: 188.9 | BF56: 199.1 | BG56: 0.565 | BH56: 0.307 | BI56: 0.426 | BJ56: 1.321 | BK56: 0.488 | BL56: 0.446 | BN56: 4.459 | BO56: 3.589 | BP56: 3.244 | BR56: 1.142 | BT56: 101.4
A57: 38352 | B57: 200400 | C57: 229600 | D57: 0.0581 | E57: 0.0216 | F57: 0.0424 | G57: 0.02304188 | I57: 69970 | K57: 422000 | L57: 2082000 | M57: 0.054 | N57: 0.0141 | O57: 0.12277015 | Q57: 0.0182 | R57: 0.0169 | S57: 0.0403 | T57: 0.1 | U57: 4074000 | V57: 0.093 | W57: 2430200 | X57: 196.1 | Z57: 119.5 | AA57: 214.8 | AB57: 107.7 | AC57: 0.092 | AD57: 3.233 | AE57: 1.199 | AF57: 0.97 | AH57: 147.8 | AI57: 122.7 | AJ57: 315.8 | AK57: 188.4 | AL57: 179 | AM57: 103.8 | AN57: 97.6 | AO57: 193.6 | AP57: 2.14 | AQ57: 2.776 | AR57: 109.9 | AS57: 426.5 | AU57: 138.4 | AW57: 213.7 | AX57: 1.154 | AY57: 126.6 | AZ57: 205.4 | BA57: 125.5 | BC57: 327.5 | BE57: 189.9 | BF57: 201.2 | BG57: 0.572 | BH57: 0.285 | BI57: 0.43 | BJ57: 2.467 | BK57: 0.474 | BL57: 0.449 | BN57: 4.099 | BO57: 3.369 | BP57: 3.35 | BR57: 0.865 | BT57: 101.5
A58: 38442 | B58: 201500 | C58: 229300 | D58: 0.0604 | E58: 0.0263 | F58: 0.045 | G58: 0.02238654 | I58: 71060 | K58: 445000 | L58: 2062000 | M58: 0.052 | N58: 0.0142 | O58: 0.14799802 | Q58: 0.0162 | R58: 0.0161 | S58: 0.037 | T58: 0.101 | U58: 4044000 | V58: 0.091 | W58: 2491900 | X58: 215.2 | Z58: 120.1 | AA58: 218.1 | AB58: 112 | AC58: 0.094 | AD58: 3.226 | AE58: 1.132 | AF58: 1.002 | AH58: 150 | AI58: 123.6 | AJ58: 319.7 | AK58: 189.1 | AL58: 183.3 | AM58: 106.8 | AN58: 99.5 | AO58: 217.4 | AP58: 2.218 | AQ58: 3.009 | AR58: 110.9 | AS58: 433 | AU58: 138.3 | AW58: 215.4 | AX58: 1.096 | AY58: 128.6 | AZ58: 210.1 | BA58: 126.1 | BC58: 330.2 | BE58: 191.7 | BF58: 203.3 | BG58: 0.57 | BH58: 0.326 | BI58: 0.433 | BJ58: 1.548 | BK58: 0.507 | BL58: 0.44 | BN58: 4.354 | BO58: 3.355 | BP58: 3.224 | BR58: 0.783 | BT58: 101.5
A59: 38533 | B59: 229000 | C59: 226100 | D59: 0.0553 | E59: 0.0304 | F59: 0.0394 | G59: 0.02191008 | I59: 71060 | K59: 455000 | L59: 2178000 | M59: 0.05 | N59: 0.0155 | O59: 0.14828576 | Q59: 0.015 | R59: 0.0151 | S59: 0.0367 | T59: 0.098 | U59: 4062000 | V59: 0.09 | W59: 2529300 | X59: 209.6 | Z59: 128.8 | AA59: 219.1 | AB59: 113.8 | AC59: 0.104 | AD59: 3.122 | AE59: 1.139 | AF59: 1.09 | AH59: 152 | AI59: 123.6 | AJ59: 322.8 | AK59: 190.5 | AL59: 184.6 | AM59: 108.4 | AN59: 99.8 | AO59: 219.6 | AP59: 2.338 | AQ59: 3.416 | AR59: 111.2 | AS59: 440.4 | AU59: 139.3 | AW59: 217 | AX59: 1.124 | AY59: 130.1 | AZ59: 222.4 | BA59: 126 | BC59: 325.4 | BE59: 193.2 | BF59: 203 | BG59: 0.547 | BH59: 0.337 | BI59: 0.428 | BJ59: 1.655 | BK59: 0.493 | BL59: 0.455 | BN59: 4.44 | BO59: 3.457 | BP59: 3.519 | BR59: 1.012 | BT59: 102.6
A60: 38625 | B60: 225400 | C60: 240400 | D60: 0.0591 | E60: 0.0362 | F60: 0.0434 | G60: 0.02326514 | I60: 71060 | K60: 487000 | L60: 2263000 | M60: 0.05 | N60: 0.0159 | O60: 0.15139959 | Q60: 0.0147 | R60: 0.0155 | S60: 0.039 | T60: 0.099 | U60: 4352000 | V60: 0.09 | W60: 2600100 | X60: 202.4 | Z60: 134.9 | AA60: 218.6 | AB60: 117 | AC60: 0.106 | AD60: 3.133 | AE60: 1.279 | AF60: 1.052 | AH60: 152.6 | AI60: 123.7 | AJ60: 325.3 | AK60: 191.5 | AL60: 184.7 | AM60: 108.9 | AN60: 98.9 | AO60: 218.1 | AP60: 2.377 | AQ60: 3.376 | AR60: 112.7 | AS60: 446.6 | AU60: 140.3 | AW60: 218.7 | AX60: 1.324 | AY60: 131.4 | AZ60: 220.7 | BA60: 125.7 | BC60: 334.8 | BE60: 194.6 | BF60: 204.6 | BG60: 0.544 | BH60: 0.329 | BI60: 0.437 | BJ60: 1.429 | BK60: 0.485 | BL60: 0.482 | BN60: 4.321 | BO60: 3.404 | BP60: 3.302 | BR60: 1.363 | BT60: 102.7
A61: 38717 | B61: 221600 | C61: 238600 | D61: 0.0622 | E61: 0.0416 | F61: 0.0439 | G61: 0.02463042 | I61: 71060 | K61: 511000 | L61: 2120000 | M61: 0.049 | N61: 0.0164 | O61: 0.1502855 | Q61: 0.0144 | R61: 0.016 | S61: 0.0354 | T61: 0.096 | U61: 4282000 | V61: 0.086 | W61: 2633500 | X61: 195.3 | Z61: 138.9 | AA61: 222.3 | AB61: 118.9 | AC61: 0.102 | AD61: 3.241 | AE61: 1.35 | AF61: 1.046 | AH61: 154.1 | AI61: 123.7 | AJ61: 329.2 | AK61: 192.9 | AL61: 185.7 | AM61: 109.4 | AN61: 99.7 | AO61: 217 | AP61: 2.303 | AQ61: 3.235 | AR61: 114 | AS61: 452.7 | AU61: 140.2 | AW61: 220.3 | AX61: 1.498 | AY61: 133.2 | AZ61: 217.6 | BA61: 126.4 | BC61: 338.6 | BE61: 196 | BF61: 206.6 | BG61: 0.524 | BH61: 0.303 | BI61: 0.449 | BJ61: 1.848 | BK61: 0.482 | BL61: 0.498 | BN61: 4.433 | BO61: 3.327 | BP61: 3.459 | BR61: 0.885 | BT61: 103.4
A62: 38807 | B62: 217200 | C62: 238800 | D62: 0.0635 | E62: 0.0459 | F62: 0.0486 | G62: 0.02575349 | I62: 71850 | K62: 552000 | L62: 2118000 | M62: 0.047 | N62: 0.0161 | O62: 0.14989443 | Q62: 0.0139 | R62: 0.0152 | S62: 0.0386 | T62: 0.095 | U62: 4732000 | V62: 0.082 | W62: 2640300 | X62: 206.6 | Z62: 139.8 | AA62: 224.8 | AB62: 124.8 | AC62: 0.109 | AD62: 3.161 | AE62: 1.302 | AF62: 1.04 | AG62: 3.295 | AH62: 154.8 | AI62: 123.8 | AJ62: 332.6 | AK62: 194 | AL62: 189.7 | AM62: 110.3 | AN62: 100.9 | AO62: 227 | AP62: 2.251 | AQ62: 3.301 | AR62: 115.4 | AS62: 459.5 | AU62: 140.8 | AW62: 222.2 | AX62: 1.335 | AY62: 134.9 | AZ62: 222.6 | BA62: 126.7 | BC62: 341.9 | BD62: 12.9 | BE62: 197.6 | BF62: 208.5 | BG62: 0.534 | BH62: 0.326 | BI62: 0.471 | BJ62: 1.649 | BK62: 0.508 | BL62: 0.517 | BM62: 1.383 | BN62: 4.365 | BO62: 3.396 | BP62: 3.517 | BR62: 0.888 | BT62: 104
A63: 38898 | B63: 230100 | C63: 243200 | D63: 0.0678 | E63: 0.0499 | F63: 0.0515 | G63: 0.03029285 | I63: 71850 | K63: 566000 | L63: 1867000 | M63: 0.046 | N63: 0.0162 | O63: 0.15044255 | Q63: 0.013 | R63: 0.0145 | S63: 0.0413 | T63: 0.096 | U63: 4614000 | V63: 0.084 | W63: 2648700 | X63: 194.5 | Z63: 139.6 | AA63: 233.9 | AB63: 126.6 | AC63: 0.118 | AD63: 3.001 | AE63: 1.242 | AF63: 1.074 | AG63: 3.277 | AH63: 155.8 | AI63: 123.9 | AJ63: 336 | AK63: 194.7 | AL63: 190.2 | AM63: 111.9 | AN63: 100.7 | AO63: 226.8 | AP63: 2.237 | AQ63: 3.158 | AR63: 117 | AS63: 466.5 | AU63: 141 | AW63: 224.6 | AX63: 1.21 | AY63: 136.6 | AZ63: 234.3 | BA63: 127.3 | BC63: 345.2 | BD63: 12.7 | BE63: 199.2 | BF63: 209.1 | BG63: 0.549 | BH63: 0.336 | BI63: 0.504 | BJ63: 1.457 | BK63: 0.511 | BL63: 0.541 | BM63: 1.32 | BN63: 4.234 | BO63: 3.399 | BP63: 3.369 | BR63: 1.119 | BT63: 104.2
A64: 38990 | B64: 221100 | C64: 226700 | D64: 0.0631 | E64: 0.0525 | F64: 0.0464 | G64: 0.03207054 | I64: 71850 | K64: 559000 | L64: 1655000 | M64: 0.045 | N64: 0.0174 | O64: 0.15367228 | Q64: 0.0126 | R64: 0.0157 | S64: 0.0412 | T64: 0.099 | U64: 4737000 | V64: 0.08 | W64: 2642700 | X64: 180.2 | Z64: 145.2 | AA64: 234.3 | AB64: 128.1 | AC64: 0.118 | AD64: 3.049 | AE64: 1.254 | AF64: 1.083 | AG64: 3.397 | AH64: 156.2 | AI64: 123.6 | AJ64: 339.1 | AK64: 196.3 | AL64: 192.4 | AM64: 113.4 | AN64: 100.2 | AO64: 237.8 | AP64: 2.202 | AQ64: 3.173 | AR64: 118.7 | AS64: 473.9 | AU64: 139.9 | AW64: 227.2 | AX64: 1.239 | AY64: 138.2 | AZ64: 229.5 | BA64: 127.1 | BC64: 347.5 | BD64: 12.3 | BE64: 200.5 | BF64: 210.7 | BG64: 0.55 | BH64: 0.341 | BI64: 0.515 | BJ64: 1.908 | BK64: 0.479 | BL64: 0.563 | BM64: 1.43 | BN64: 4.215 | BO64: 3.552 | BP64: 3.533 | BR64: 1.483 | BT64: 104.5
A65: 39082 | B65: 220800 | C65: 244700 | D65: 0.0618 | E65: 0.0524 | F65: 0.0471 | G65: 0.031159 | I65: 71850 | K65: 536000 | L65: 1638000 | M65: 0.044 | N65: 0.0192 | O65: 0.15509711 | Q65: 0.0115 | R65: 0.0175 | S65: 0.0395 | T65: 0.098 | U65: 4620000 | V65: 0.079 | W65: 2637500 | X65: 165.7 | Z65: 146.1 | AA65: 239.9 | AB65: 128.6 | AC65: 0.11 | AD65: 3.004 | AE65: 1.543 | AF65: 1.137 | AG65: 3.284 | AH65: 156.4 | AI65: 124.2 | AJ65: 341.2 | AK65: 197.1 | AL65: 193.9 | AM65: 114.5 | AN65: 97.4 | AO65: 242.8 | AP65: 2.259 | AQ65: 3.113 | AR65: 119.5 | AS65: 481.3 | AU65: 137.2 | AW65: 229.8 | AX65: 1.285 | AY65: 139.6 | AZ65: 217.8 | BA65: 127 | BC65: 347.5 | BD65: 11.2 | BE65: 202.2 | BF65: 212.5 | BG65: 0.555 | BH65: 0.318 | BI65: 0.506 | BJ65: 1.639 | BK65: 0.499 | BL65: 0.517 | BM65: 1.455 | BN65: 4.015 | BO65: 3.458 | BP65: 3.409 | BR65: 0.958 | BT65: 106
A66: 39172 | B66: 216200 | C66: 262600 | D66: 0.0616 | E66: 0.0526 | F66: 0.0465 | G66: 0.03099888 | I66: 73010 | K66: 545000 | L66: 1596000 | M66: 0.044 | N66: 0.0208 | O66: 0.15526607 | Q66: 0.0119 | R66: 0.0175 | S66: 0.0398 | T66: 0.101 | U66: 4962000 | V66: 0.08 | W66: 2646700 | X66: 174.8 | Z66: 142.8 | AA66: 263.1 | AB66: 131.2 | AC66: 0.113 | AD66: 3.072 | AE66: 1.634 | AF66: 1.161 | AG66: 3.337 | AH66: 157.1 | AI66: 124 | AJ66: 345.899 | AK66: 200.432 | AL66: 194.8 | AM66: 116.7 | AN66: 101.2 | AO66: 242.5 | AP66: 2.292 | AQ66: 3.475 | AR66: 120.485 | AS66: 486.972 | AU66: 135.201 | AW66: 232.349 | AX66: 1.291 | AY66: 141.621 | AZ66: 225.893 | BA66: 127.655 | BC66: 346.967 | BD66: 10.816 | BE66: 204.082 | BF66: 215.091 | BG66: 0.548 | BH66: 0.357 | BI66: 0.518 | BJ66: 1.555 | BK66: 0.51 | BL66: 0.518 | BM66: 1.631 | BN66: 4.082 | BO66: 3.464 | BP66: 3.485 | BQ66: 85.1 | BR66: 1.301 | BT66: 106.6
A67: 39263 | B67: 229200 | C67: 235500 | D67: 0.0667 | E67: 0.0525 | F67: 0.0503 | G67: 0.02621714 | I67: 73010 | K67: 542000 | L67: 1407000 | M67: 0.046 | N67: 0.0229 | O67: 0.1563251 | Q67: 0.0119 | R67: 0.0179 | S67: 0.0402 | T67: 0.095 | U67: 4859000 | V67: 0.083 | W67: 2604300 | X67: 174.4 | Z67: 142.7 | AA67: 263.3 | AB67: 131.8 | AC67: 0.122 | AD67: 3.427 | AE67: 1.373 | AF67: 1.193 | AG67: 3.513 | AH67: 159.1 | AI67: 123.1 | AJ67: 349.513 | AK67: 202.557 | AL67: 195.3 | AM67: 117.6 | AN67: 102.7 | AO67: 242.5 | AP67: 2.333 | AQ67: 3.407 | AR67: 120.885 | AS67: 492.45 | AU67: 134.57 | AW67: 234.283 | AX67: 1.299 | AY67: 143.337 | AZ67: 233.389 | BA67: 127.361 | BC67: 351.704 | BD67: 10.612 | BE67: 205.934 | BF67: 215.86 | BG67: 0.529 | BH67: 0.35 | BI67: 0.521 | BJ67: 1.51 | BK67: 0.512 | BL67: 0.538 | BM67: 1.425 | BN67: 3.981 | BO67: 3.657 | BP67: 3.473 | BQ67: 85.4 | BR67: 1.321 | BT67: 107.2
A68: 39355 | B68: 208600 | C68: 240300 | D68: 0.0642 | E68: 0.0494 | F68: 0.0459 | G68: 0.02475003 | I68: 73010 | K68: 527000 | L68: 1261000 | M68: 0.047 | N68: 0.0272 | O68: 0.15712123 | Q68: 0.0121 | R68: 0.0212 | S68: 0.0441 | T68: 0.098 | U68: 4652000 | V68: 0.084 | W68: 2557000 | X68: 169.5 | Z68: 143.5 | AA68: 263.9 | AB68: 132.3 | AC68: 0.121 | AD68: 3.841 | AE68: 1.825 | AF68: 1.212 | AG68: 3.528 | AH68: 158.8 | AI68: 123.7 | AJ68: 354.531 | AK68: 205.003 | AL68: 195.7 | AM68: 118.7 | AN68: 102.7 | AO68: 242.5 | AP68: 2.372 | AQ68: 3.497 | AR68: 122.292 | AS68: 498.288 | AU68: 136.022 | AW68: 236.239 | AX68: 1.207 | AY68: 145.177 | AZ68: 230.694 | BA68: 126.193 | BC68: 353.405 | BD68: 10.502 | BE68: 208.805 | BF68: 217.589 | BG68: 0.546 | BH68: 0.36 | BI68: 0.518 | BJ68: 1.496 | BK68: 0.505 | BL68: 0.52 | BM68: 1.494 | BN68: 4.479 | BO68: 3.784 | BP68: 3.558 | BQ68: 83.8 | BR68: 1.503 | BT68: 108.9
A69: 39447 | B69: 205000 | C69: 227700 | D69: 0.0617 | E69: 0.0424 | F69: 0.0404 | G69: 0.02712396 | I69: 73010 | K69: 497000 | L69: 1149000 | M69: 0.05 | N69: 0.031 | O69: 0.15846367 | Q69: 0.013 | R69: 0.0256 | S69: 0.046 | T69: 0.096 | U69: 4545000 | V69: 0.088 | W69: 2541900 | X69: 159 | Z69: 149.4 | AA69: 264 | AB69: 133.2 | AC69: 0.115 | AD69: 3.87 | AE69: 2.099 | AF69: 1.28 | AG69: 3.376 | AH69: 159.7 | AI69: 124.6 | AJ69: 358.908 | AK69: 206.874 | AL69: 195.8 | AM69: 119.9 | AN69: 102.9 | AO69: 245.5 | AP69: 2.234 | AQ69: 3.685 | AR69: 123.928 | AS69: 507.107 | AU69: 137.855 | AW69: 238.873 | AX69: 1.281 | AY69: 147.094 | AZ69: 233.408 | BA69: 126.066 | BC69: 356.176 | BD69: 10.247 | BE69: 210.233 | BF69: 219.656 | BG69: 0.551 | BH69: 0.398 | BI69: 0.503 | BJ69: 2.147 | BK69: 0.525 | BL69: 0.52 | BM69: 1.775 | BN69: 4.445 | BO69: 3.688 | BP69: 3.646 | BQ69: 83.8 | BR69: 0.905 | BS69: 100 | BT69: 108.4
A70: 39538 | B70: 197600 | C70: 229300 | D70: 0.0585 | E70: 0.0261 | F70: 0.0345 | G70: 0.02688949 | I70: 70520 | K70: 470000 | L70: 967000 | M70: 0.051 | N70: 0.0368 | O70: 0.15775857 | Q70: 0.0144 | R70: 0.029 | S70: 0.0477 | T70: 0.101 | U70: 4225000 | V70: 0.091 | W70: 2485800 | X70: 152 | Z70: 141 | AA70: 267.9 | AB70: 134.3 | AC70: 0.116 | AD70: 3.781 | AE70: 2.203 | AF70: 1.35 | AG70: 3.372 | AH70: 159.8 | AI70: 125.1 | AJ70: 361.533 | AK70: 209.324 | AL70: 197.2 | AM70: 119.5 | AN70: 103.6 | AO70: 252.4 | AP70: 2.293 | AQ70: 3.685 | AR70: 126.325 | AS70: 513.602 | AU70: 138.541 | AW70: 240.68 | AX70: 1.358 | AY70: 149.199 | AZ70: 242.929 | BA70: 127.423 | BC70: 359.246 | BD70: 10.204 | BE70: 212.537 | BF70: 222.752 | BG70: 0.584 | BH70: 0.489 | BI70: 0.504 | BJ70: 1.835 | BK70: 0.597 | BL70: 0.542 | BM70: 1.587 | BN70: 4.572 | BO70: 3.623 | BP70: 3.771 | BQ70: 87 | BR70: 0.898 | BT70: 112
A71: 39629 | B71: 213600 | C71: 234300 | D71: 0.0645 | E71: 0.02 | F71: 0.0399 | G71: 0.02933931 | I71: 70520 | K71: 435000 | L71: 1180000 | M71: 0.056 | N71: 0.0436 | O71: 0.15326612 | Q71: 0.0177 | R71: 0.0319 | S71: 0.049 | T71: 0.1 | U71: 3830000 | V71: 0.1 | W71: 2403100 | X71: 166.6 | Z71: 162.7 | AA71: 272.2 | AB71: 136.2 | AC71: 0.128 | AD71: 3.773 | AE71: 1.92 | AF71: 1.373 | AG71: 3.403 | AH71: 161.1 | AI71: 125.4 | AJ71: 363.671 | AK71: 213.333 | AL71: 199.1 | AM71: 122.3 | AN71: 103.8 | AO71: 263.4 | AP71: 2.269 | AQ71: 3.685 | AR71: 127.824 | AS71: 520.48 | AU71: 135.02 | AW71: 242.882 | AX71: 1.578 | AY71: 151.238 | AZ71: 264.681 | BA71: 127.625 | BC71: 357.325 | BD71: 10.085 | BE71: 215.015 | BF71: 223.52 | BG71: 0.753 | BH71: 0.529 | BI71: 0.525 | BJ71: 1.814 | BK71: 0.633 | BL71: 0.598 | BM71: 1.59 | BN71: 4.54 | BO71: 3.655 | BP71: 4.062 | BQ71: 87 | BR71: 1.136 | BT71: 112.6
A72: 39721 | B72: 190300 | C72: 225200 | D72: 0.0609 | E72: 0.0181 | F72: 0.0385 | G72: 0.03071629 | I72: 70520 | K72: 395000 | L72: 797000 | M72: 0.061 | N72: 0.0528 | O72: 0.15546547 | Q72: 0.0177 | R72: 0.0369 | S72: 0.048 | T72: 0.099 | U72: 3222000 | V72: 0.111 | W72: 2305900 | X72: 162.9 | Z72: 207.8 | AA72: 273.2 | AB72: 137.6 | AC72: 0.13 | AD72: 3.773 | AE72: 1.978 | AF72: 1.379 | AG72: 3.359 | AH72: 162.4 | AI72: 125.6 | AJ72: 365.841 | AK72: 217.768 | AL72: 209.9 | AM72: 125.8 | AN72: 106.1 | AO72: 298.5 | AP72: 2.419 | AQ72: 3.685 | AR72: 131.048 | AS72: 528.244 | AU72: 131.176 | AW72: 245.175 | AX72: 1.448 | AY72: 154.139 | AZ72: 261.318 | BA72: 128.584 | BC72: 362.641 | BD72: 9.93 | BE72: 218.225 | BF72: 224.614 | BG72: 0.853 | BH72: 0.532 | BI72: 0.563 | BJ72: 1.591 | BK72: 0.631 | BL72: 0.763 | BM72: 1.884 | BN72: 4.815 | BO72: 3.725 | BP72: 4.123 | BQ72: 93.1 | BR72: 1.471 | BT72: 114
A73: 39813 | B73: 175000 | C73: 229600 | D73: 0.051 | E73: 0.0016 | F73: 0.0225 | G73: 0.02614507 | I73: 70520 | K73: 353000 | L73: 554000 | M73: 0.073 | N73: 0.0658 | O73: 0.1572136 | Q73: 0.0254 | R73: 0.049 | S73: 0.0564 | T73: 0.101 | U73: 3146000 | V73: 0.136 | W73: 2050500 | X73: 146.1 | Z73: 233.2 | AA73: 271.4 | AB73: 138.8 | AC73: 0.124 | AD73: 3.681 | AE73: 1.834 | AF73: 1.415 | AG73: 3.284 | AH73: 162.5 | AI73: 127 | AJ73: 368.748 | AK73: 219.073 | AL73: 216.5 | AM73: 125.7 | AN73: 107.3 | AO73: 302.6 | AP73: 2.406 | AQ73: 3.685 | AR73: 133.077 | AS73: 535.488 | AU73: 127.323 | AW73: 246.992 | AX73: 1.355 | AY73: 156.673 | AZ73: 237.638 | BA73: 128.535 | BC73: 362.69 | BD73: 9.935 | BE73: 220.684 | BF73: 226.281 | BG73: 0.813 | BH73: 0.504 | BI73: 0.534 | BJ73: 1.734 | BK73: 0.617 | BL73: 0.678 | BM73: 1.821 | BN73: 4.952 | BO73: 3.67 | BP73: 4.482 | BQ73: 94.2 | BR73: 0.934 | BT73: 111.3
A74: 39903 | B74: 169700 | C74: 205100 | D74: 0.0485 | E74: 0.0018 | F74: 0.0271 | G74: 0.02437701 | I74: 70070 | K74: 311000 | L74: 513000 | M74: 0.087 | N74: 0.0801 | O74: 0.155975 | Q74: 0.0317 | R74: 0.0572 | S74: 0.0651 | T74: 0.101 | U74: 2534000 | V74: 0.158 | W74: 1835800 | X74: 134.8 | Z74: 226.3 | AA74: 273.2 | AB74: 139.3 | AC74: 0.126 | AD74: 3.116 | AE74: 1.693 | AF74: 1.41 | AG74: 3.405 | AH74: 162.8 | AI74: 128.2 | AJ74: 371.705 | AK74: 218.51 | AL74: 213.9 | AM74: 124.5 | AN74: 111.5 | AO74: 299.6 | AP74: 2.269 | AQ74: 3.685 | AR74: 134.484 | AS74: 541.493 | AU74: 122.21 | AV74: 99.7 | AW74: 248.396 | AX74: 1.208 | AY74: 157.985 | AZ74: 230.735 | BA74: 129.669 | BC74: 365.245 | BD74: 9.832 | BE74: 222.216 | BF74: 227.982 | BG74: 0.774 | BH74: 0.503 | BI74: 0.571 | BJ74: 1.511 | BK74: 0.634 | BL74: 0.652 | BM74: 1.762 | BN74: 4.758 | BO74: 3.59 | BP74: 4.55 | BQ74: 94.2 | BR74: 0.889 | BT74: 114.9
A75: 39994 | B75: 181900 | C75: 214700 | D75: 0.0542 | E75: 0.0021 | F75: 0.0353 | G75: 0.02078064 | I75: 70070 | K75: 280000 | L75: 601000 | M75: 0.095 | N75: 0.0857 | O75: 0.15251967 | Q75: 0.0378 | R75: 0.0615 | S75: 0.0677 | T75: 0.106 | U75: 2503000 | V75: 0.165 | W75: 1753800 | X75: 135.6 | Z75: 223.7 | AA75: 273.3 | AB75: 138.3 | AC75: 0.132 | AD75: 3.009 | AE75: 1.529 | AF75: 1.385 | AG75: 3.398 | AH75: 164.4 | AI75: 129.1 | AJ75: 375.177 | AK75: 217.813 | AL75: 213 | AM75: 123.9 | AN75: 108.8 | AO75: 301.8 | AP75: 2.234 | AQ75: 3.685 | AR75: 134.27 | AS75: 547.876 | AT75: 102.1 | AU75: 123.236 | AV75: 100.4 | AW75: 249.381 | AX75: 1.06 | AY75: 160.548 | AZ75: 232.54 | BA75: 129.623 | BC75: 368.081 | BD75: 9.737 | BE75: 223.163 | BF75: 227.572 | BG75: 0.766 | BH75: 0.516 | BI75: 0.562 | BJ75: 1.604 | BK75: 0.617 | BL75: 0.634 | BM75: 1.637 | BN75: 4.723 | BO75: 3.621 | BP75: 4.557 | BQ75: 94.2 | BR75: 1.06 | BT75: 114.9
A76: 40086 | B76: 175900 | C76: 216600 | D76: 0.0504 | E76: 0.0015 | F76: 0.0331 | G76: 0.01602846 | I76: 70070 | K76: 252000 | L76: 609000 | M76: 0.098 | N76: 0.0947 | O76: 0.1508588 | Q76: 0.0439 | R76: 0.0688 | S76: 0.0649 | T76: 0.111 | U76: 2487000 | V76: 0.167 | W76: 1778300 | X76: 146.1 | Z76: 217.8 | AA76: 273.3 | AB76: 136.8 | AC76: 0.13 | AD76: 2.981 | AE76: 1.627 | AF76: 1.34 | AG76: 3.285 | AH76: 168.2 | AI76: 130 | AJ76: 378.359 | AK76: 217.258 | AL76: 207.5 | AM76: 123.6 | AN76: 107.1 | AO76: 301.8 | AP76: 2.138 | AQ76: 3.685 | AR76: 133.406 | AS76: 554.747 | AT76: 100.9 | AU76: 127.631 | AV76: 101.9 | AW76: 249.261 | AX76: 1.028 | AY76: 163.238 | AZ76: 239.855 | BA76: 128.201 | BC76: 369.279 | BD76: 9.499 | BE76: 224.003 | BF76: 228.286 | BG76: 0.76 | BH76: 0.51 | BI76: 0.58 | BJ76: 1.538 | BK76: 0.605 | BL76: 0.612 | BM76: 1.678 | BN76: 4.61 | BO76: 3.592 | BP76: 4.627 | BQ76: 95.9 | BR76: 1.255 | BT76: 117
A77: 40178 | B77: 169600 | C77: 222600 | D77: 0.0514 | E77: 0.0012 | F77: 0.0385 | G77: 0.01318775 | I77: 70070 | K77: 234000 | L77: 664000 | M77: 0.099 | N77: 0.104 | O77: 0.14896385 | Q77: 0.0427 | R77: 0.0749 | S77: 0.0633 | T77: 0.107 | U77: 2568000 | V77: 0.172 | W77: 1905500 | X77: 150.3 | Z77: 217.2 | AA77: 273.5 | AB77: 136.1 | AC77: 0.124 | AD77: 3.105 | AE77: 1.772 | AF77: 1.39 | AG77: 3.31 | AH77: 169.3 | AI77: 131.8 | AJ77: 381.111 | AK77: 217.904 | AL77: 207.1 | AM77: 123.6 | AN77: 107.4 | AO77: 301.2 | AP77: 2.186 | AQ77: 3.669 | AR77: 134.781 | AS77: 560.087 | AT77: 104.7 | AU77: 139.376 | AV77: 103.3 | AW77: 248.667 | AX77: 1.105 | AY77: 165.532 | AZ77: 245.203 | BA77: 127.119 | BC77: 370.954 | BD77: 9.445 | BE77: 224.789 | BF77: 228.343 | BG77: 0.751 | BH77: 0.464 | BI77: 0.596 | BJ77: 1.961 | BK77: 0.571 | BL77: 0.56 | BM77: 2.097 | BN77: 4.552 | BO77: 3.57 | BP77: 4.653 | BQ77: 96.2 | BR77: 0.932 | BT77: 116.1
A78: 40268 | B78: 169500 | C78: 224800 | D78: 0.0499 | E78: 0.0016 | F78: 0.0384 | G78: 0.009255025 | I78: 68420 | K78: 227000 | L78: 687000 | M78: 0.099 | N78: 0.1149 | O78: 0.1451494 | Q78: 0.0392 | R78: 0.075 | S78: 0.0578 | T78: 0.106 | U78: 2679000 | V78: 0.171 | W78: 1993000 | X78: 166.7 | Z78: 219.4 | AA78: 274.1 | AB78: 136.1 | AC78: 0.125 | AD78: 3.188 | AE78: 1.822 | AF78: 1.368 | AG78: 3.261 | AH78: 168.7 | AI78: 132.5 | AJ78: 385.712 | AK78: 218.99 | AL78: 206.5 | AM78: 123.3 | AN78: 104.2 | AO78: 301.9 | AP78: 2.24 | AQ78: 3.565 | AR78: 135.523 | AS78: 567.221 | AT78: 105.6 | AU78: 142.377 | AV78: 104.9 | AW78: 248.854 | AX78: 1.137 | AY78: 168.47 | AZ78: 244.766 | BA78: 126.75 | BC78: 370.119 | BD78: 9.525 | BE78: 224.991 | BF78: 228.429 | BG78: 0.764 | BH78: 0.479 | BI78: 0.636 | BJ78: 2.007 | BK78: 0.575 | BL78: 0.557 | BM78: 1.776 | BN78: 4.708 | BO78: 3.669 | BP78: 4.57 | BQ78: 96.3 | BR78: 0.858 | BT78: 117.1
A79: 40359 | B79: 183500 | C79: 219500 | D79: 0.0469 | E79: 0.0018 | F79: 0.0297 | G79: 0.007780126 | I79: 68420 | K79: 212000 | L79: 587000 | M79: 0.094 | N79: 0.1108 | O79: 0.14069775 | Q79: 0.0364 | R79: 0.0699 | S79: 0.051 | T79: 0.106 | U79: 2801000 | V79: 0.164 | W79: 2093800 | X79: 162.9 | Z79: 225.7 | AA79: 275.6 | AB79: 135.3 | AC79: 0.132 | AD79: 3.297 | AE79: 1.494 | AF79: 1.383 | AG79: 3.323 | AH79: 169.6 | AI79: 132.7 | AJ79: 388.188 | AK79: 219.285 | AL79: 208 | AM79: 123.3 | AN79: 104.2 | AO79: 303.8 | AP79: 2.4 | AQ79: 3.697 | AR79: 136.686 | AS79: 573.555 | AT79: 104.2 | AU79: 141.951 | AV79: 105.9 | AW79: 249.327 | AX79: 1.084 | AY79: 170.505 | AZ79: 257.825 | BA79: 125.589 | BC79: 373.545 | BD79: 9.421 | BE79: 225.797 | BF79: 230.225 | BG79: 0.739 | BH79: 0.484 | BI79: 0.623 | BJ79: 1.586 | BK79: 0.577 | BL79: 0.585 | BM79: 1.847 | BN79: 4.525 | BO79: 4.046 | BP79: 4.706 | BQ79: 96.3 | BR79: 1.096 | BT79: 118.6
A80: 40451 | B80: 172400 | C80: 228000 | D80: 0.0432 | E80: 0.0019 | F80: 0.0253 | G80: 0.006638685 | I80: 68420 | K80: 201000 | L80: 563000 | M80: 0.095 | N80: 0.1065 | O80: 0.13917807 | Q80: 0.0332 | R80: 0.0685 | S80: 0.0458 | T80: 0.103 | U80: 2918000 | V80: 0.169 | W80: 2147000 | X80: 153.2 | Z80: 223 | AA80: 275.4 | AB80: 134.9 | AC80: 0.132 | AD80: 3.278 | AE80: 1.753 | AF80: 1.386 | AG80: 3.311 | AH80: 172.7 | AI80: 133.4 | AJ80: 391.288 | AK80: 220.219 | AL80: 207.8 | AM80: 124.3 | AN80: 104.2 | AO80: 320 | AP80: 2.398 | AQ80: 4.174 | AR80: 137.802 | AS80: 577.502 | AT80: 103 | AU80: 144.032 | AV80: 107 | AW80: 249.663 | AX80: 1.062 | AY80: 172.675 | AZ80: 252.525 | BA80: 124.535 | BC80: 372.59 | BD80: 9.372 | BE80: 227.075 | BF80: 230.332 | BG80: 0.723 | BH80: 0.483 | BI80: 0.63 | BJ80: 1.503 | BK80: 0.573 | BL80: 0.597 | BM80: 1.781 | BN80: 4.726 | BO80: 4.574 | BP80: 4.631 | BQ80: 96 | BR80: 1.302 | BT80: 119
A81: 40543 | B81: 169300 | C81: 241200 | D81: 0.0486 | E81: 0.0018 | F81: 0.033 | G81: 0.008307821 | I81: 68420 | K81: 190000 | L81: 632000 | M81: 0.093 | N81: 0.1032 | O81: 0.13580863 | Q81: 0.0296 | R81: 0.0651 | S81: 0.0414 | T81: 0.094 | U81: 3058000 | V81: 0.166 | W81: 2259200 | X81: 159.2 | Y81: 100 | Z81: 222.6 | AA81: 275.9 | AB81: 134.9 | AC81: 0.125 | AD81: 3.318 | AE81: 1.793 | AF81: 1.386 | AG81: 3.324 | AH81: 173.1 | AI81: 135.1 | AJ81: 393.514 | AK81: 221.215 | AL81: 209.7 | AM81: 124.7 | AN81: 104.2 | AO81: 320 | AP81: 2.378 | AQ81: 4.146 | AR81: 139.223 | AS81: 582.695 | AT81: 103.5 | AU81: 145.669 | AV81: 107.5 | AW81: 250.641 | AX81: 1.078 | AY81: 174.973 | AZ81: 257.172 | BA81: 123.931 | BC81: 372.32 | BD81: 9.252 | BE81: 227.722 | BF81: 230.159 | BG81: 0.728 | BH81: 0.441 | BI81: 0.643 | BJ81: 1.591 | BK81: 0.587 | BL81: 0.582 | BM81: 1.828 | BN81: 4.933 | BO81: 4.16 | BP81: 4.742 | BQ81: 95.9 | BR81: 1.021 | BT81: 118.3
A82: 40633 | B82: 160600 | C82: 220500 | D82: 0.0486 | E82: 0.0014 | F82: 0.0347 | G82: 0.01179972 | I82: 67410 | K82: 179000 | L82: 583000 | M82: 0.09 | N82: 0.1037 | O82: 0.1330846 | Q82: 0.0244 | R82: 0.0627 | S82: 0.0382 | T82: 0.097 | U82: 3261000 | V82: 0.16 | W82: 2297200 | X82: 165 | Y82: 105 | Z82: 217.3 | AA82: 279.5 | AB82: 134.7 | AC82: 0.127 | AD82: 3.503 | AE82: 1.732 | AF82: 1.415 | AG82: 3.218 | AH82: 173.7 | AI82: 136.7 | AJ82: 396.29 | AK82: 225.213 | AL82: 214.6 | AM82: 126.8 | AN82: 102.2 | AO82: 320.1 | AP82: 2.715 | AQ82: 4.642 | AR82: 140.686 | AS82: 589.292 | AT82: 108.5 | AU82: 145.646 | AV82: 109.5 | AW82: 251.905 | AX82: 1.077 | AY82: 177.543 | AZ82: 270.366 | BA82: 124.735 | BC82: 375.256 | BD82: 9.133 | BE82: 229.282 | BF82: 230.034 | BG82: 0.745 | BH82: 0.508 | BI82: 0.664 | BJ82: 2.086 | BK82: 0.621 | BL82: 0.636 | BM82: 2.182 | BN82: 5.065 | BO82: 4.537 | BP82: 4.837 | BQ82: 96.4 | BR82: 0.957 | BT82: 120.6
A83: 40724 | B83: 176100 | C83: 240200 | D83: 0.0451 | E83: 0.0009 | F83: 0.0318 | G83: 0.0129395 | I83: 67410 | K83: 166000 | L83: 636000 | M83: 0.091 | N83: 0.1055 | O83: 0.13057706 | Q83: 0.0212 | R83: 0.0582 | S83: 0.0365 | T83: 0.092 | U83: 3455000 | V83: 0.161 | W83: 2282200 | X83: 158.2 | Y83: 107.4 | Z83: 232.2 | AA83: 283.3 | AB83: 135 | AC83: 0.134 | AD83: 3.622 | AE83: 1.683 | AF83: 1.49 | AG83: 3.127 | AH83: 174.6 | AI83: 138.4 | AJ83: 399.416 | AK83: 227.515 | AL83: 224.8 | AM83: 127.7 | AN83: 105.1 | AO83: 323.3 | AP83: 2.774 | AQ83: 5.234 | AR83: 144.618 | AS83: 595.097 | AT83: 105.9 | AU83: 148.518 | AV83: 110.3 | AW83: 252.986 | AX83: 1.077 | AY83: 179.304 | AZ83: 272.297 | BA83: 125.048 | BC83: 377.248 | BD83: 9.008 | BE83: 231.097 | BF83: 230.614 | BG83: 0.755 | BH83: 0.528 | BI83: 0.684 | BJ83: 1.559 | BK83: 0.614 | BL83: 0.685 | BM83: 1.638 | BN83: 5.443 | BO83: 4.84 | BP83: 5.038 | BQ83: 96.1 | BR83: 1.014 | BT83: 120.4
A84: 40816 | B84: 165400 | C84: 217000 | D84: 0.0401 | E84: 0.0008 | F84: 0.0192 | G84: 0.01721515 | I84: 67410 | K84: 160000 | L84: 610000 | M84: 0.09 | N84: 0.105 | O84: 0.12944597 | Q84: 0.0184 | R84: 0.0567 | S84: 0.0345 | T84: 0.098 | U84: 3774000 | V84: 0.164 | W84: 2344900 | X84: 158.9 | Y84: 108 | Z84: 238.8 | AA84: 283.3 | AB84: 135.2 | AC84: 0.135 | AD84: 3.715 | AE84: 1.947 | AF84: 1.477 | AG84: 3.217 | AH84: 177 | AI84: 139.7 | AJ84: 402.202 | AK84: 230.682 | AL84: 225 | AM84: 128.7 | AN84: 105.1 | AO84: 323.1 | AP84: 2.868 | AQ84: 5.651 | AR84: 145.646 | AS84: 603.166 | AT84: 112.6 | AU84: 151.677 | AV84: 111 | AW84: 254.895 | AX84: 1.063 | AY84: 181.475 | AZ84: 271.199 | BA84: 125.013 | BC84: 381.479 | BD84: 8.953 | BE84: 233.032 | BF84: 230.974 | BG84: 0.719 | BH84: 0.55 | BI84: 0.702 | BJ84: 1.503 | BK84: 0.607 | BL84: 0.735 | BM84: 1.685 | BN84: 5.707 | BO84: 4.819 | BP84: 5.036 | BQ84: 96.1 | BR84: 1.438 | BT84: 121.3
A85: 40908 | B85: 162600 | C85: 218600 | D85: 0.0395 | E85: 0.0007 | F85: 0.0189 | G85: 0.02045078 | I85: 67410 | K85: 151000 | L85: 697000 | M85: 0.085 | N85: 0.1025 | O85: 0.12749684 | Q85: 0.0164 | R85: 0.0555 | S85: 0.0325 | T85: 0.094 | U85: 3768000 | V85: 0.152 | W85: 2404300 | X85: 158 | Y85: 105.2 | Z85: 228.9 | AA85: 283.1 | AB85: 135.6 | AC85: 0.127 | AD85: 3.565 | AE85: 1.874 | AF85: 1.42 | AG85: 3.102 | AH85: 179.2 | AI85: 141.8 | AJ85: 407.23 | AK85: 231.557 | AL85: 224.8 | AM85: 130.1 | AN85: 106.3 | AO85: 323.8 | AP85: 2.921 | AQ85: 5.437 | AR85: 147.499 | AS85: 609.736 | AT85: 110.9 | AU85: 152.083 | AV85: 111.5 | AW85: 256.8 | AX85: 1.034 | AY85: 183.219 | AZ85: 266.958 | BA85: 125.17 | BC85: 386.396 | BD85: 8.876 | BE85: 234.435 | BF85: 232.302 | BG85: 0.729 | BH85: 0.51 | BI85: 0.703 | BJ85: 1.531 | BK85: 0.599 | BL85: 0.666 | BM85: 1.707 | BN85: 5.43 | BO85: 4.55 | BP85: 5.032 | BQ85: 96.1 | BR85: 0.983 | BT85: 120.9
A86: 40999 | B86: 165100 | C86: 239800 | D86: 0.0399 | E86: 0.0013 | F86: 0.0223 | G86: 0.02122799 | H86: 206.3 | I86: 67400 | J86: 1653000 | K86: 145000 | L86: 806000 | M86: 0.082 | N86: 0.1033 | O86: 0.12237059 | P86: 0.1033 | Q86: 0.0153 | R86: 0.0533 | S86: 0.0306 | T86: 0.088 | U86: 3979000 | V86: 0.146 | W86: 2466400 | X86: 166.3 | Y86: 107.8 | Z86: 208 | AA86: 288.6 | AB86: 137.1 | AC86: 0.127 | AD86: 3.499 | AE86: 1.774 | AF86: 1.395 | AG86: 3.183 | AH86: 179.9 | AI86: 142.5 | AJ86: 410.257 | AK86: 232.591 | AL86: 227.7 | AM86: 131.7 | AN86: 107.2 | AO86: 323.7 | AP86: 3.016 | AQ86: 5.558 | AR86: 148.298 | AS86: 614.307 | AT86: 112.3 | AU86: 149.265 | AV86: 112.4 | AW86: 258.335 | AX86: 0.978 | AY86: 185.999 | AZ86: 269.566 | BA86: 126.107 | BB86: 126.7 | BC86: 391.599 | BD86: 8.806 | BE86: 236.073 | BF86: 233.3 | BG86: 0.7 | BH86: 0.519 | BI86: 0.711 | BJ86: 1.452 | BK86: 0.607 | BL86: 0.68 | BM86: 1.509 | BN86: 5.659 | BO86: 4.6 | BP86: 5.087 | BQ86: 96 | BR86: 0.85 | BT86: 122.3
A87: 41090 | B87: 189600 | C87: 232600 | D87: 0.0366 | E87: 0.0016 | F87: 0.0167 | G87: 0.02238926 | H87: 183.2 | I87: 67400 | J87: 1595000 | K87: 145000 | L87: 794000 | M87: 0.082 | N87: 0.1045 | O87: 0.12034065 | P87: 0.0915 | Q87: 0.014 | R87: 0.0502 | S87: 0.0292 | T87: 0.086 | U87: 3911000 | V87: 0.147 | W87: 2505900 | X87: 176.3 | Y87: 102.9 | Z87: 231.5 | AA87: 288.7 | AB87: 137.2 | AC87: 0.135 | AD87: 3.396 | AE87: 1.67 | AF87: 1.403 | AG87: 3.195 | AH87: 180.8 | AI87: 143.5 | AJ87: 415.289 | AK87: 233.683 | AL87: 230.5 | AM87: 130.8 | AN87: 108.4 | AO87: 337.9 | AP87: 3.007 | AQ87: 5.582 | AR87: 148.542 | AS87: 619.049 | AT87: 118.5 | AU87: 152.263 | AV87: 113.3 | AW87: 259.893 | AX87: 0.927 | AY87: 189.068 | AZ87: 276.784 | BA87: 126.054 | BB87: 131.1 | BC87: 395.478 | BD87: 8.799 | BE87: 237.839 | BF87: 233.981 | BG87: 0.681 | BH87: 0.519 | BI87: 0.684 | BJ87: 1.492 | BK87: 0.605 | BL87: 0.676 | BM87: 1.422 | BN87: 5.475 | BO87: 4.326 | BP87: 5.264 | BQ87: 95.8 | BR87: 1.032 | BS87: 116 | BT87: 121.8
A88: 41182 | B88: 178900 | C88: 254600 | D88: 0.034 | E88: 0.0014 | F88: 0.0165 | G88: 0.02219253 | H88: 198.6 | I88: 67400 | J88: 1476000 | K88: 144000 | L88: 930000 | M88: 0.078 | N88: 0.1048 | O88: 0.12083107 | P88: 0.0912 | Q88: 0.0125 | R88: 0.0502 | S88: 0.0282 | T88: 0.086 | U88: 3882000 | V88: 0.148 | W88: 2489500 | X88: 175.9 | Y88: 102.1 | Z88: 233.9 | AA88: 288.6 | AB88: 137.9 | AC88: 0.133 | AD88: 3.469 | AE88: 1.889 | AF88: 1.401 | AG88: 3.117 | AH88: 183.4 | AI88: 144.4 | AJ88: 418.453 | AK88: 234.404 | AL88: 230.8 | AM88: 131.2 | AN88: 107.6 | AO88: 340.7 | AP88: 3.024 | AQ88: 5.693 | AR88: 148.798 | AS88: 625.946 | AT88: 110.7 | AU88: 149.647 | AV88: 113.8 | AW88: 261.62 | AX88: 0.953 | AY88: 191.777 | AZ88: 268.791 | BA88: 125.31 | BB88: 137.7 | BC88: 400.681 | BD88: 8.643 | BE88: 239.565 | BF88: 234.913 | BG88: 0.684 | BH88: 0.528 | BI88: 0.685 | BJ88: 1.384 | BK88: 0.597 | BL88: 0.645 | BM88: 1.533 | BN88: 5.575 | BO88: 4.692 | BP88: 4.785 | BQ88: 95.8 | BR88: 1.296 | BS88: 114.6 | BT88: 122.4
A89: 41274 | B89: 180300 | C89: 258300 | D89: 0.0335 | E89: 0.0016 | F89: 0.0178 | G89: 0.02107127 | H89: 207.1 | I89: 67400 | J89: 1499000 | K89: 150000 | L89: 941000 | M89: 0.079 | N89: 0.1003 | O89: 0.11754033 | P89: 0.0882 | Q89: 0.0118 | R89: 0.0472 | S89: 0.0271 | T89: 0.087 | U89: 3970000 | V89: 0.144 | W89: 2539400 | X89: 185.7 | Y89: 103.6 | Z89: 227.7 | AA89: 288.6 | AB89: 139.1 | AC89: 0.127 | AD89: 3.58 | AE89: 2.007 | AF89: 1.436 | AG89: 3.267 | AH89: 183.7 | AI89: 145.6 | AJ89: 420.321 | AK89: 235.677 | AL89: 230.7 | AM89: 132.2 | AN89: 109 | AO89: 340.6 | AP89: 3.08 | AQ89: 5.921 | AR89: 148.761 | AS89: 631.853 | AT89: 111.4 | AU89: 149.243 | AV89: 114.4 | AW89: 263.669 | AX89: 1.004 | AY89: 193.706 | AZ89: 273.364 | BA89: 125.202 | BB89: 134.8 | BC89: 400.418 | BD89: 8.582 | BE89: 240.359 | BF89: 236.46 | BG89: 0.714 | BH89: 0.5 | BI89: 0.682 | BJ89: 1.594 | BK89: 0.606 | BL89: 0.621 | BM89: 1.487 | BN89: 5.867 | BO89: 4.639 | BP89: 4.713 | BQ89: 95.8 | BR89: 1.035 | BS89: 114.1 | BT89: 122.5
A90: 41364 | B90: 184500 | C90: 257500 | D90: 0.0357 | E90: 0.0014 | F90: 0.0187 | G90: 0.02096923 | H90: 195.5 | I90: 69950 | J90: 1611000 | K90: 155000 | L90: 936000 | M90: 0.075 | N90: 0.0973 | O90: 0.12006598 | P90: 0.0808 | Q90: 0.0111 | R90: 0.0445 | S90: 0.0264 | T90: 0.086 | U90: 4076000 | V90: 0.139 | W90: 2587800 | X90: 216.7 | Y90: 104.1 | Z90: 224.7 | AA90: 289.2 | AB90: 140.2 | AC90: 0.128 | AD90: 3.431 | AE90: 1.925 | AF90: 1.412 | AG90: 3.226 | AH90: 184.5 | AI90: 146.3 | AJ90: 423.089 | AK90: 236.213 | AL90: 230.2 | AM90: 134 | AN90: 108.8 | AO90: 339.8 | AP90: 3.332 | AQ90: 6.014 | AR90: 147.916 | AS90: 638.068 | AT90: 110.2 | AU90: 148.912 | AV90: 114.3 | AW90: 265.603 | AX90: 0.994 | AY90: 195.671 | AZ90: 280.356 | BA90: 125.33 | BB90: 137 | BC90: 403.975 | BD90: 8.628 | BE90: 241.409 | BF90: 237.73 | BG90: 0.714 | BH90: 0.499 | BI90: 0.65 | BJ90: 1.493 | BK90: 0.609 | BL90: 0.611 | BM90: 2.072 | BN90: 5.736 | BO90: 4.909 | BP90: 4.97 | BQ90: 95.8 | BR90: 0.988 | BS90: 113.7 | BT90: 123.8
A91: 41455 | B91: 214600 | C91: 259800 | D91: 0.0446 | E91: 0.0009 | F91: 0.0252 | G91: 0.01874046 | H91: 169.7 | I91: 69950 | J91: 1467000 | K91: 161000 | L91: 942000 | M91: 0.075 | N91: 0.0932 | O91: 0.11794391 | P91: 0.0749 | Q91: 0.0104 | R91: 0.0406 | S91: 0.0253 | T91: 0.082 | U91: 4150000 | V91: 0.142 | W91: 2622800 | X91: 190.4 | Y91: 101.4 | Z91: 241.8 | AA91: 289.1 | AB91: 141.7 | AC91: 0.137 | AD91: 3.458 | AE91: 1.859 | AF91: 1.439 | AG91: 3.525 | AH91: 187 | AI91: 146.6 | AJ91: 424.286 | AK91: 236.98 | AL91: 229.9 | AM91: 133.6 | AN91: 108.9 | AO91: 339 | AP91: 3.382 | AQ91: 5.588 | AR91: 146.384 | AS91: 642.074 | AT91: 113.5 | AU91: 148.742 | AV91: 114.9 | AW91: 267.451 | AX91: 1.038 | AY91: 197.503 | AZ91: 286.832 | BA91: 125.412 | BB91: 138.6 | BC91: 405.274 | BD91: 8.504 | BE91: 243.016 | BF91: 238.188 | BG91: 0.723 | BH91: 0.533 | BI91: 0.644 | BJ91: 1.47 | BK91: 0.603 | BL91: 0.646 | BM91: 1.424 | BN91: 5.493 | BO91: 5.334 | BP91: 4.507 | BQ91: 95.8 | BR91: 1.147 | BS91: 113.7 | BT91: 123.6
A92: 41547 | B92: 198500 | C92: 269800 | D92: 0.0432 | E92: 0.0008 | F92: 0.0264 | G92: 0.01888205 | H92: 166.6 | I92: 69950 | J92: 1478000 | K92: 183000 | L92: 1004000 | M92: 0.072 | N92: 0.0866 | O92: 0.11837713 | P92: 0.0678 | Q92: 0.0098 | R92: 0.0376 | S92: 0.0244 | T92: 0.083 | U92: 4128000 | V92: 0.135 | W92: 2639400 | X92: 191.8 | Y92: 101.9 | Z92: 244 | AA92: 289.1 | AB92: 142.4 | AC92: 0.137 | AD92: 3.428 | AE92: 1.897 | AF92: 1.419 | AG92: 3.608 | AH92: 189.4 | AI92: 147.4 | AJ92: 428.29 | AK92: 237.519 | AL92: 230.5 | AM92: 133.8 | AN92: 109.1 | AO92: 339 | AP92: 3.502 | AQ92: 5.091 | AR92: 145.379 | AS92: 647.333 | AT92: 113.5 | AU92: 150.458 | AV92: 115.7 | AW92: 269.315 | AX92: 1 | AY92: 198.742 | AZ92: 273.182 | BA92: 124.314 | BB92: 142.6 | BC92: 408.949 | BD92: 8.494 | BE92: 244.036 | BF92: 239.843 | BG92: 0.741 | BH92: 0.522 | BI92: 0.633 | BJ92: 1.566 | BK92: 0.601 | BL92: 0.746 | BM92: 1.559 | BN92: 5.433 | BO92: 5.68 | BP92: 4.528 | BQ92: 95.8 | BR92: 1.334 | BS92: 113.8 | BT92: 124.8
A93: 41639 | B93: 197700 | C93: 275500 | D93: 0.0448 | E93: 0.0009 | F93: 0.0304 | G93: 0.01872378 | H93: 169.9 | I93: 69950 | J93: 1597000 | K93: 186000 | L93: 1005000 | M93: 0.067 | N93: 0.0829 | O93: 0.11985283 | P93: 0.058 | Q93: 0.0089 | R93: 0.0358 | S93: 0.0238 | T93: 0.082 | U93: 4121000 | V93: 0.131 | W93: 2685200 | X93: 197.6 | Y93: 99 | Z93: 227.3 | AA93: 289.3 | AB93: 142.9 | AC93: 0.131 | AD93: 3.501 | AE93: 2.026 | AF93: 1.385 | AG93: 3.46 | AH93: 190 | AI93: 148.1 | AJ93: 428.622 | AK93: 238.182 | AL93: 231.2 | AM93: 133.9 | AN93: 109.1 | AO93: 339 | AP93: 3.46 | AQ93: 4.948 | AR93: 145.664 | AS93: 653.524 | AT93: 111.2 | AU93: 152.457 | AV93: 116.5 | AW93: 271.22 | AX93: 0.998 | AY93: 200.661 | AZ93: 273.161 | BA93: 123.409 | BB93: 132.5 | BC93: 411.525 | BD93: 8.441 | BE93: 245.3 | BF93: 240.709 | BG93: 0.735 | BH93: 0.513 | BI93: 0.592 | BJ93: 1.727 | BK93: 0.592 | BL93: 0.667 | BM93: 1.701 | BN93: 5.386 | BO93: 5.544 | BP93: 4.536 | BQ93: 95.6 | BR93: 1.129 | BS93: 113.8 | BT93: 124.7
A94: 41729 | B94: 196500 | C94: 282300 | D94: 0.044 | E94: 0.0008 | F94: 0.0273 | G94: 0.01821445 | H94: 173.3 | I94: 69060 | J94: 1532000 | K94: 190000 | L94: 1067000 | M94: 0.067 | N94: 0.0777 | O94: 0.11883752 | P94: 0.0536 | Q94: 0.009 | R94: 0.0333 | S94: 0.0232 | T94: 0.083 | U94: 4388000 | V94: 0.127 | W94: 2715100 | X94: 211.5 | Y94: 101 | Z94: 229.4 | AA94: 292.3 | AB94: 145.4 | AC94: 0.135 | AD94: 3.669 | AE94: 2.061 | AF94: 1.359 | AG94: 3.468 | AH94: 190.6 | AI94: 148.7 | AJ94: 432.211 | AK94: 240.447 | AL94: 232.8 | AM94: 135.3 | AN94: 107.5 | AO94: 339 | AP94: 3.698 | AQ94: 5.005 | AR94: 145.136 | AS94: 658.904 | AT94: 111.7 | AU94: 149.641 | AV94: 116 | AW94: 273.341 | AX94: 1.154 | AY94: 202.363 | AZ94: 273.384 | BA94: 123.505 | BB94: 144.8 | BC94: 413.578 | BD94: 8.381 | BE94: 246.878 | BF94: 241.07 | BG94: 0.733 | BH94: 0.551 | BI94: 0.604 | BJ94: 1.632 | BK94: 0.597 | BL94: 0.678 | BM94: 1.565 | BN94: 5.579 | BO94: 5.552 | BP94: 4.538 | BQ94: 95.6 | BR94: 1.212 | BS94: 113.8 | BT94: 126.3
A95: 41820 | B95: 223000 | C95: 287000 | D95: 0.0414 | E95: 0.001 | F95: 0.0253 | G95: 0.02142724 | H95: 156.6 | I95: 69060 | J95: 1435000 | K95: 199000 | L95: 1010000 | M95: 0.061 | N95: 0.0743 | O95: 0.1162113 | P95: 0.0491 | Q95: 0.008 | R95: 0.0303 | S95: 0.0226 | T95: 0.075 | U95: 4982000 | V95: 0.12 | W95: 2751200 | X95: 204.5 | Y95: 100.9 | Z95: 229.2 | AA95: 292.3 | AB95: 147 | AC95: 0.143 | AD95: 3.626 | AE95: 1.948 | AF95: 1.4 | AG95: 3.504 | AH95: 192.7 | AI95: 150.4 | AJ95: 435.187 | AK95: 242.646 | AL95: 232.8 | AM95: 136.2 | AN95: 107 | AO95: 341 | AP95: 3.88 | AQ95: 4.67 | AR95: 144.558 | AS95: 664.26 | AT95: 106.9 | AU95: 148.921 | AV95: 116.3 | AW95: 275.819 | AX95: 1.088 | AY95: 203.791 | AZ95: 296.981 | BA95: 123.534 | BB95: 141.3 | BC95: 416.64 | BD95: 8.37 | BE95: 248.445 | BF95: 241.78 | BG95: 0.742 | BH95: 0.532 | BI95: 0.61 | BJ95: 1.675 | BK95: 0.607 | BL95: 0.685 | BM95: 1.79 | BN95: 5.56 | BO95: 6.106 | BP95: 4.35 | BQ95: 95.6 | BR95: 1.299 | BS95: 113.8 | BT95: 126.3
A96: 41912 | B96: 209600 | C96: 261500 | D96: 0.042 | E96: 0.0009 | F96: 0.0252 | G96: 0.0195017 | H96: 168.4 | I96: 69060 | J96: 1380000 | K96: 210000 | L96: 1077000 | M96: 0.059 | N96: 0.0706 | O96: 0.11646935 | P96: 0.0442 | Q96: 0.0077 | R96: 0.0288 | S96: 0.022 | T96: 0.074 | U96: 4914000 | V96: 0.117 | W96: 2808000 | X96: 211.1 | Y96: 103.9 | Z96: 222.9 | AA96: 292.3 | AB96: 149.1 | AC96: 0.141 | AD96: 3.732 | AE96: 1.97 | AF96: 1.405 | AG96: 3.481 | AH96: 195.2 | AI96: 150.5 | AJ96: 437.091 | AK96: 244.48 | AL96: 232.9 | AM96: 136.5 | AN96: 108.1 | AO96: 345.3 | AP96: 4.096 | AQ96: 5.215 | AR96: 144.472 | AS96: 668.789 | AT96: 111.4 | AU96: 149.859 | AV96: 116.7 | AW96: 278.149 | AX96: 1.058 | AY96: 206.33 | AZ96: 267.142 | BA96: 122.58 | BB96: 139.9 | BC96: 417.538 | BD96: 8.327 | BE96: 250.57 | BF96: 242.191 | BG96: 0.746 | BH96: 0.513 | BI96: 0.608 | BJ96: 1.546 | BK96: 0.606 | BL96: 0.671 | BM96: 1.658 | BN96: 5.565 | BO96: 5.953 | BP96: 4.357 | BQ96: 95.6 | BR96: 1.486 | BS96: 113.8 | BT96: 128.2
A97: 42004 | B97: 209200 | C97: 301500 | D97: 0.0387 | E97: 0.0012 | F97: 0.0217 | G97: 0.01961226 | H97: 171.1 | I97: 69060 | J97: 1463000 | K97: 210000 | L97: 1072000 | M97: 0.056 | N97: 0.065 | O97: 0.11631979 | P97: 0.0401 | Q97: 0.0072 | R97: 0.0275 | S97: 0.0215 | T97: 0.07 | U97: 5130000 | V97: 0.112 | W97: 2833300 | X97: 200.3 | Y97: 104.7 | Z97: 232.5 | AA97: 292.3 | AB97: 150.4 | AC97: 0.135 | AD97: 3.82 | AE97: 2.21 | AF97: 1.466 | AG97: 3.482 | AH97: 195.5 | AI97: 152.7 | AJ97: 441.464 | AK97: 246.237 | AL97: 232.9 | AM97: 136.8 | AN97: 107.5 | AO97: 344.8 | AP97: 4.156 | AQ97: 4.59 | AR97: 144.693 | AS97: 674.253 | AT97: 114.6 | AU97: 145.83 | AV97: 117.7 | AW97: 280.383 | AX97: 1.06 | AY97: 209.853 | AZ97: 265.356 | BA97: 122.237 | BB97: 137.4 | BC97: 420.198 | BD97: 8.221 | BE97: 252.628 | BF97: 244.345 | BG97: 0.7 | BH97: 0.511 | BI97: 0.614 | BJ97: 2.189 | BK97: 0.585 | BL97: 0.636 | BM97: 1.826 | BN97: 5.438 | BO97: 5.531 | BP97: 4.27 | BQ97: 94.7 | BR97: 1.246 | BS97: 114 | BT97: 128.1
A98: 42094 | B98: 212100 | C98: 286600 | D98: 0.0369 | E98: 0.0011 | F98: 0.0194 | G98: 0.01989606 | H98: 175.2 | I98: 72790 | J98: 1424000 | K98: 204000 | L98: 1072000 | M98: 0.054 | N98: 0.0624 | O98: 0.11556607 | P98: 0.0356 | Q98: 0.0075 | R98: 0.0251 | S98: 0.0211 | T98: 0.071 | U98: 5210000 | V98: 0.109 | W98: 2842500 | X98: 195.7 | Y98: 100.6 | Z98: 226.8 | AA98: 292.3 | AB98: 152.5 | AC98: 0.136 | AD98: 3.463 | AE98: 2.133 | AF98: 1.44 | AG98: 3.522 | AH98: 196.3 | AI98: 152.6 | AJ98: 442.943 | AK98: 246.072 | AL98: 234.7 | AM98: 137.6 | AN98: 106.9 | AO98: 344.5 | AP98: 4.2 | AQ98: 4.827 | AR98: 144.504 | AS98: 681.693 | AT98: 115 | AU98: 147.694 | AV98: 116.7 | AW98: 283.056 | AX98: 0.985 | AY98: 211.468 | AZ98: 264.248 | BA98: 122.803 | BB98: 140.7 | BC98: 419.865 | BD98: 8.17 | BE98: 254.108 | BF98: 243.996 | BG98: 0.67 | BH98: 0.518 | BI98: 0.66 | BJ98: 1.819 | BK98: 0.593 | BL98: 0.639 | BM98: 2.007 | BN98: 5.384 | BO98: 5.367 | BP98: 4.4 | BQ98: 94.8 | BR98: 1.201 | BS98: 114 | BT98: 128.7
... A113: 43465 | B113: 277000 | C113: 329700 | D113: 0.0455 | E113: 0.0227 | F113: 0.0269 | G113: 0.02456173 | H113: 147.3 | I113: 77700 | J113: 1185880 | K113: 346000 | L113: 1317000 | M113: 0.039 | N113: 0.0283 | O113: 0.11666352 | P113: 0.01 | Q113: 0.0094 | R113: 0.0156 | S113: 0.0254 | T113: 0.066 | U113: 7489000 | V113: 0.076 | W113: 2979300 | X113: 210 | Y113: 102.5 | Z113: 254.2 | AA113: 315.4 | AB113: 170.1 | AC113: 0.135 | AD113: 2.853 | AE113: 1.595 | AF113: 1.29 | AG113: 3.112 | AH113: 207.5 | AI113: 181.8 | AJ113: 488.82 | AK113: 255.877 | AL113: 264.5 | AM113: 150.4 | AN113: 106.1 | AO113: 410.7 | AP113: 3.725 | AQ113: 4.306 | AR113: 145.105 | AS113: 752.155 | AT113: 111.2 | AU113: 140.18 | AV113: 134.9 | AW113: 324.408 | AX113: 1.085 | AY113: 242.436 | AZ113: 248.489 | BA113: 122.265 | BB113: 144.4 | BC113: 475.458 | BD113: 7.442 | BE113: 279.419 | BF113: 268.225 | BG113: 0.712 | BH113: 0.437 | BI113: 0.573 | BJ113: 2.175 | BK113: 0.577 | BL113: 0.718 | BM113: 2.352 | BN113: 5.36 | BO113: 5.502 | BP113: 4.447 | BQ113: 93.5 | BR113: 1.389 | BS113: 113.9 | BT113: 141.5
A114: 43555 | B114: 274400 | C114: 310600 | D114: 0.0406 | E114: 0.0241 | F114: 0.0241 | G114: 0.02356946 | H114: 157.2 | I114: 83260 | J114: 1115955 | K114: 337000 | L114: 1295000 | M114: 0.038 | N114: 0.0269 | O114: 0.11499875 | P114: 0.0093 | Q114: 0.0116 | R114: 0.0155 | S114: 0.0254 | T114: 0.07 | U114: 7317000 | V114: 0.074 | W114: 2935600 | X114: 216.3 | Y114: 96.6 | Z114: 242.5 | AA114: 322.3 | AB114: 171.5 | AC114: 0.135 | AD114: 2.944 | AE114: 1.544 | AF114: 1.261 | AG114: 3.048 | AH114: 208.3 | AI114: 181.7 | AJ114: 491.412 | AK114: 257.681 | AL114: 266.5 | AM114: 153.6 | AN114: 111.6 | AO114: 410.7 | AP114: 3.725 | AQ114: 4.053 | AR114: 145.823 | AS114: 759.001 | AT114: 112.1 | AU114: 141.218 | AV114: 134.3 | AW114: 327.539 | AX114: 1.048 | AY114: 242.397 | AZ114: 256.023 | BA114: 123.746 | BB114: 142 | BC114: 475.919 | BD114: 7.39 | BE114: 281.887 | BF114: 269.664 | BG114: 0.757 | BH114: 0.445 | BI114: 0.596 | BJ114: 2.079 | BK114: 0.581 | BL114: 0.755 | BM114: 2.356 | BN114: 5.193 | BO114: 5.608 | BP114: 4.587 | BQ114: 93.5 | BR114: 1.346 | BS114: 115.1 | BT114: 145.5 | BU114: =100 -> 100
...

Sheet COST_INDEX
B1: {=FRED_HISTORY!AC1:BT1} -> Power (per KWH) | C1: Milk | D1: Eggs | E1: Bread | F1: Chicken (boneless) | G1: Home Insurance | H1: Auto Insurance | I1: Medical Care | J1: Food Overall | K1: Doors & Windows | L1: HVAC System | M1: Fridge | N1: Water Heater | O1: Beef | P1: Coffee | Q1: Car Parts | R1: Childcare / Education | S1: Clothing | T1: Used Car | U1: Health Insurance (PPI) | V1: Rent | W1: Natural Gas | X1: Water/Sewer/Trash (CPI) | Y1: Public Transit Fares | Z1: Furniture | AA1: Cleaning Supplies | AB1: Cable / Streaming TV | AC1: Internet / IT | AD1: Food Away From Home | AE1: Personal Care | AF1: Rice per lb | AG1: White Flour per lb | AH1: White Sugar per lb | AI1: Tomatoes per lb | AJ1: Bananas per lb | AK1: Potatoes per lb | AL1: Lettuce per lb | AM1: Cheddar Cheese per lb | AN1: Bacon per lb | AO1: Potato Chips | AP1: Disposable Diapers | AQ1: Oranges per lb | AR1: Tissue Paper / Toilet Paper | AS1: Trash Collection (PPI)
B2: 3 | C2: 3 | D2: 3 | E2: 3 | F2: 3 | G2: 3 | H2: 3 | I2: 3 | J2: 3 | K2: 2 | L2: 1 | M2: 2 | N2: 1 | O2: 3 | P2: 3 | Q2: 2 | R2: 3 | S2: 2 | T2: 3 | U2: 3 | V2: 3 | W2: 3 | X2: 3 | Y2: 1 | Z2: 1 | AA2: 1 | AB2: 1 | AC2: 1 | AD2: 2 | AE2: 2 | AF2: 3 | AG2: 3 | AH2: 3 | AI2: 3 | AJ2: 3 | AK2: 3 | AL2: 3 | AM2: 3 | AN2: 3 | AO2: 2 | AP2: 2 | AQ2: 3 | AR2: 3 | AS2: 2
A3: Baseline 3/19 | B3: {=INDEX(FRED_HISTORY_QUARTERLY!$AC:$BT, $A$4, 0)} -> 0.135 | C3: 2.944 | D3: 1.544 | E3: 1.261 | F3: 3.048 | G3: 208.3 | H3: 181.7 | I3: 491.412 | J3: 257.681 | K3: 266.5 | L3: 153.6 | M3: 111.6 | N3: 410.7 | O3: 3.725 | P3: 4.053 | Q3: 145.823 | R3: 759.001 | S3: 112.1 | T3: 141.218 | U3: 134.3 | V3: 327.539 | W3: 1.048 | X3: 242.397 | Y3: 256.023 | Z3: 123.746 | AA3: 142 | AB3: 475.919 | AC3: 7.39 | AD3: 281.887 | AE3: 269.664 | AF3: 0.757 | AG3: 0.445 | AH3: 0.596 | AI3: 2.079 | AJ3: 0.581 | AK3: 0.755 | AL3: 2.356 | AM3: 5.193 | AN3: 5.608 | AO3: 4.587 | AP3: 93.5 | AQ3: 1.346 | AR3: 115.1 | AS3: 145.5
A4: =MATCH(DATE(2019,3,31), FRED_HISTORY_QUARTERLY!$A:$A, 0) -> 114
A6: Date | C6: Cost Index | E6: quarter date | G6: cost index quarterly
A7: =IFERROR(__xludf.DUMMYFUNCTION("FILTER(FRED_HISTORY!$A$2:$A1000, YEAR(FRED_HISTORY!$A$2:$A1000)>=2024)"),45688.0) -> 45688 | C7: {=IF($A7="","", 100 * SUMPRODUCT( INDEX(FRED_HISTORY!$AC:$BT, MATCH($A7, FRED_HISTORY!$A:$A, 0), 0) / $B$3:$AS$3, $B$2:$AS$2 ) / SUM($B$2:$AS$2) )} -> 134.76881 | E7: =IFERROR(__xludf.DUMMYFUNCTION("FILTER(FRED_HISTORY_QUARTERLY!$A$114:$A1000, FRED_HISTORY_QUARTERLY!$A$114:$A1000<>"""")"),43555.0) -> 43555 | G7: {=IF($E7="","", 100 * SUMPRODUCT( INDEX(FRED_HISTORY_QUARTERLY!$AC:$BT, MATCH($E7, FRED_HISTORY_QUARTERLY!$A:$A, 0), 0) / $B$3:$AS$3, $B$2:$AS$2 ) / SUM($B$2:$AS$2) )} -> 100
A8: =IFERROR(__xludf.DUMMYFUNCTION("""COMPUTED_VALUE"""),45716.0) -> 45716 | C8: {=IF($A8="","", 100 * SUMPRODUCT( INDEX(FRED_HISTORY!$AC:$BT, MATCH($A8, FRED_HISTORY!$A:$A, 0), 0) / $B$3:$AS$3, $B$2:$AS$2 ) / SUM($B$2:$AS$2) )} -> 136.62388 | E8: =IFERROR(__xludf.DUMMYFUNCTION("""COMPUTED_VALUE"""),43646.0) -> 43646 | G8: {=IF($E8="","", 100 * SUMPRODUCT( INDEX(FRED_HISTORY_QUARTERLY!$AC:$BT, MATCH($E8, FRED_HISTORY_QUARTERLY!$A:$A, 0), 0) / $B$3:$AS$3, $B$2:$AS$2 ) / SUM($B$2:$AS$2) )} -> 99.325027
A9: =IFERROR(__xludf.DUMMYFUNCTION("""COMPUTED_VALUE"""),45747.0) -> 45747 | C9: {=IF($A9="","", 100 * SUMPRODUCT( INDEX(FRED_HISTORY!$AC:$BT, MATCH($A9, FRED_HISTORY!$A:$A, 0), 0) / $B$3:$AS$3, $B$2:$AS$2 ) / SUM($B$2:$AS$2) )} -> 137.9882 | E9: =IFERROR(__xludf.DUMMYFUNCTION("""COMPUTED_VALUE"""),43738.0) -> 43738 | G9: {=IF($E9="","", 100 * SUMPRODUCT( INDEX(FRED_HISTORY_QUARTERLY!$AC:$BT, MATCH($E9, FRED_HISTORY_QUARTERLY!$A:$A, 0), 0) / $B$3:$AS$3, $B$2:$AS$2 ) / SUM($B$2:$AS$2) )} -> 100.38415
A10: =IFERROR(__xludf.DUMMYFUNCTION("""COMPUTED_VALUE"""),45777.0) -> 45777 | C10: {=IF($A10="","", 100 * SUMPRODUCT( INDEX(FRED_HISTORY!$AC:$BT, MATCH($A10, FRED_HISTORY!$A:$A, 0), 0) / $B$3:$AS$3, $B$2:$AS$2 ) / SUM($B$2:$AS$2) )} -> 136.50129 | E10: =IFERROR(__xludf.DUMMYFUNCTION("""COMPUTED_VALUE"""),43830.0) -> 43830 | G10: {=IF($E10="","", 100 * SUMPRODUCT( INDEX(FRED_HISTORY_QUARTERLY!$AC:$BT, MATCH($E10, FRED_HISTORY_QUARTERLY!$A:$A, 0), 0) / $B$3:$AS$3, $B$2:$AS$2 ) / SUM($B$2:$AS$2) )} -> 100.54797
A11: =IFERROR(__xludf.DUMMYFUNCTION("""COMPUTED_VALUE"""),45808.0) -> 45808 | C11: {=IF($A11="","", 100 * SUMPRODUCT( INDEX(FRED_HISTORY!$AC:$BT, MATCH($A11, FRED_HISTORY!$A:$A, 0), 0) / $B$3:$AS$3, $B$2:$AS$2 ) / SUM($B$2:$AS$2) )} -> 136.74338 | E11: =IFERROR(__xludf.DUMMYFUNCTION("""COMPUTED_VALUE"""),43921.0) -> 43921 | G11: {=IF($E11="","", 100 * SUMPRODUCT( INDEX(FRED_HISTORY_QUARTERLY!$AC:$BT, MATCH($E11, FRED_HISTORY_QUARTERLY!$A:$A, 0), 0) / $B$3:$AS$3, $B$2:$AS$2 ) / SUM($B$2:$AS$2) )} -> 100.88816
A12: =IFERROR(__xludf.DUMMYFUNCTION("""COMPUTED_VALUE"""),45838.0) -> 45838 | C12: {=IF($A12="","", 100 * SUMPRODUCT( INDEX(FRED_HISTORY!$AC:$BT, MATCH($A12, FRED_HISTORY!$A:$A, 0), 0) / $B$3:$AS$3, $B$2:$AS$2 ) / SUM($B$2:$AS$2) )} -> 136.48325 | E12: =IFERROR(__xludf.DUMMYFUNCTION("""COMPUTED_VALUE"""),44012.0) -> 44012 | G12: {=IF($E12="","", 100 * SUMPRODUCT( INDEX(FRED_HISTORY_QUARTERLY!$AC:$BT, MATCH($E12, FRED_HISTORY_QUARTERLY!$A:$A, 0), 0) / $B$3:$AS$3, $B$2:$AS$2 ) / SUM($B$2:$AS$2) )} -> 103.4244
A13: =IFERROR(__xludf.DUMMYFUNCTION("""COMPUTED_VALUE"""),45869.0) -> 45869 | C13: {=IF($A13="","", 100 * SUMPRODUCT( INDEX(FRED_HISTORY!$AC:$BT, MATCH($A13, FRED_HISTORY!$A:$A, 0), 0) / $B$3:$AS$3, $B$2:$AS$2 ) / SUM($B$2:$AS$2) )} -> 136.9445 | E13: =IFERROR(__xludf.DUMMYFUNCTION("""COMPUTED_VALUE"""),44104.0) -> 44104 | G13: {=IF($E13="","", 100 * SUMPRODUCT( INDEX(FRED_HISTORY_QUARTERLY!$AC:$BT, MATCH($E13, FRED_HISTORY_QUARTERLY!$A:$A, 0), 0) / $B$3:$AS$3, $B$2:$AS$2 ) / SUM($B$2:$AS$2) )} -> 102.97302
A14: =IFERROR(__xludf.DUMMYFUNCTION("""COMPUTED_VALUE"""),45900.0) -> 45900 | C14: {=IF($A14="","", 100 * SUMPRODUCT( INDEX(FRED_HISTORY!$AC:$BT, MATCH($A14, FRED_HISTORY!$A:$A, 0), 0) / $B$3:$AS$3, $B$2:$AS$2 ) / SUM($B$2:$AS$2) )} -> 137.97614 | E14: =IFERROR(__xludf.DUMMYFUNCTION("""COMPUTED_VALUE"""),44196.0) -> 44196 | G14: {=IF($E14="","", 100 * SUMPRODUCT( INDEX(FRED_HISTORY_QUARTERLY!$AC:$BT, MATCH($E14, FRED_HISTORY_QUARTERLY!$A:$A, 0), 0) / $B$3:$AS$3, $B$2:$AS$2 ) / SUM($B$2:$AS$2) )} -> 103.77718
A15: =IFERROR(__xludf.DUMMYFUNCTION("""COMPUTED_VALUE"""),45930.0) -> 45930 | C15: {=IF($A15="","", 100 * SUMPRODUCT( INDEX(FRED_HISTORY!$AC:$BT, MATCH($A15, FRED_HISTORY!$A:$A, 0), 0) / $B$3:$AS$3, $B$2:$AS$2 ) / SUM($B$2:$AS$2) )} -> 138.19723 | E15: =IFERROR(__xludf.DUMMYFUNCTION("""COMPUTED_VALUE"""),44286.0) -> 44286 | G15: {=IF($E15="","", 100 * SUMPRODUCT( INDEX(FRED_HISTORY_QUARTERLY!$AC:$BT, MATCH($E15, FRED_HISTORY_QUARTERLY!$A:$A, 0), 0) / $B$3:$AS$3, $B$2:$AS$2 ) / SUM($B$2:$AS$2) )} -> 104.43205
A16: =IFERROR(__xludf.DUMMYFUNCTION("""COMPUTED_VALUE"""),45961.0) -> 45961 | C16: {=IF($A16="","", 100 * SUMPRODUCT( INDEX(FRED_HISTORY!$AC:$BT, MATCH($A16, FRED_HISTORY!$A:$A, 0), 0) / $B$3:$AS$3, $B$2:$AS$2 ) / SUM($B$2:$AS$2) )} -> 0 | E16: =IFERROR(__xludf.DUMMYFUNCTION("""COMPUTED_VALUE"""),44377.0) -> 44377 | G16: {=IF($E16="","", 100 * SUMPRODUCT( INDEX(FRED_HISTORY_QUARTERLY!$AC:$BT, MATCH($E16, FRED_HISTORY_QUARTERLY!$A:$A, 0), 0) / $B$3:$AS$3, $B$2:$AS$2 ) / SUM($B$2:$AS$2) )} -> 107.96611
E17: =IFERROR(__xludf.DUMMYFUNCTION("""COMPUTED_VALUE"""),44469.0) -> 44469 | G17: {=IF($E17="","", 100 * SUMPRODUCT( INDEX(FRED_HISTORY_QUARTERLY!$AC:$BT, MATCH($E17, FRED_HISTORY_QUARTERLY!$A:$A, 0), 0) / $B$3:$AS$3, $B$2:$AS$2 ) / SUM($B$2:$AS$2) )} -> 110.90891
E18: =IFERROR(__xludf.DUMMYFUNCTION("""COMPUTED_VALUE"""),44561.0) -> 44561 | G18: {=IF($E18="","", 100 * SUMPRODUCT( INDEX(FRED_HISTORY_QUARTERLY!$AC:$BT, MATCH($E18, FRED_HISTORY_QUARTERLY!$A:$A, 0), 0) / $B$3:$AS$3, $B$2:$AS$2 ) / SUM($B$2:$AS$2) )} -> 113.19556
E19: =IFERROR(__xludf.DUMMYFUNCTION("""COMPUTED_VALUE"""),44651.0) -> 44651 | G19: {=IF($E19="","", 100 * SUMPRODUCT( INDEX(FRED_HISTORY_QUARTERLY!$AC:$BT, MATCH($E19, FRED_HISTORY_QUARTERLY!$A:$A, 0), 0) / $B$3:$AS$3, $B$2:$AS$2 ) / SUM($B$2:$AS$2) )} -> 116.71858
E20: =IFERROR(__xludf.DUMMYFUNCTION("""COMPUTED_VALUE"""),44742.0) -> 44742 | G20: {=IF($E20="","", 100 * SUMPRODUCT( INDEX(FRED_HISTORY_QUARTERLY!$AC:$BT, MATCH($E20, FRED_HISTORY_QUARTERLY!$A:$A, 0), 0) / $B$3:$AS$3, $B$2:$AS$2 ) / SUM($B$2:$AS$2) )} -> 122.80633
E21: =IFERROR(__xludf.DUMMYFUNCTION("""COMPUTED_VALUE"""),44834.0) -> 44834 | G21: {=IF($E21="","", 100 * SUMPRODUCT( INDEX(FRED_HISTORY_QUARTERLY!$AC:$BT, MATCH($E21, FRED_HISTORY_QUARTERLY!$A:$A, 0), 0) / $B$3:$AS$3, $B$2:$AS$2 ) / SUM($B$2:$AS$2) )} -> 126.44162
E22: =IFERROR(__xludf.DUMMYFUNCTION("""COMPUTED_VALUE"""),44926.0) -> 44926 | G22: {=IF($E22="","", 100 * SUMPRODUCT( INDEX(FRED_HISTORY_QUARTERLY!$AC:$BT, MATCH($E22, FRED_HISTORY_QUARTERLY!$A:$A, 0), 0) / $B$3:$AS$3, $B$2:$AS$2 ) / SUM($B$2:$AS$2) )} -> 129.0522
E23: =IFERROR(__xludf.DUMMYFUNCTION("""COMPUTED_VALUE"""),45016.0) -> 45016 | G23: {=IF($E23="","", 100 * SUMPRODUCT( INDEX(FRED_HISTORY_QUARTERLY!$AC:$BT, MATCH($E23, FRED_HISTORY_QUARTERLY!$A:$A, 0), 0) / $B$3:$AS$3, $B$2:$AS$2 ) / SUM($B$2:$AS$2) )} -> 126.79537
E24: =IFERROR(__xludf.DUMMYFUNCTION("""COMPUTED_VALUE"""),45107.0) -> 45107 | G24: {=IF($E24="","", 100 * SUMPRODUCT( INDEX(FRED_HISTORY_QUARTERLY!$AC:$BT, MATCH($E24, FRED_HISTORY_QUARTERLY!$A:$A, 0), 0) / $B$3:$AS$3, $B$2:$AS$2 ) / SUM($B$2:$AS$2) )} -> 124.93679
E25: =IFERROR(__xludf.DUMMYFUNCTION("""COMPUTED_VALUE"""),45199.0) -> 45199 | G25: {=IF($E25="","", 100 * SUMPRODUCT( INDEX(FRED_HISTORY_QUARTERLY!$AC:$BT, MATCH($E25, FRED_HISTORY_QUARTERLY!$A:$A, 0), 0) / $B$3:$AS$3, $B$2:$AS$2 ) / SUM($B$2:$AS$2) )} -> 126.03474
E26: =IFERROR(__xludf.DUMMYFUNCTION("""COMPUTED_VALUE"""),45291.0) -> 45291 | G26: {=IF($E26="","", 100 * SUMPRODUCT( INDEX(FRED_HISTORY_QUARTERLY!$AC:$BT, MATCH($E26, FRED_HISTORY_QUARTERLY!$A:$A, 0), 0) / $B$3:$AS$3, $B$2:$AS$2 ) / SUM($B$2:$AS$2) )} -> 126.45759
E27: =IFERROR(__xludf.DUMMYFUNCTION("""COMPUTED_VALUE"""),45382.0) -> 45382 | G27: {=IF($E27="","", 100 * SUMPRODUCT( INDEX(FRED_HISTORY_QUARTERLY!$AC:$BT, MATCH($E27, FRED_HISTORY_QUARTERLY!$A:$A, 0), 0) / $B$3:$AS$3, $B$2:$AS$2 ) / SUM($B$2:$AS$2) )} -> 127.91453
E28: =IFERROR(__xludf.DUMMYFUNCTION("""COMPUTED_VALUE"""),45473.0) -> 45473 | G28: {=IF($E28="","", 100 * SUMPRODUCT( INDEX(FRED_HISTORY_QUARTERLY!$AC:$BT, MATCH($E28, FRED_HISTORY_QUARTERLY!$A:$A, 0), 0) / $B$3:$AS$3, $B$2:$AS$2 ) / SUM($B$2:$AS$2) )} -> 128.54315
E29: =IFERROR(__xludf.DUMMYFUNCTION("""COMPUTED_VALUE"""),45565.0) -> 45565 | G29: {=IF($E29="","", 100 * SUMPRODUCT( INDEX(FRED_HISTORY_QUARTERLY!$AC:$BT, MATCH($E29, FRED_HISTORY_QUARTERLY!$A:$A, 0), 0) / $B$3:$AS$3, $B$2:$AS$2 ) / SUM($B$2:$AS$2) )} -> 132.0287
E30: =IFERROR(__xludf.DUMMYFUNCTION("""COMPUTED_VALUE"""),45657.0) -> 45657 | G30: {=IF($E30="","", 100 * SUMPRODUCT( INDEX(FRED_HISTORY_QUARTERLY!$AC:$BT, MATCH($E30, FRED_HISTORY_QUARTERLY!$A:$A, 0), 0) / $B$3:$AS$3, $B$2:$AS$2 ) / SUM($B$2:$AS$2) )} -> 132.74649

Sheet INVEST_HISTORY
A1: date | B1: Gold | C1: Silver | D1: Platinum | E1: S&P 500 | F1: Dow J | G1: BTC | H1: ETH | I1: XRP | J1: 1 yr | K1: 2 yr | L1: 5 yr | M1: 10 yr | N1: 20 yr | O1: 30 yr | P1: DXY
A2: {=EOMONTH( DATE(2025,1,1), SEQUENCE( DATEDIF(DATE(2025,1,1), TODAY(), "M") + 1, 1, 0, 1 ) )} -> 45688 | B2: =IFERROR(__xludf.DUMMYFUNCTION("ARRAYFORMULA( IF( $A$2:$A1000="""", """", VLOOKUP( $A$2:$A1000, GOOGLEFINANCE(""GLD"", ""price"", DATE(2025,1,1), TODAY()), 2, TRUE ) ) ) "),258.05) -> 258.05 | C2: =IFERROR(__xludf.DUMMYFUNCTION("ARRAYFORMULA( IF( $A$2:$A1000="""", """", VLOOKUP( $A$2:$A1000, GOOGLEFINANCE(""SLV"", ""price"", DATE(2025,1,1), TODAY()), 2, TRUE ) ) ) "),28.72) -> 28.72 | D2: =IFERROR(__xludf.DUMMYFUNCTION("ARRAYFORMULA( IF($A$2:$A1000="""","""", VLOOKUP( $A$2:$A1000, GOOGLEFINANCE(""PPLT"",""price"",DATE(2025,1,1),TODAY()), 2, TRUE ) ) ) "),88.76) -> 88.76 | E2: =IFERROR(__xludf.DUMMYFUNCTION("ARRAYFORMULA( IF( $A$2:$A1000="""", """", VLOOKUP( $A$2:$A1000, GOOGLEFINANCE("".INX"", ""price"", DATE(2025,1,1), TODAY()), 2, TRUE ) ) ) "),6071.17) -> 6071.17 | F2: =IFERROR(__xludf.DUMMYFUNCTION("ARRAYFORMULA( IF($A$2:$A1000="""","""", VLOOKUP( $A$2:$A1000, GOOGLEFINANCE(""DIA"",""price"",DATE(2025,1,1),TODAY()), 2, TRUE ) ) ) "),448.82) -> 448.82 | G2: =IFERROR(__xludf.DUMMYFUNCTION("ARRAYFORMULA( IF($A$2:$A1000="""","""", VLOOKUP( $A$2:$A1000, GOOGLEFINANCE(""CURRENCY:BTCUSD"",""price"",DATE(2025,1,1),TODAY()), 2, TRUE ) ) ) "),105403.1) -> 105403.1 | H2: =IFERROR(__xludf.DUMMYFUNCTION("ARRAYFORMULA( IF($A$2:$A1000="""","""", VLOOKUP( $A$2:$A1000, GOOGLEFINANCE(""CURRENCY:ETHUSD"",""price"",DATE(2025,1,1),TODAY()), 2, TRUE ) ) ) "),3114.3033) -> 3114.3033 | I2: =IFERROR(__xludf.DUMMYFUNCTION("ARRAYFORMULA( IF($A$2:$A1000="""","""", VLOOKUP( $A$2:$A1000, GOOGLEFINANCE(""CURRENCY:XRPUSD"",""price"",DATE(2025,1,1),TODAY()), 2, TRUE ) ) ) "),3.0687) -> 3.0687 | J2: 0.0417 | K2: 0.0422 | L2: 0.0436 | M2: 0.0458 | N2: 0.0488 | O2: 0.0483 | P2: =IFERROR(__xludf.DUMMYFUNCTION("IF($A2="""","""", INDEX( GOOGLEFINANCE(""NYICDX"",""price"",$A2-5,$A2), ROWS(GOOGLEFINANCE(""NYICDX"",""price"",$A2-5,$A2)), 2 ) ) "),108.5) -> 108.5
A3: 45716 | B3: =IFERROR(__xludf.DUMMYFUNCTION("""COMPUTED_VALUE"""),264.93) -> 264.93 | C3: =IFERROR(__xludf.DUMMYFUNCTION("""COMPUTED_VALUE"""),28.4) -> 28.4 | D3: =IFERROR(__xludf.DUMMYFUNCTION("""COMPUTED_VALUE"""),86.78) -> 86.78 | E3: =IFERROR(__xludf.DUMMYFUNCTION("""COMPUTED_VALUE"""),5861.57) -> 5861.57 | F3: =IFERROR(__xludf.DUMMYFUNCTION("""COMPUTED_VALUE"""),432.35) -> 432.35 | G3: =IFERROR(__xludf.DUMMYFUNCTION("""COMPUTED_VALUE"""),85090.99) -> 85090.99 | H3: =IFERROR(__xludf.DUMMYFUNCTION("""COMPUTED_VALUE"""),2332.5324) -> 2332.5324 | I3: =IFERROR(__xludf.DUMMYFUNCTION("""COMPUTED_VALUE"""),2.1926) -> 2.1926 | J3: 0.0408 | K3: 0.0399 | L3: 0.0403 | M3: 0.0424 | N3: 0.0455 | O3: 0.0451 | P3: =IFERROR(__xludf.DUMMYFUNCTION("IF($A3="""","""", INDEX( GOOGLEFINANCE(""NYICDX"",""price"",$A3-5,$A3), ROWS(GOOGLEFINANCE(""NYICDX"",""price"",$A3-5,$A3)), 2 ) ) "),107.56) -> 107.56
A4: 45747 | B4: =IFERROR(__xludf.DUMMYFUNCTION("""COMPUTED_VALUE"""),284.06) -> 284.06 | C4: =IFERROR(__xludf.DUMMYFUNCTION("""COMPUTED_VALUE"""),31.0) -> 31 | D4: =IFERROR(__xludf.DUMMYFUNCTION("""COMPUTED_VALUE"""),89.96) -> 89.96 | E4: =IFERROR(__xludf.DUMMYFUNCTION("""COMPUTED_VALUE"""),5580.94) -> 5580.94 | F4: =IFERROR(__xludf.DUMMYFUNCTION("""COMPUTED_VALUE"""),415.62) -> 415.62 | G4: =IFERROR(__xludf.DUMMYFUNCTION("""COMPUTED_VALUE"""),83184.34) -> 83184.34 | H4: =IFERROR(__xludf.DUMMYFUNCTION("""COMPUTED_VALUE"""),1827.4434) -> 1827.4434 | I4: =IFERROR(__xludf.DUMMYFUNCTION("""COMPUTED_VALUE"""),2.1387) -> 2.1387 | J4: 0.0403 | K4: 0.0389 | L4: 0.0396 | M4: 0.0423 | N4: 0.0462 | O4: 0.0459 | P4: =IFERROR(__xludf.DUMMYFUNCTION("IF($A4="""","""", INDEX( GOOGLEFINANCE(""NYICDX"",""price"",$A4-5,$A4), ROWS(GOOGLEFINANCE(""NYICDX"",""price"",$A4-5,$A4)), 2 ) ) "),104.18) -> 104.18
A5: 45777 | B5: =IFERROR(__xludf.DUMMYFUNCTION("""COMPUTED_VALUE"""),306.06) -> 306.06 | C5: =IFERROR(__xludf.DUMMYFUNCTION("""COMPUTED_VALUE"""),29.83) -> 29.83 | D5: =IFERROR(__xludf.DUMMYFUNCTION("""COMPUTED_VALUE"""),89.57) -> 89.57 | E5: =IFERROR(__xludf.DUMMYFUNCTION("""COMPUTED_VALUE"""),5560.83) -> 5560.83 | F5: =IFERROR(__xludf.DUMMYFUNCTION("""COMPUTED_VALUE"""),405.21) -> 405.21 | G5: =IFERROR(__xludf.DUMMYFUNCTION("""COMPUTED_VALUE"""),94717.11) -> 94717.11 | H5: =IFERROR(__xludf.DUMMYFUNCTION("""COMPUTED_VALUE"""),1800.1999) -> 1800.1999 | I5: =IFERROR(__xludf.DUMMYFUNCTION("""COMPUTED_VALUE"""),2.2952) -> 2.2952 | J5: 0.0385 | K5: 0.036 | L5: 0.0372 | M5: 0.0417 | N5: 0.0468 | O5: 0.0466 | P5: =IFERROR(__xludf.DUMMYFUNCTION("IF($A5="""","""", INDEX( GOOGLEFINANCE(""NYICDX"",""price"",$A5-5,$A5), ROWS(GOOGLEFINANCE(""NYICDX"",""price"",$A5-5,$A5)), 2 ) ) "),99.69) -> 99.69
A6: 45808 | B6: =IFERROR(__xludf.DUMMYFUNCTION("""COMPUTED_VALUE"""),303.6) -> 303.6 | C6: =IFERROR(__xludf.DUMMYFUNCTION("""COMPUTED_VALUE"""),30.0) -> 30 | D6: =IFERROR(__xludf.DUMMYFUNCTION("""COMPUTED_VALUE"""),96.75) -> 96.75 | E6: =IFERROR(__xludf.DUMMYFUNCTION("""COMPUTED_VALUE"""),5911.69) -> 5911.69 | F6: =IFERROR(__xludf.DUMMYFUNCTION("""COMPUTED_VALUE"""),422.85) -> 422.85 | G6: =IFERROR(__xludf.DUMMYFUNCTION("""COMPUTED_VALUE"""),106021.6) -> 106021.6 | H6: =IFERROR(__xludf.DUMMYFUNCTION("""COMPUTED_VALUE"""),2631.6787) -> 2631.6787 | I6: =IFERROR(__xludf.DUMMYFUNCTION("""COMPUTED_VALUE"""),2.2442) -> 2.2442 | J6: 0.0411 | K6: 0.0389 | L6: 0.0396 | M6: 0.0441 | N6: 0.0493 | O6: 0.0492 | P6: =IFERROR(__xludf.DUMMYFUNCTION("IF($A6="""","""", INDEX( GOOGLEFINANCE(""NYICDX"",""price"",$A6-5,$A6), ROWS(GOOGLEFINANCE(""NYICDX"",""price"",$A6-5,$A6)), 2 ) ) "),99.44) -> 99.44
A7: 45838 | B7: =IFERROR(__xludf.DUMMYFUNCTION("""COMPUTED_VALUE"""),301.22) -> 301.22 | C7: =IFERROR(__xludf.DUMMYFUNCTION("""COMPUTED_VALUE"""),32.62) -> 32.62 | D7: =IFERROR(__xludf.DUMMYFUNCTION("""COMPUTED_VALUE"""),122.01) -> 122.01 | E7: =IFERROR(__xludf.DUMMYFUNCTION("""COMPUTED_VALUE"""),6173.07) -> 6173.07 | F7: =IFERROR(__xludf.DUMMYFUNCTION("""COMPUTED_VALUE"""),438.0) -> 438 | G7: =IFERROR(__xludf.DUMMYFUNCTION("""COMPUTED_VALUE"""),107249.3) -> 107249.3 | H7: =IFERROR(__xludf.DUMMYFUNCTION("""COMPUTED_VALUE"""),2436.9814) -> 2436.9814 | I7: =IFERROR(__xludf.DUMMYFUNCTION("""COMPUTED_VALUE"""),2.186) -> 2.186 | J7: 0.0396 | K7: 0.0372 | L7: 0.0379 | M7: 0.0424 | N7: 0.0479 | O7: 0.0478 | P7: =IFERROR(__xludf.DUMMYFUNCTION("IF($A7="""","""", INDEX( GOOGLEFINANCE(""NYICDX"",""price"",$A7-5,$A7), ROWS(GOOGLEFINANCE(""NYICDX"",""price"",$A7-5,$A7)), 2 ) ) "),96.77) -> 96.77
A8: 45869 | B8: =IFERROR(__xludf.DUMMYFUNCTION("""COMPUTED_VALUE"""),300.96) -> 300.96 | C8: =IFERROR(__xludf.DUMMYFUNCTION("""COMPUTED_VALUE"""),33.51) -> 33.51 | D8: =IFERROR(__xludf.DUMMYFUNCTION("""COMPUTED_VALUE"""),118.76) -> 118.76 | E8: =IFERROR(__xludf.DUMMYFUNCTION("""COMPUTED_VALUE"""),6362.9) -> 6362.9 | F8: =IFERROR(__xludf.DUMMYFUNCTION("""COMPUTED_VALUE"""),444.76) -> 444.76 | G8: =IFERROR(__xludf.DUMMYFUNCTION("""COMPUTED_VALUE"""),118176.2) -> 118176.2 | H8: =IFERROR(__xludf.DUMMYFUNCTION("""COMPUTED_VALUE"""),3793.1021) -> 3793.1021 | I8: =IFERROR(__xludf.DUMMYFUNCTION("""COMPUTED_VALUE"""),3.1283) -> 3.1283 | J8: 0.041 | K8: 0.0394 | L8: 0.0396 | M8: 0.0437 | N8: 0.0489 | O8: 0.0489 | P8: =IFERROR(__xludf.DUMMYFUNCTION("IF($A8="""","""", INDEX( GOOGLEFINANCE(""NYICDX"",""price"",$A8-5,$A8), ROWS(GOOGLEFINANCE(""NYICDX"",""price"",$A8-5,$A8)), 2 ) ) "),100.04) -> 100.04
A9: 45900 | B9: =IFERROR(__xludf.DUMMYFUNCTION("""COMPUTED_VALUE"""),318.07) -> 318.07 | C9: =IFERROR(__xludf.DUMMYFUNCTION("""COMPUTED_VALUE"""),36.19) -> 36.19 | D9: =IFERROR(__xludf.DUMMYFUNCTION("""COMPUTED_VALUE"""),125.22) -> 125.22 | E9: =IFERROR(__xludf.DUMMYFUNCTION("""COMPUTED_VALUE"""),6460.26) -> 6460.26 | F9: =IFERROR(__xludf.DUMMYFUNCTION("""COMPUTED_VALUE"""),456.09) -> 456.09 | G9: =IFERROR(__xludf.DUMMYFUNCTION("""COMPUTED_VALUE"""),108454.4) -> 108454.4 | H9: =IFERROR(__xludf.DUMMYFUNCTION("""COMPUTED_VALUE"""),4359.9902) -> 4359.9902 | I9: =IFERROR(__xludf.DUMMYFUNCTION("""COMPUTED_VALUE"""),2.8217) -> 2.8217 | J9: 0.0383 | K9: 0.0359 | L9: 0.0368 | M9: 0.0423 | N9: 0.0486 | O9: 0.0492 | P9: =IFERROR(__xludf.DUMMYFUNCTION("IF($A9="""","""", INDEX( GOOGLEFINANCE(""NYICDX"",""price"",$A9-5,$A9), ROWS(GOOGLEFINANCE(""NYICDX"",""price"",$A9-5,$A9)), 2 ) ) "),97.85) -> 97.85
A10: 45930 | B10: =IFERROR(__xludf.DUMMYFUNCTION("""COMPUTED_VALUE"""),352.46) -> 352.46 | C10: =IFERROR(__xludf.DUMMYFUNCTION("""COMPUTED_VALUE"""),42.5) -> 42.5 | D10: =IFERROR(__xludf.DUMMYFUNCTION("""COMPUTED_VALUE"""),145.77) -> 145.77 | E10: =IFERROR(__xludf.DUMMYFUNCTION("""COMPUTED_VALUE"""),6661.21) -> 6661.21 | F10: =IFERROR(__xludf.DUMMYFUNCTION("""COMPUTED_VALUE"""),463.04) -> 463.04 | G10: =IFERROR(__xludf.DUMMYFUNCTION("""COMPUTED_VALUE"""),111908.8) -> 111908.8 | H10: =IFERROR(__xludf.DUMMYFUNCTION("""COMPUTED_VALUE"""),4144.5016) -> 4144.5016 | I10: =IFERROR(__xludf.DUMMYFUNCTION("""COMPUTED_VALUE"""),2.8669) -> 2.8669 | J10: 0.0368 | K10: 0.036 | L10: 0.0374 | M10: 0.0416 | N10: 0.0471 | O10: 0.0473 | P10: =IFERROR(__xludf.DUMMYFUNCTION("IF($A10="""","""", INDEX( GOOGLEFINANCE(""NYICDX"",""price"",$A10-5,$A10), ROWS(GOOGLEFINANCE(""NYICDX"",""price"",$A10-5,$A10)), 2 ) ) "),97.78) -> 97.78
A11: 45961 | B11: =IFERROR(__xludf.DUMMYFUNCTION("""COMPUTED_VALUE"""),370.13) -> 370.13 | C11: =IFERROR(__xludf.DUMMYFUNCTION("""COMPUTED_VALUE"""),44.34) -> 44.34 | D11: =IFERROR(__xludf.DUMMYFUNCTION("""COMPUTED_VALUE"""),146.86) -> 146.86 | E11: =IFERROR(__xludf.DUMMYFUNCTION("""COMPUTED_VALUE"""),6822.34) -> 6822.34 | F11: =IFERROR(__xludf.DUMMYFUNCTION("""COMPUTED_VALUE"""),475.01) -> 475.01 | G11: =IFERROR(__xludf.DUMMYFUNCTION("""COMPUTED_VALUE"""),110670.7) -> 110670.7 | H11: =IFERROR(__xludf.DUMMYFUNCTION("""COMPUTED_VALUE"""),3903.8702) -> 3903.8702 | I11: =IFERROR(__xludf.DUMMYFUNCTION("""COMPUTED_VALUE"""),2.552) -> 2.552 | J11: 0.037 | K11: 0.036 | L11: 0.0371 | M11: 0.0411 | N11: 0.0465 | O11: 0.0467 | P11: =IFERROR(__xludf.DUMMYFUNCTION("IF($A11="""","""", INDEX( GOOGLEFINANCE(""NYICDX"",""price"",$A11-5,$A11), ROWS(GOOGLEFINANCE(""NYICDX"",""price"",$A11-5,$A11)), 2 ) ) "),99.72) -> 99.72
A12: 45991 | B12: =IFERROR(__xludf.DUMMYFUNCTION("""COMPUTED_VALUE"""),387.88) -> 387.88 | C12: =IFERROR(__xludf.DUMMYFUNCTION("""COMPUTED_VALUE"""),51.21) -> 51.21 | D12: =IFERROR(__xludf.DUMMYFUNCTION("""COMPUTED_VALUE"""),152.59) -> 152.59 | E12: =IFERROR(__xludf.DUMMYFUNCTION("""COMPUTED_VALUE"""),6812.61) -> 6812.61 | F12: =IFERROR(__xludf.DUMMYFUNCTION("""COMPUTED_VALUE"""),477.18) -> 477.18 | G12: =IFERROR(__xludf.DUMMYFUNCTION("""COMPUTED_VALUE"""),90869.59) -> 90869.59 | H12: =IFERROR(__xludf.DUMMYFUNCTION("""COMPUTED_VALUE"""),3032.1419) -> 3032.1419 | I12: =IFERROR(__xludf.DUMMYFUNCTION("""COMPUTED_VALUE"""),2.1805) -> 2.1805 | J12: 0.0361 | K12: 0.0347 | L12: 0.0359 | M12: 0.0402 | N12: 0.0462 | O12: 0.0467 | P12: =IFERROR(__xludf.DUMMYFUNCTION("IF($A12="""","""", INDEX( GOOGLEFINANCE(""NYICDX"",""price"",$A12-5,$A12), ROWS(GOOGLEFINANCE(""NYICDX"",""price"",$A12-5,$A12)), 2 ) ) "),99.48) -> 99.48
A13: 46022 | B13: =IFERROR(__xludf.DUMMYFUNCTION("""COMPUTED_VALUE"""),398.89) -> 398.89 | C13: =IFERROR(__xludf.DUMMYFUNCTION("""COMPUTED_VALUE"""),68.98) -> 68.98 | D13: =IFERROR(__xludf.DUMMYFUNCTION("""COMPUTED_VALUE"""),198.61) -> 198.61 | E13: =IFERROR(__xludf.DUMMYFUNCTION("""COMPUTED_VALUE"""),6896.24) -> 6896.24 | F13: =IFERROR(__xludf.DUMMYFUNCTION("""COMPUTED_VALUE"""),483.59) -> 483.59 | G13: =IFERROR(__xludf.DUMMYFUNCTION("""COMPUTED_VALUE"""),87222.09) -> 87222.09 | H13: =IFERROR(__xludf.DUMMYFUNCTION("""COMPUTED_VALUE"""),2935.1436) -> 2935.1436 | I13: =IFERROR(__xludf.DUMMYFUNCTION("""COMPUTED_VALUE"""),1.8479) -> 1.8479 | J13: 0.036 | K13: 0.0352 | L13: 0.0368 | M13: 0.0411 | N13: 0.0472 | O13: 0.0476 | P13: =IFERROR(__xludf.DUMMYFUNCTION("IF($A13="""","""", INDEX( GOOGLEFINANCE(""NYICDX"",""price"",$A13-5,$A13), ROWS(GOOGLEFINANCE(""NYICDX"",""price"",$A13-5,$A13)), 2 ) ) "),98.28) -> 98.28
A14: 46053 | B14: =IFERROR(__xludf.DUMMYFUNCTION("""COMPUTED_VALUE"""),409.23) -> 409.23 | C14: =IFERROR(__xludf.DUMMYFUNCTION("""COMPUTED_VALUE"""),70.96) -> 70.96 | D14: =IFERROR(__xludf.DUMMYFUNCTION("""COMPUTED_VALUE"""),209.45) -> 209.45 | E14: =IFERROR(__xludf.DUMMYFUNCTION("""COMPUTED_VALUE"""),6944.82) -> 6944.82 | F14: =IFERROR(__xludf.DUMMYFUNCTION("""COMPUTED_VALUE"""),489.96) -> 489.96 | G14: =IFERROR(__xludf.DUMMYFUNCTION("""COMPUTED_VALUE"""),91332.58) -> 91332.58 | H14: =IFERROR(__xludf.DUMMYFUNCTION("""COMPUTED_VALUE"""),3166.9241) -> 3166.9241 | I14: =IFERROR(__xludf.DUMMYFUNCTION("""COMPUTED_VALUE"""),2.1671) -> 2.1671
B15: =IFERROR(__xludf.DUMMYFUNCTION("""COMPUTED_VALUE"""),"") | C15: =IFERROR(__xludf.DUMMYFUNCTION("""COMPUTED_VALUE"""),"") | D15: =IFERROR(__xludf.DUMMYFUNCTION("""COMPUTED_VALUE"""),"") | E15: =IFERROR(__xludf.DUMMYFUNCTION("""COMPUTED_VALUE"""),"") | F15: =IFERROR(__xludf.DUMMYFUNCTION("""COMPUTED_VALUE"""),"") | G15: =IFERROR(__xludf.DUMMYFUNCTION("""COMPUTED_VALUE"""),"") | H15: =IFERROR(__xludf.DUMMYFUNCTION("""COMPUTED_VALUE"""),"") | I15: =IFERROR(__xludf.DUMMYFUNCTION("""COMPUTED_VALUE"""),"")
B16: =IFERROR(__xludf.DUMMYFUNCTION("""COMPUTED_VALUE"""),"") | C16: =IFERROR(__xludf.DUMMYFUNCTION("""COMPUTED_VALUE"""),"") | D16: =IFERROR(__xludf.DUMMYFUNCTION("""COMPUTED_VALUE"""),"") | E16: =IFERROR(__xludf.DUMMYFUNCTION("""COMPUTED_VALUE"""),"") | F16: =IFERROR(__xludf.DUMMYFUNCTION("""COMPUTED_VALUE"""),"") | G16: =IFERROR(__xludf.DUMMYFUNCTION("""COMPUTED_VALUE"""),"") | H16: =IFERROR(__xludf.DUMMYFUNCTION("""COMPUTED_VALUE"""),"") | I16: =IFERROR(__xludf.DUMMYFUNCTION("""COMPUTED_VALUE"""),"")
B17: =IFERROR(__xludf.DUMMYFUNCTION("""COMPUTED_VALUE"""),"") | C17: =IFERROR(__xludf.DUMMYFUNCTION("""COMPUTED_VALUE"""),"") | D17: =IFERROR(__xludf.DUMMYFUNCTION("""COMPUTED_VALUE"""),"") | E17: =IFERROR(__xludf.DUMMYFUNCTION("""COMPUTED_VALUE"""),"") | F17: =IFERROR(__xludf.DUMMYFUNCTION("""COMPUTED_VALUE"""),"") | G17: =IFERROR(__xludf.DUMMYFUNCTION("""COMPUTED_VALUE"""),"") | H17: =IFERROR(__xludf.DUMMYFUNCTION("""COMPUTED_VALUE"""),"") | I17: =IFERROR(__xludf.DUMMYFUNCTION("""COMPUTED_VALUE"""),"")
B18: =IFERROR(__xludf.DUMMYFUNCTION("""COMPUTED_VALUE"""),"") | C18: =IFERROR(__xludf.DUMMYFUNCTION("""COMPUTED_VALUE"""),"") | D18: =IFERROR(__xludf.DUMMYFUNCTION("""COMPUTED_VALUE"""),"") | E18: =IFERROR(__xludf.DUMMYFUNCTION("""COMPUTED_VALUE"""),"") | F18: =IFERROR(__xludf.DUMMYFUNCTION("""COMPUTED_VALUE"""),"") | G18: =IFERROR(__xludf.DUMMYFUNCTION("""COMPUTED_VALUE"""),"") | H18: =IFERROR(__xludf.DUMMYFUNCTION("""COMPUTED_VALUE"""),"") | I18: =IFERROR(__xludf.DUMMYFUNCTION("""COMPUTED_VALUE"""),"")
B19: =IFERROR(__xludf.DUMMYFUNCTION("""COMPUTED_VALUE"""),"") | C19: =IFERROR(__xludf.DUMMYFUNCTION("""COMPUTED_VALUE"""),"") | D19: =IFERROR(__xludf.DUMMYFUNCTION("""COMPUTED_VALUE"""),"") | E19: =IFERROR(__xludf.DUMMYFUNCTION("""COMPUTED_VALUE"""),"") | F19: =IFERROR(__xludf.DUMMYFUNCTION("""COMPUTED_VALUE"""),"") | G19: =IFERROR(__xludf.DUMMYFUNCTION("""COMPUTED_VALUE"""),"") | H19: =IFERROR(__xludf.DUMMYFUNCTION("""COMPUTED_VALUE"""),"") | I19: =IFERROR(__xludf.DUMMYFUNCTION("""COMPUTED_VALUE"""),"")
B20: =IFERROR(__xludf.DUMMYFUNCTION("""COMPUTED_VALUE"""),"") | C20: =IFERROR(__xludf.DUMMYFUNCTION("""COMPUTED_VALUE"""),"") | D20: =IFERROR(__xludf.DUMMYFUNCTION("""COMPUTED_VALUE"""),"") | E20: =IFERROR(__xludf.DUMMYFUNCTION("""COMPUTED_VALUE"""),"") | F20: =IFERROR(__xludf.DUMMYFUNCTION("""COMPUTED_VALUE"""),"") | G20: =IFERROR(__xludf.DUMMYFUNCTION("""COMPUTED_VALUE"""),"") | H20: =IFERROR(__xludf.DUMMYFUNCTION("""COMPUTED_VALUE"""),"") | I20: =IFERROR(__xludf.DUMMYFUNCTION("""COMPUTED_VALUE"""),"")
B21: =IFERROR(__xludf.DUMMYFUNCTION("""COMPUTED_VALUE"""),"") | C21: =IFERROR(__xludf.DUMMYFUNCTION("""COMPUTED_VALUE"""),"") | D21: =IFERROR(__xludf.DUMMYFUNCTION("""COMPUTED_VALUE"""),"") | E21: =IFERROR(__xludf.DUMMYFUNCTION("""COMPUTED_VALUE"""),"") | F21: =IFERROR(__xludf.DUMMYFUNCTION("""COMPUTED_VALUE"""),"") | G21: =IFERROR(__xludf.DUMMYFUNCTION("""COMPUTED_VALUE"""),"") | H21: =IFERROR(__xludf.DUMMYFUNCTION("""COMPUTED_VALUE"""),"") | I21: =IFERROR(__xludf.DUMMYFUNCTION("""COMPUTED_VALUE"""),"")
B22: =IFERROR(__xludf.DUMMYFUNCTION("""COMPUTED_VALUE"""),"") | C22: =IFERROR(__xludf.DUMMYFUNCTION("""COMPUTED_VALUE"""),"") | D22: =IFERROR(__xludf.DUMMYFUNCTION("""COMPUTED_VALUE"""),"") | E22: =IFERROR(__xludf.DUMMYFUNCTION("""COMPUTED_VALUE"""),"") | F22: =IFERROR(__xludf.DUMMYFUNCTION("""COMPUTED_VALUE"""),"") | G22: =IFERROR(__xludf.DUMMYFUNCTION("""COMPUTED_VALUE"""),"") | H22: =IFERROR(__xludf.DUMMYFUNCTION("""COMPUTED_VALUE"""),"") | I22: =IFERROR(__xludf.DUMMYFUNCTION("""COMPUTED_VALUE"""),"")
B23: =IFERROR(__xludf.DUMMYFUNCTION("""COMPUTED_VALUE"""),"") | C23: =IFERROR(__xludf.DUMMYFUNCTION("""COMPUTED_VALUE"""),"") | D23: =IFERROR(__xludf.DUMMYFUNCTION("""COMPUTED_VALUE"""),"") | E23: =IFERROR(__xludf.DUMMYFUNCTION("""COMPUTED_VALUE"""),"") | F23: =IFERROR(__xludf.DUMMYFUNCTION("""COMPUTED_VALUE"""),"") | G23: =IFERROR(__xludf.DUMMYFUNCTION("""COMPUTED_VALUE"""),"") | H23: =IFERROR(__xludf.DUMMYFUNCTION("""COMPUTED_VALUE"""),"") | I23: =IFERROR(__xludf.DUMMYFUNCTION("""COMPUTED_VALUE"""),"")
B24: =IFERROR(__xludf.DUMMYFUNCTION("""COMPUTED_VALUE"""),"") | C24: =IFERROR(__xludf.DUMMYFUNCTION("""COMPUTED_VALUE"""),"") | D24: =IFERROR(__xludf.DUMMYFUNCTION("""COMPUTED_VALUE"""),"") | E24: =IFERROR(__xludf.DUMMYFUNCTION("""COMPUTED_VALUE"""),"") | F24: =IFERROR(__xludf.DUMMYFUNCTION("""COMPUTED_VALUE"""),"") | G24: =IFERROR(__xludf.DUMMYFUNCTION("""COMPUTED_VALUE"""),"") | H24: =IFERROR(__xludf.DUMMYFUNCTION("""COMPUTED_VALUE"""),"") | I24: =IFERROR(__xludf.DUMMYFUNCTION("""COMPUTED_VALUE"""),"")
B25: =IFERROR(__xludf.DUMMYFUNCTION("""COMPUTED_VALUE"""),"") | C25: =IFERROR(__xludf.DUMMYFUNCTION("""COMPUTED_VALUE"""),"") | D25: =IFERROR(__xludf.DUMMYFUNCTION("""COMPUTED_VALUE"""),"") | E25: =IFERROR(__xludf.DUMMYFUNCTION("""COMPUTED_VALUE"""),"") | F25: =IFERROR(__xludf.DUMMYFUNCTION("""COMPUTED_VALUE"""),"") | G25: =IFERROR(__xludf.DUMMYFUNCTION("""COMPUTED_VALUE"""),"") | H25: =IFERROR(__xludf.DUMMYFUNCTION("""COMPUTED_VALUE"""),"") | I25: =IFERROR(__xludf.DUMMYFUNCTION("""COMPUTED_VALUE"""),"")
B26: =IFERROR(__xludf.DUMMYFUNCTION("""COMPUTED_VALUE"""),"") | C26: =IFERROR(__xludf.DUMMYFUNCTION("""COMPUTED_VALUE"""),"") | D26: =IFERROR(__xludf.DUMMYFUNCTION("""COMPUTED_VALUE"""),"") | E26: =IFERROR(__xludf.DUMMYFUNCTION("""COMPUTED_VALUE"""),"") | F26: =IFERROR(__xludf.DUMMYFUNCTION("""COMPUTED_VALUE"""),"") | G26: =IFERROR(__xludf.DUMMYFUNCTION("""COMPUTED_VALUE"""),"") | H26: =IFERROR(__xludf.DUMMYFUNCTION("""COMPUTED_VALUE"""),"") | I26: =IFERROR(__xludf.DUMMYFUNCTION("""COMPUTED_VALUE"""),"")
... B1000: =IFERROR(__xludf.DUMMYFUNCTION("""COMPUTED_VALUE"""),"") | C1000: =IFERROR(__xludf.DUMMYFUNCTION("""COMPUTED_VALUE"""),"") | D1000: =IFERROR(__xludf.DUMMYFUNCTION("""COMPUTED_VALUE"""),"") | E1000: =IFERROR(__xludf.DUMMYFUNCTION("""COMPUTED_VALUE"""),"") | F1000: =IFERROR(__xludf.DUMMYFUNCTION("""COMPUTED_VALUE"""),"") | G1000: =IFERROR(__xludf.DUMMYFUNCTION("""COMPUTED_VALUE"""),"") | H1000: =IFERROR(__xludf.DUMMYFUNCTION("""COMPUTED_VALUE"""),"") | I1000: =IFERROR(__xludf.DUMMYFUNCTION("""COMPUTED_VALUE"""),"")

Sheet Trump Tracke v3
A1: T.R.U.M.P. Tracker | J1: HOUSING METRICS | P1: COST TRACKERS | T1: LAST UPDATED: 10/09/2025 09:22 AM EST
A2: unbiased, raw housing data. | J2: KPI | K2: Target | L2: Current | M2: Start | N2: Total Change | P2: Builder Expenses | Q2: Current | R2: Start | S2: Total Change | V2: Household Expenses | W2: Current | X2: Start | Y2: Total Change
A3: Housing Health Score | J3: Resale Home (Median $) | K3: 385000 | L3: 422600 | M3: 393400 | N3: =(L3-M3) -> 29200 | P3: Softwood Lumber | Q3: 262.856 | R3: 267.54 | S3: =IF(OR(Q3="", R3=""), "", Q3 - R3) -> -4.684 | T3: =IF(OR(Q3="", R3="", R3=0), "", IF((Q3 - R3)/R3 >= 0.1, "⬆️⬆️ MAJOR Rise", IF((Q3 - R3)/R3 >= 0.01, "⬆️ Rise", IF((Q3 - R3)/R3 <= -0.1, "⬇️⬇️ MAJOR Drop", IF((Q3 - R3)/R3 <= -0.01, "⬇️ Drop", "Stable"))))) -> ⬇️ Drop | V3: Food Overall | W3: 341.208 | X3: 335.67 | Y3: =IF(OR(W3="", X3=""), "", W3 - X3) -> 5.538 | Z3: =IF(OR(W3="", X3="", X3=0), "", IF((W3 - X3)/X3 >= 0.1, "⬆️⬆️ MAJOR Rise", IF((W3 - X3)/X3 >= 0.01, "⬆️ Rise", IF((W3 - X3)/X3 <= -0.1, "⬇️⬇️ MAJOR Drop", IF((W3 - X3)/X3 <= -0.01, "⬇️ Drop", "Stable"))))) -> ⬆️ Rise
A4: Today | B4: =(Q22 * 0.45) + (Q21 * 0.35) + ((135 - Q23) / 135 * 100) * 0.2 -> 49.241451 | C4: 🔴 Nowhere close to affordable | J4: New Construction (Median $) | K4: 401800 | L4: 413500 | M4: 427900 | N4: =(L4-M4) -> -14400 | P4: Steel | Q4: 144.164 | R4: 131.69 | S4: =IF(OR(Q4="", R4=""), "", Q4 - R4) -> 12.474 | T4: =IF(OR(Q4="", R4="", R4=0), "", IF((Q4 - R4)/R4 >= 0.1, "⬆️⬆️ MAJOR Rise", IF((Q4 - R4)/R4 >= 0.01, "⬆️ Rise", IF((Q4 - R4)/R4 <= -0.1, "⬇️⬇️ MAJOR Drop", IF((Q4 - R4)/R4 <= -0.01, "⬇️ Drop", "Stable"))))) -> ⬆️ Rise | V4: Doors/Windows | W4: 472.83 | X4: 429.67 | Y4: =IF(OR(W4="", X4=""), "", W4 - X4) -> 43.16 | Z4: =IF(OR(W4="", X4="", X4=0), "", IF((W4 - X4)/X4 >= 0.1, "⬆️⬆️ MAJOR Rise", IF((W4 - X4)/X4 >= 0.01, "⬆️ Rise", IF((W4 - X4)/X4 <= -0.1, "⬇️⬇️ MAJOR Drop", IF((W4 - X4)/X4 <= -0.01, "⬇️ Drop", "Stable"))))) -> ⬆️⬆️ MAJOR Rise
A5: 90 Day | B5: TBD | C5: TBD | J5: Affordable Home (Median $) | K5: 310000 | L5: 361000 | M5: 348600 | N5: =(L5-M5) -> 12400 | P5: Shingles | Q5: 375.402 | R5: 359.22 | S5: =IF(OR(Q5="", R5=""), "", Q5 - R5) -> 16.182 | T5: =IF(OR(Q5="", R5="", R5=0), "", IF((Q5 - R5)/R5 >= 0.1, "⬆️⬆️ MAJOR Rise", IF((Q5 - R5)/R5 >= 0.01, "⬆️ Rise", IF((Q5 - R5)/R5 <= -0.1, "⬇️⬇️ MAJOR Drop", IF((Q5 - R5)/R5 <= -0.01, "⬇️ Drop", "Stable"))))) -> ⬆️ Rise | V5: HVAC System | W5: 232.94 | X5: 222.5 | Y5: =IF(OR(W5="", X5=""), "", W5 - X5) -> 10.44 | Z5: =IF(OR(W5="", X5="", X5=0), "", IF((W5 - X5)/X5 >= 0.1, "⬆️⬆️ MAJOR Rise", IF((W5 - X5)/X5 >= 0.01, "⬆️ Rise", IF((W5 - X5)/X5 <= -0.1, "⬇️⬇️ MAJOR Drop", IF((W5 - X5)/X5 <= -0.01, "⬇️ Drop", "Stable"))))) -> ⬆️ Rise
A6: 1 Year | B6: TBD | C6: TBD | P6: Plumbing | Q6: 479.987 | R6: 421.34 | S6: =IF(OR(Q6="", R6=""), "", Q6 - R6) -> 58.647 | T6: =IF(OR(Q6="", R6="", R6=0), "", IF((Q6 - R6)/R6 >= 0.1, "⬆️⬆️ MAJOR Rise", IF((Q6 - R6)/R6 >= 0.01, "⬆️ Rise", IF((Q6 - R6)/R6 <= -0.1, "⬇️⬇️ MAJOR Drop", IF((Q6 - R6)/R6 <= -0.01, "⬇️ Drop", "Stable"))))) -> ⬆️⬆️ MAJOR Rise | V6: Fridge | W6: 133.343 | X6: 132.62 | Y6: =IF(OR(W6="", X6=""), "", W6 - X6) -> 0.723 | Z6: =IF(OR(W6="", X6="", X6=0), "", IF((W6 - X6)/X6 >= 0.1, "⬆️⬆️ MAJOR Rise", IF((W6 - X6)/X6 >= 0.01, "⬆️ Rise", IF((W6 - X6)/X6 <= -0.1, "⬇️⬇️ MAJOR Drop", IF((W6 - X6)/X6 <= -0.01, "⬇️ Drop", "Stable"))))) -> Stable
A7: 5 Year | B7: TBD | C7: TBD | P7: Concrete | Q7: 252.556 | R7: 251.22 | S7: =IF(OR(Q7="", R7=""), "", Q7 - R7) -> 1.336 | T7: =IF(OR(Q7="", R7="", R7=0), "", IF((Q7 - R7)/R7 >= 0.1, "⬆️⬆️ MAJOR Rise", IF((Q7 - R7)/R7 >= 0.01, "⬆️ Rise", IF((Q7 - R7)/R7 <= -0.1, "⬇️⬇️ MAJOR Drop", IF((Q7 - R7)/R7 <= -0.01, "⬇️ Drop", "Stable"))))) -> Stable | V7: Water Heater | W7: 641.38 | X7: 591.49 | Y7: =IF(OR(W7="", X7=""), "", W7 - X7) -> 49.89 | Z7: =IF(OR(W7="", X7="", X7=0), "", IF((W7 - X7)/X7 >= 0.1, "⬆️⬆️ MAJOR Rise", IF((W7 - X7)/X7 >= 0.01, "⬆️ Rise", IF((W7 - X7)/X7 <= -0.1, "⬇️⬇️ MAJOR Drop", IF((W7 - X7)/X7 <= -0.01, "⬇️ Drop", "Stable"))))) -> ⬆️ Rise
P8: Household Expenses | T8: =IF(OR(Q8="", R8="", R8=0), "", IF((Q8 - R8)/R8 >= 0.1, "⚠️ MAJOR Rise", IF((Q8 - R8)/R8 >= 0.01, "🔺 Rise", IF((Q8 - R8)/R8 <= -0.1, "✅ MAJOR drop", IF((Q8 - R8)/R8 <= -0.01, "✅ drop", "Stable"))))) | V8: Household Expenses | Z8: =IF(OR(W8="", X8="", X8=0), "", IF((W8 - X8)/X8 >= 0.1, "⚠️ MAJOR Rise", IF((W8 - X8)/X8 >= 0.01, "🔺 Rise", IF((W8 - X8)/X8 <= -0.1, "✅ MAJOR drop", IF((W8 - X8)/X8 <= -0.01, "✅ drop", "Stable")))))
A9: Bill Tracker | J9: Mortgage Rate | K9: 0.0672 | L9: 0.0634 | M9: 0.0707 | N9: =(L9-M9)*100 -> -0.73 | P9: Power (per KWH) | Q9: 0.19 | R9: 0.179 | S9: =IF(OR(Q9="", R9=""), "", Q9 - R9) -> 0.011 | T9: =IF(OR(Q9="", R9="", R9=0), "", IF((Q9 - R9)/R9 >= 0.1, "⬆️⬆️ MAJOR Rise", IF((Q9 - R9)/R9 >= 0.01, "⬆️ Rise", IF((Q9 - R9)/R9 <= -0.1, "⬇️⬇️ MAJOR Drop", IF((Q9 - R9)/R9 <= -0.01, "⬇️ Drop", "Stable"))))) -> ⬆️ Rise | V9: Beef | W9: 6.38 | X9: 5.54 | Y9: =IF(OR(W9="", X9=""), "", W9 - X9) -> 0.84 | Z9: =IF(OR(W9="", X9="", X9=0), "", IF((W9 - X9)/X9 >= 0.1, "⬆️⬆️ MAJOR Rise", IF((W9 - X9)/X9 >= 0.01, "⬆️ Rise", IF((W9 - X9)/X9 <= -0.1, "⬇️⬇️ MAJOR Drop", IF((W9 - X9)/X9 <= -0.01, "⬇️ Drop", "Stable"))))) -> ⬆️⬆️ MAJOR Rise
A10: Bill # | B10: Name | C10: Status | D10: Bill # (last met) | E10: Purpose | J10: Fed Rate | K10: 0.0433 | L10: 0.0422 | M10: 0.0433 | N10: =(L10-M10)*100 -> -0.11 | P10: Milk | Q10: 4.171 | R10: 4.03 | S10: =IF(OR(Q10="", R10=""), "", Q10 - R10) -> 0.141 | T10: =IF(OR(Q10="", R10="", R10=0), "", IF((Q10 - R10)/R10 >= 0.1, "⬆️⬆️ MAJOR Rise", IF((Q10 - R10)/R10 >= 0.01, "⬆️ Rise", IF((Q10 - R10)/R10 <= -0.1, "⬇️⬇️ MAJOR Drop", IF((Q10 - R10)/R10 <= -0.01, "⬇️ Drop", "Stable"))))) -> ⬆️ Rise | V10: Coffee | W10: 8.892 | X10: 7.01 | Y10: =IF(OR(W10="", X10=""), "", W10 - X10) -> 1.882 | Z10: =IF(OR(W10="", X10="", X10=0), "", IF((W10 - X10)/X10 >= 0.1, "⬆️⬆️ MAJOR Rise", IF((W10 - X10)/X10 >= 0.01, "⬆️ Rise", IF((W10 - X10)/X10 <= -0.1, "⬇️⬇️ MAJOR Drop", IF((W10 - X10)/X10 <= -0.01, "⬇️ Drop", "Stable"))))) -> ⬆️⬆️ MAJOR Rise
A11: HR 2945 (US) | B11: Housing for All Act | C11: Currently at committee lvl | D11: SB 391 (nevada) | E11: cap corporate home ownership | J11: 10 Year Treasury Yield | K11: 0.0439 | L11: 0.0412 | M11: 0.04623 | N11: =(L11-M11)*100 -> -0.503 | P11: Eggs | Q11: 3.587 | R11: 4.95 | S11: =IF(OR(Q11="", R11=""), "", Q11 - R11) -> -1.363 | T11: =IF(OR(Q11="", R11="", R11=0), "", IF((Q11 - R11)/R11 >= 0.1, "⬆️⬆️ MAJOR Rise", IF((Q11 - R11)/R11 >= 0.01, "⬆️ Rise", IF((Q11 - R11)/R11 <= -0.1, "⬇️⬇️ MAJOR Drop", IF((Q11 - R11)/R11 <= -0.01, "⬇️ Drop", "Stable"))))) -> ⬇️⬇️ MAJOR Drop | V11: Car Parts | W11: 187.124 | X11: 182.98 | Y11: =IF(OR(W11="", X11=""), "", W11 - X11) -> 4.144 | Z11: =IF(OR(W11="", X11="", X11=0), "", IF((W11 - X11)/X11 >= 0.1, "⬆️⬆️ MAJOR Rise", IF((W11 - X11)/X11 >= 0.01, "⬆️ Rise", IF((W11 - X11)/X11 <= -0.1, "⬇️⬇️ MAJOR Drop", IF((W11 - X11)/X11 <= -0.01, "⬇️ Drop", "Stable"))))) -> ⬆️ Rise
A12: HR 2725 (US) | B12: Affordable Housing Credit Improvement | C12: "ways & means" committee | D12: AB 11 (california) | E12: build social housing units | J12: Core Inflation Y.O.Y. | K12: 0.03288774 | L12: 0.034 | M12: 0.0363 | N12: =(L12-M12)*100 -> -0.23 | P12: Bread | Q12: 1.841 | R12: 1.93 | S12: =IF(OR(Q12="", R12=""), "", Q12 - R12) -> -0.089 | T12: =IF(OR(Q12="", R12="", R12=0), "", IF((Q12 - R12)/R12 >= 0.1, "⬆️⬆️ MAJOR Rise", IF((Q12 - R12)/R12 >= 0.01, "⬆️ Rise", IF((Q12 - R12)/R12 <= -0.1, "⬇️⬇️ MAJOR Drop", IF((Q12 - R12)/R12 <= -0.01, "⬇️ Drop", "Stable"))))) -> ⬇️ Drop | V12: Childcare/education | W12: 893.305 | X12: 879.54 | Y12: =IF(OR(W12="", X12=""), "", W12 - X12) -> 13.765 | Z12: =IF(OR(W12="", X12="", X12=0), "", IF((W12 - X12)/X12 >= 0.1, "⬆️⬆️ MAJOR Rise", IF((W12 - X12)/X12 >= 0.01, "⬆️ Rise", IF((W12 - X12)/X12 <= -0.1, "⬇️⬇️ MAJOR Drop", IF((W12 - X12)/X12 <= -0.01, "⬇️ Drop", "Stable"))))) -> ⬆️ Rise
A13: SB 79 (california) | B13: Transit - Orented Housing | C13: Senate Finance Committee | J13: Median Mortgage p/month* | K13: 2250 | L13: 2670 | M13: 2705 | N13: =(L13-M13) -> -35 | P13: Boneless Chicken | Q13: 4.212 | R13: 3.97 | S13: =IF(OR(Q13="", R13=""), "", Q13 - R13) -> 0.242 | T13: =IF(OR(Q13="", R13="", R13=0), "", IF((Q13 - R13)/R13 >= 0.1, "⬆️⬆️ MAJOR Rise", IF((Q13 - R13)/R13 >= 0.01, "⬆️ Rise", IF((Q13 - R13)/R13 <= -0.1, "⬇️⬇️ MAJOR Drop", IF((Q13 - R13)/R13 <= -0.01, "⬇️ Drop", "Stable"))))) -> ⬆️ Rise | V13: Clothing | W13: 133.608 | X13: 128.175 | Y13: =IF(OR(W13="", X13=""), "", W13 - X13) -> 5.433 | Z13: =IF(OR(W13="", X13="", X13=0), "", IF((W13 - X13)/X13 >= 0.1, "⬆️⬆️ MAJOR Rise", IF((W13 - X13)/X13 >= 0.01, "⬆️ Rise", IF((W13 - X13)/X13 <= -0.1, "⬇️⬇️ MAJOR Drop", IF((W13 - X13)/X13 <= -0.01, "⬇️ Drop", "Stable"))))) -> ⬆️ Rise
A14: S 934 (US) | B14: Senate Finance Committee | C14: Senate Finance Committee | P14: Gallon of Gas | Q14: 3.23 | R14: 3.21 | S14: =IF(OR(Q14="", R14=""), "", Q14 - R14) -> 0.02 | T14: =IF(OR(Q14="", R14="", R14=0), "", IF((Q14 - R14)/R14 >= 0.1, "⬆️⬆️ MAJOR Rise", IF((Q14 - R14)/R14 >= 0.01, "⬆️ Rise", IF((Q14 - R14)/R14 <= -0.1, "⬇️⬇️ MAJOR Drop", IF((Q14 - R14)/R14 <= -0.01, "⬇️ Drop", "Stable"))))) -> Stable | V14: Used Car | W14: 185.322 | X14: 185.43 | Y14: =IF(OR(W14="", X14=""), "", W14 - X14) -> -0.108 | Z14: =IF(OR(W14="", X14="", X14=0), "", IF((W14 - X14)/X14 >= 0.1, "⬆️⬆️ MAJOR Rise", IF((W14 - X14)/X14 >= 0.01, "⬆️ Rise", IF((W14 - X14)/X14 <= -0.1, "⬇️⬇️ MAJOR Drop", IF((W14 - X14)/X14 <= -0.01, "⬇️ Drop", "Stable"))))) -> Stable
A15: HR {tbd} (US) | B15: No tax on home sales act | C15: recently introduced | J15: FTHB Affordability Index | K15: 95 | L15: 64.6 | M15: 66.8 | N15: =(L15-M15)/M15 -> -0.032934132 | P15: Home Insurance | Q15: 265.527 | R15: 260.75 | S15: =IF(OR(Q15="", R15=""), "", Q15 - R15) -> 4.777 | T15: =IF(OR(Q15="", R15="", R15=0), "", IF((Q15 - R15)/R15 >= 0.1, "⬆️⬆️ MAJOR Rise", IF((Q15 - R15)/R15 >= 0.01, "⬆️ Rise", IF((Q15 - R15)/R15 <= -0.1, "⬇️⬇️ MAJOR Drop", IF((Q15 - R15)/R15 <= -0.01, "⬇️ Drop", "Stable"))))) -> ⬆️ Rise | V15: Health Insurance | W15: 162.734 | X15: 160.488 | Y15: =IF(OR(W15="", X15=""), "", W15 - X15) -> 2.246 | Z15: =IF(OR(W15="", X15="", X15=0), "", IF((W15 - X15)/X15 >= 0.1, "⬆️⬆️ MAJOR Rise", IF((W15 - X15)/X15 >= 0.01, "⬆️ Rise", IF((W15 - X15)/X15 <= -0.1, "⬇️⬇️ MAJOR Drop", IF((W15 - X15)/X15 <= -0.01, "⬇️ Drop", "Stable"))))) -> ⬆️ Rise
A16: HR 2710 (US) | B16: People over parking act | C16: recently introduced | J16: Housing Affordability Index | K16: 125 | L16: 98.8 | M16: 100.7 | N16: =(L16-M16)/M16 -> -0.018867925 | P16: Car Insurance | Q16: 222.137 | R16: 218.25 | S16: =IF(OR(Q16="", R16=""), "", Q16 - R16) -> 3.887 | T16: =IF(OR(Q16="", R16="", R16=0), "", IF((Q16 - R16)/R16 >= 0.1, "⬆️⬆️ MAJOR Rise", IF((Q16 - R16)/R16 >= 0.01, "⬆️ Rise", IF((Q16 - R16)/R16 <= -0.1, "⬇️⬇️ MAJOR Drop", IF((Q16 - R16)/R16 <= -0.01, "⬇️ Drop", "Stable"))))) -> ⬆️ Rise | V16: Rent | W16: 437.46 | X16: 429.017 | Y16: =IF(OR(W16="", X16=""), "", W16 - X16) -> 8.443 | Z16: =IF(OR(W16="", X16="", X16=0), "", IF((W16 - X16)/X16 >= 0.1, "⬆️⬆️ MAJOR Rise", IF((W16 - X16)/X16 >= 0.01, "⬆️ Rise", IF((W16 - X16)/X16 <= -0.1, "⬇️⬇️ MAJOR Drop", IF((W16 - X16)/X16 <= -0.01, "⬇️ Drop", "Stable"))))) -> ⬆️ Rise
J17: Median Household Income | K17: 80610 | L17: 83730 | M17: 80610 | N17: =(L17-M17) -> 3120 | P17: Medical Care | Q17: 582.832 | R17: 571.234 | S17: =IF(OR(Q17="", R17=""), "", Q17 - R17) -> 11.598 | T17: =IF(OR(Q17="", R17="", R17=0), "", IF((Q17 - R17)/R17 >= 0.1, "⬆️⬆️ MAJOR Rise", IF((Q17 - R17)/R17 >= 0.01, "⬆️ Rise", IF((Q17 - R17)/R17 <= -0.1, "⬇️⬇️ MAJOR Drop", IF((Q17 - R17)/R17 <= -0.01, "⬇️ Drop", "Stable"))))) -> ⬆️ Rise | V17: Orange Juice
V18: Bananas
A19: Affordability by Region | J19: Bills in Congress** | K19: literally anything | L19: 3 | M19: 3 | N19: =2 -> 2 | P19: THE KEY 3 | R19: the 3 scores below, are weighted and used as an index for the Housing Health Score (P27) | V19: Potato chips | W19: =IFS( ISNUMBER(L16), IFS( L16>=95, 40, L16>=90, 35 + (L16 - 90) * 1, L16>=85, 30 + (L16 - 85) * 1, L16>=80, 25 + (L16 - 80) * 1, L16>=70, 18 + (L16 - 70) * 0.7, L16>=60, 12 + (L16 - 60) * 0.6, TRUE, 6 ), "❌ NOT A NUMBER" ) -> #N/A
A20: metric | B20: North East | C20: Midwest | D20: South | E20: West | P20: Variable | Q20: Score | R20: Tier | T20: Monthly Change
A21: Resale Home (Median $) | B21: 477100 | C21: 297900 | D21: 363900 | E21: 623700 | J21: Total Homes for Sale | K21: 2502500 | L21: 1100407 | M21: 829376 | N21: =(L21-M21) -> 271031 | P21: Supply | Q21: =IFS( V21>=0.9, 100, V21>=0.8, (V21 - 0.8)*190 + 80, V21>=0.65, (V21 - 0.65)*126.67 + 60, V21>=0.45, (V21 - 0.45)*100 + 40, V21>=0.3, (V21 - 0.3)*126.67 + 20, TRUE, V21*30 + 10 ) -> 47.710103 | R21: =IFS( Q21>=90, "🟢 Balanced", Q21>=70, "🟡 Slight Undersupply", Q21>=45, "🟠 Tight Market", TRUE, "🔴 Critical Shortage" ) -> 🟠 Tight Market | T21: TBD | V21: =( (L23/K23)*0.5 + (L22/K22)*0.25 + (L24/K24)*0.15 + (L21/K21)*0.1 ) -> 0.52710103
A22: Median Qualifying Income | B22: 120912 | C22: 75504 | D22: 92208 | E22: 158064 | J22: New Construction for Sale | K22: 550000 | L22: 490000 | M22: 496000 | N22: =(L22-M22) -> -6000 | P22: Affordability | Q22: =( IFS( L15>=95, 40, L15>=90, 35 + (L15 - 90) * 1, L15>=85, 30 + (L15 - 85) * 1, L15>=80, 25 + (L15 - 80) * 1, L15>=70, 18 + (L15 - 70) * 0.7, L15>=60, 12 + (L15 - 60) * 0.6, TRUE, 6 ) + IFS( L16>=125, 20, L16>=115, 17 + (L16 - 115) * 0.3, L16>=105, 13 + (L16 - 105) * 0.4, L16>=95, 9 + (L16 - 95) * 0.4, L16>=85, 6 + (L16 - 85) * 0.3, TRUE, 3 ) + IFS( L9<=0.045, 15, L9<=0.05, 12 + (0.05 - L9) * 600, L9<=0.055, 9 + (0.055 - L9) * 600, L9<=0.06, 6 + (0.06 - L9) * 600, L9<=0.065, 3 + (0.065 - L9) * 600, L9<=0.07, 1.5 + (0.07 - L9) * 300, TRUE, 0 ) + IFS( L11<=0.023, 7.5, L11<=0.03, 6 + (0.03 - L11) / 0.007 * 1.5, L11<=0.04, 4.5 + (0.04 - L11) / 0.01 * 1.5, L11<=0.045, 3 + (0.045 - L11) / 0.005 * 1.5, L11<=0.05, 1.5 + (0.05 - L11) / 0.005 * 1.5, TRUE, 0 ) + IFS( L17>=100000, 17.5, L17>=97000, 15 + (L17 - 97000) / 3000 * 2.5, L17>=90000, 12 + (L17 - 90000) / 7000 * 3, L17>=85000, 9 + (L17 - 85000) / 5000 * 3, L17>=80000, 6 + (L17 - 80000) / 5000 * 3, TRUE, 3 ) ) -> 41.618 | R22: =IFS( Q22>=80, "🟢 Affordable", Q22>=60, "🟡 Pressured", Q22>=40, "🟠 Very Strained", TRUE, "🔴 Meltdown" ) -> 🟠 Very Strained | T22: TBD | V22: =AVERAGE(L16*0.85, L15) -> 74.29 | W22: =AVERAGE(K16*0.85, K15) -> 100.625 | X22: =AVERAGE(L16*0.85, L15) -> 74.29
A23: Median Family Income | B23: 113317 | C23: 101308 | D23: 96751 | E23: 112549 | J23: Resale Homes for Sale | K23: 2000500 | L23: =L21-L22 -> 610407 | M23: =M21-M22 -> 333376 | N23: =(L23-M23) -> 277031 | P23: Crash Likelihood | Q23: =MIN(100, SUM(E32:E35, E36:E46)) -> 41.75 | R23: =IFS( Q23>=100, "🔴 MELTDOWN", Q23>=80, "🟠 Crash in Sight", Q23>=70, "🟡 Correction in Sight", Q23>=45, "🟢 Slightly Slower", TRUE, "🟢 No Where Close" ) -> 🟢 No Where Close | T23: TBD
A24: Median Mortgage (P&I) | B24: 2614 | C24: 1566 | D24: 1944 | E24: 3346 | J24: Building Permits | K24: 1850000 | L24: 1330000 | M24: 1456000 | N24: =(L24-M24) -> -126000 | V24: links with promises + updates
A25: Affordability Index | B25: 93.7 | C25: 134.2 | D25: 104.9 | E25: 71.2 | J25: *$2,000 in HI & $2,000 in property taxes are escrowed into this payment. 30 year term w/ 10% down. No HOA or PMI. Based off "Resale Home (Median $) | V25: Agenda 47
A26: month prior | B26: 89.4 | C26: 133.7 | D26: 105 | E26: 70.3 | J26: **tracking for "Regulatory Costs", "Zoning Laws", "Impact Fee Structure", and "First time home buyer" related legislation | V26: Everything Trump has done so far to effect Housing (click)
A27: last year | B27: 100.9 | C27: 136.8 | D27: 102 | E27: 71 | P27: Housing Health Score | V27: Latest on Housing & Urban Development
J28: (get NOTIFIED of BIG updates) | P28: Today | Q28: =(Q22 * 0.45) + (Q21 * 0.35) + ((135 - Q23) / 135 * 100) * 0.2 -> 49.241451 | R28: =IFS( Q28 >= 85, "🟢 Affordable Housing", Q28 >= 72.5, "🟡 Buyer's Market", Q28 >= 60, "🟠 Neutral Market", Q28 >= 50, "🔴 Affordability Crisis", Q28 >= 40, "🔴 Nowhere close to affordable", TRUE, "🔥 Crisis Mode ") -> 🔴 Nowhere close to affordable | V28: Project 2025 Tracker (projected housing related changes)
A30: HOUSING CRASH TRACKER (P23)
A31: Variable | C31: Category | D31: Current | E31: Points | F31: Tier
A32: Unemployment Rate | C32: Critical | D32: 0.043 | E32: =IFS(D32 < 0.04, 0, D32 < 0.06, 3, D32 < 0.08, 6, D32 < 0.1, 9, TRUE, 12) -> 3 | F32: =IFS( E32>=10, "🔴 High Risk", E32>=6, "🟠 Elevated Risk", E32>=3, "🟡 Moderate Risk", TRUE, "🟢 Low Risk" ) -> 🟡 Moderate Risk
A33: FHA Mortgage Delinquency Rate | C33: Critical | D33: 0.1006 | E33: =IFS(D33 < 0.05, 0, D33 < 0.1, 3, D33 < 0.13, 6, D33 < 0.15, 9, TRUE, 12) -> 6 | F33: =IFS( E33>=10, "🔴 High Risk", E33>=6, "🟠 Elevated Risk", E33>=3, "🟡 Moderate Risk", TRUE, "🟢 Low Risk" ) -> 🟠 Elevated Risk
A34: Total Mortgage Delinquency Rate | C34: Critical | D34: 0.0179 | E34: =IFS(D34<2%, 0, D34<5%, 5, D34<10%, 10, TRUE, 15) -> 0 | F34: =IFS( E34>=10, "🔴 High Risk", E34>=6, "🟠 Elevated Risk", E34>=3, "🟡 Moderate Risk", TRUE, "🟢 Low Risk" ) -> 🟢 Low Risk
A35: Total Housing Supply | C35: Critical | D35: 1100407 | E35: =IFS(D35 > 0.6, 0, D35 > 0.45, 3, D35 > 0.3, 6, D35 > 0.15, 9, TRUE, 12) -> 0 | F35: =IFS( E35>=10, "🔴 High Risk", E35>=6, "🟠 Elevated Risk", E35>=3, "🟡 Moderate Risk", TRUE, "🟢 Low Risk" ) -> 🟢 Low Risk
A36: Disposable Income of Homeowners | C36: Major | D36: 0.11249194 | E36: =IFS(D36 > 0.13, 0, D36 > 0.11, 2, D36 > 0.09, 4, D36 > 0.07, 6, TRUE, 8) -> 2 | F36: =IFS( E36>=10, "🔴 High Risk", E36>=6, "🟠 Elevated Risk", E36>=3, "🟡 Moderate Risk", TRUE, "🟢 Low Risk" ) -> 🟢 Low Risk
A37: Foreclosure Rate | C37: Major | D37: 0.0047 | E37: =IFS(D37 < 0.005, 0, D37 < 0.01, 2, D37 < 0.02, 4, D37 < 0.03, 6, TRUE, 8) -> 0 | F37: =IFS( E37>=10, "🔴 High Risk", E37>=6, "🟠 Elevated Risk", E37>=3, "🟡 Moderate Risk", TRUE, "🟢 Low Risk" ) -> 🟢 Low Risk
A38: Business Loan Delinquencies | C38: Major | D38: 0.0128 | E38: =IFS(D38 < 0.01, 0, D38 < 0.015, 2, D38 < 0.02, 4, D38 < 0.03, 6, TRUE, 8) -> 2 | F38: =IFS( E38>=10, "🔴 High Risk", E38>=6, "🟠 Elevated Risk", E38>=3, "🟡 Moderate Risk", TRUE, "🟢 Low Risk" ) -> 🟢 Low Risk
A39: Delinquency Rate on All Loans | C39: Major | D39: 0.0147 | E39: =IFS(D39 < 0.015, 0, D39 < 0.025, 2, D39 < 0.04, 4, D39 < 0.06, 6, TRUE, 8) -> 0 | F39: =IFS( E39>=10, "🔴 High Risk", E39>=6, "🟠 Elevated Risk", E39>=3, "🟡 Moderate Risk", TRUE, "🟢 Low Risk" ) -> 🟢 Low Risk
A40: Credit Card Delinquencies | C40: Minor | D40: 0.0305 | E40: =IFS(D40 < 0.02, 0, D40 < 0.03, 1.5, D40 < 0.04, 3.25, D40 < 0.05, 5, TRUE, 6.25) -> 3.25 | F40: =IFS( E40>=10, "🔴 High Risk", E40>=6, "🟠 Elevated Risk", E40>=3, "🟡 Moderate Risk", TRUE, "🟢 Low Risk" ) -> 🟡 Moderate Risk
A41: Car Payment Defaults (subprime) | C41: Minor | D41: 0.063 | E41: =IFS(D41<3%, 0, D41<6%, 3, D41<10%, 6, TRUE, 9) -> 6 | F41: =IFS( E41>=10, "🔴 High Risk", E41>=6, "🟠 Elevated Risk", E41>=3, "🟡 Moderate Risk", TRUE, "🟢 Low Risk" ) -> 🟠 Elevated Risk
A42: Rental Vacancy Rate | C42: Minor | D42: 0.07 | E42: =IFS(D42 < 0.06, 0, D42 < 0.07, 1.5, D42 < 0.08, 3.25, D42 < 0.09, 5, TRUE, 6.25) -> 3.25 | F42: =IFS( E42>=10, "🔴 High Risk", E42>=6, "🟠 Elevated Risk", E42>=3, "🟡 Moderate Risk", TRUE, "🟢 Low Risk" ) -> 🟡 Moderate Risk
A43: Backdated Yield Curve (12 month) | C43: Critical | D43: 0.0007 | E43: =IFS(D43 > 0.01, 0, D43 > 0, 3, D43 > -0.5, 6, D43 > -1, 9, TRUE, 12) -> 3 | F43: =IFS( E43>=10, "🔴 High Risk", E43>=6, "🟠 Elevated Risk", E43>=3, "🟡 Moderate Risk", TRUE, "🟢 Low Risk" ) -> 🟡 Moderate Risk
A44: Job Openings (JOLTS) | C44: Major | D44: 7227000 | E44: =IFS(D44 > 9000000, 0, D44 > 7500000, 2, D44 > 6000000, 4, D44 > 5000000, 6, TRUE, 8) -> 4 | F44: =IFS( E44>=10, "🔴 High Risk", E44>=6, "🟠 Elevated Risk", E44>=3, "🟡 Moderate Risk", TRUE, "🟢 Low Risk" ) -> 🟡 Moderate Risk
A45: Unemployment (U6) | C45: Major | D45: 0.081 | E45: =IFS( D45 < 0.07, 0, D45 < 0.085, 3, D45 < 0.1, 6, TRUE, 9 ) -> 3 | F45: =IFS( E45>=10, "🔴 High Risk", E45>=6, "🟠 Elevated Risk", E45>=3, "🟡 Moderate Risk", TRUE, "🟢 Low Risk" ) -> 🟡 Moderate Risk
A46: Temporary Help Firing | C46: Minor | D46: 2499000 | E46: =IFS(D46 > 3000000, 0, D46 > 2900000, 1.5, D46 > 2750000, 3.25, D46 > 2600000, 5, TRUE, 6.25) -> 6.25 | F46: =IFS( E46>=10, "🔴 High Risk", E46>=6, "🟠 Elevated Risk", E46>=3, "🟡 Moderate Risk", TRUE, "🟢 Low Risk" ) -> 🟠 Elevated Risk
A48: To be added:
A49: Layoffs (https://fred.stlouisfed.org/series/JTSLDL)

Sheet HISTORY RAW
A1: date | B1: median home value

Sheet BIDEN 2021
A1: BIDEN Tracker | J1: HOUSING METRICS | P1: COST TRACKERS | T1: LAST UPDATED: 08/07/2025 09:22 AM EST
